Workbook

Sheet Scoring
A1: Updated: | B1: 46269 | C1: LEAGUE SETTINGS & SCORING INPUTS
A2: INPUT YOUR LEAGUE SCORING HERE | I2: LEAGUE & ROSTER SETTINGS
A3: Setting: | B3: Points: | C3: DESCRIPTION | I3: #TEAMS: | J3: QB: | K3: RB: | L3: WR: | M3: TE: | N3: FLEX: | O3: BENCH: | P3: SUPERFLEX:
A4: PASSING | I4: 10 | J4: 1 | K4: 2 | L4: 2 | M4: 1 | N4: 1 | O4: 6 | P4: 0
A5: PassINCMP | B5: 0 | C5: Points Per Pass Incompletion (Use a Negative, Default is 0) | I5: ADVANCED SETTINGS
A6: PassCMP | B6: 0 | C6: Points Per Pass Completion (Default is 0) | I6: Snake OR Auction | K6: Snake | L6: ESTIMATED KEEPER SAVINGS
A7: PassYDS | B7: 25 | C7: Passing Yards Per 1 Point (Default is 25) | I7: Budget: | K7: 200 | L7: Est. Total Saved (Auction Keepers) | P7: 0
A8: PassTDs | B8: 4 | C8: Points Per Passing Touchdown (Default is 4) | I8: In the Yellow Cell (Dropdown) Change from SNAKE to AUCTION if you want AUCTION Values.
A9: INTS | B9: -1 | C9: Points Per Interception (Use a Negative, Default is -2)
A10: SACKS | B10: 0 | C10: Points Per Sack (Use a Negative, Default is 0)
A11: RUSHING
A12: RushATT | B12: 0 | C12: Points Per Rush Attempt (Default is 0)
A13: RushYDS | B13: 10 | C13: Rushing Yards Per 1 Point (Default is 10)
A14: RushTDS | B14: 6 | C14: Points Per Rushing Touchdown (Default is 6)
A15: RECEIVING
A16: RB PPR | B16: 0.5 | C16: RB Points Per Reception (Examples: 0 , .5 , 1)
A17: WR PPR | B17: 0.5 | C17: WR Points Per Reception (Examples: 0 , .5 , 1)
A18: TE PPR | B18: 0.5 | C18: TE Points Per Reception (Examples: 0 , .5 , 1)
A19: RecYDS | B19: 10 | C19: Receiving Yards Per 1 Point (Default is 10)
A20: RecTDS | B20: 6 | C20: Points Per Receiving Touchdown (Default is 6)
A21: OTHER:
A22: FL | B22: -2 | C22: Points Per Fumble Lost (Use a Negative, Default is -2)
A23: Pass1D | B23: 0 | C23: Points Per Passing 1st Down (Default is 0)
A24: Rush1D | B24: 0 | C24: Points Per Rushing 1st Down (Default is 0)
A25: Rec1D | B25: 0 | C25: Points Per Receiving 1st Down (Default is 0)
A28: 🔒 CALCULATED VALUES BELOW — DO NOT EDIT (used internally for VBD/Auction math)
A29: QBs: | B29: PassCMP | C29: PassYDS | D29: PassTDs | E29: INTS | F29: RushATT | G29: RushYDS | H29: RushTDS | I29: FL | J29: Pass1D | K29: Rush1D
A30: POINTS | B30: =B6 -> 0 | C30: =B7 -> 25 | D30: =B8 -> 4 | E30: =B9 -> -1 | F30: =B12 -> 0 | G30: =B13 -> 10 | H30: =B14 -> 6 | I30: =B22 -> -2 | J30: =B23 -> 0 | K30: =B24 -> 0
A31: RBs: | B31: RushATT | C31: RushYDS | D31: RushTDS | E31: PPR | F31: RecYDS | G31: RecTDS | H31: FL | I31: Rush1D | J31: Rec1D
A32: POINTS | B32: =B12 -> 0 | C32: =B13 -> 10 | D32: =B14 -> 6 | E32: =B16 -> 0.5 | F32: =B19 -> 10 | G32: =B20 -> 6 | H32: =B22 -> -2 | I32: =B24 -> 0 | J32: =B25 -> 0
A33: WRs: | B33: PPR | C33: RecYDS | D33: RecTDS | E33: RushATT | F33: RushYDS | G33: RushTDS | H33: FL | I33: Rush1D | J33: Rec1D
A34: POINTS | B34: =B17 -> 0.5 | C34: =B19 -> 10 | D34: =B20 -> 6 | E34: =B12 -> 0 | F34: =B13 -> 10 | G34: =B14 -> 6 | H34: =B22 -> -2 | I34: =B24 -> 0 | J34: =B25 -> 0
A35: TEs: | B35: PPR | C35: RecYDS | D35: RecTDS | E35: FL | F35: Rec1D
A36: POINTS | B36: =B18 -> 0.5 | C36: =B19 -> 10 | D36: =B20 -> 6 | E36: =B22 -> -2 | F36: =B25 -> 0
A38: Baseline Calcs
A39: #TEAMS: | B39: QB: | C39: RB: | D39: WR: | E39: TE: | F39: FLEX:
A40: =I4 -> 10 | B40: =J4+P4 -> 1 | C40: =K4 -> 2 | D40: =L4 -> 2 | E40: =M4 -> 1 | F40: =N4+I38 -> 1
A41: Roster | B41: =(J4+P4)*I4 -> 10 | C41: =ROUND(K4*I4*1.267,0) -> 25 | D41: =ROUND(L4*I4*1.23,0) -> 25 | E41: =ROUND(M4*I4*1.2,0) -> 12 | F41: =ROUND(N4*I4*1.4,0) -> 14
A42: Flex: | B42: 0 | C42: =FLEX!E1 -> 6 | D42: =FLEX!G1 -> 8 | E42: =FLEX!I1 -> 0
A43: Baselines: | B43: =ROUND(B41*1.17,) -> 12 | C43: =C41+C42 -> 31 | D43: =D41+D42 -> 33 | E43: =E41+E42 -> 12
A44: Total Dollars: | B44: =K7*I4+P7 -> 2000
A45: Total Roster: | B45: =SUM(J4:P4)*I4 -> 130
A46: Premium: | B46: =B44-B45 -> 1870
A47: Total VOR: | B47: =SUM(Aggregate!J1+Aggregate!X1+Aggregate!AL1+Aggregate!AZ1) -> 3621.4607
A48: Premium/VOR: | B48: =B46/B47 -> #VALUE!

Sheet DraftSheet
B1: ="DRAFTSHEET - "&Scoring!I4&" Team - "&Scoring!B17&" PPR - "&Scoring!J4&"QB("&Aggregate!B1&") / "&Scoring!K4&"RB("&Aggregate!P1&") / "&Scoring!L4&"WR("&Aggregate!AD1&") / "&Scoring!M4&"TE("&Aggregate!AR1&") / "&Scoring!N4&"[RB/WR/TE]" -> DRAFTSHEET - 10 Team - 0.5 PPR - 1QB(12) / 2RB(31) / 2WR(33) / 1TE(12) / 1[RB/WR/TE] | AF1: PLAYER SEARCH
B2: ="Passing: "&Scoring!B8&" PPTD, "&ROUND(1/Scoring!B7,2)&" PPY, "&Scoring!B9&" Int | Rushing: "&Scoring!B14&" PPTD, "&ROUND(1/Scoring!B13,2)&" PPY | Receiving: "&Scoring!B20&" PPTD, "&ROUND(1/Scoring!B19,2)&" PPY, "&Scoring!B17&" PPR | Draft: use 'x' if drafted by someone else, 'o' if drafted by you | Updated: "&TEXT(TODAY(),"yyyy-mm-dd") -> Passing: 4 PPTD, 0.04 PPY, -1 Int | Rushing: 6 PPTD, 0.1 PPY | Receiving: 6 PPTD, 0.1 PPY, 0.5 PPR | Draft: use 'x' if drafted by someone else, 'o' if drafted by you | Updated: 2026-09-05 | AF2: TYPE NAME HERE: | AH2: =IF($AG$2="","",IFERROR(MATCH("*"&$AG$2&"*",C5:C44,0)+4,""))
B3: QUARTERBACK | L3: RUNNING BACK | V3: WIDE RECEIVER | AF3: Position: | AG3: =IF($AG$2="","",IF(AH2<>"","QB",IF(AH3<>"","RB",IF(AH4<>"","WR",IF(AH5<>"","TE","Not Found"))))) | AH3: =IF($AG$2="","",IFERROR(MATCH("*"&$AG$2&"*",M5:M84,0)+4,""))
B4: TIER | C4: NAME | D4: TM/BYE | E4: PTS | F4: VALUE | G4: PS | H4: ECR | I4: DRAFT | L4: TIER | M4: NAME | N4: TM/BYE | O4: PTS | P4: VALUE | Q4: PS | R4: ECR | S4: DRAFT | V4: TIER | W4: NAME | X4: TM/BYE | Y4: PTS | Z4: VALUE | AA4: PS | AB4: ECR | AC4: DRAFT | AF4: Tier: | AG4: =IF($AG$2="","",IF(AH2<>"",INDEX(B:B,AH2),IF(AH3<>"",INDEX(L:L,AH3),IF(AH4<>"",INDEX(V:V,AH4),IF(AH5<>"",INDEX(B:B,AH5),""))))) | AH4: =IF($AG$2="","",IFERROR(MATCH("*"&$AG$2&"*",W5:W84,0)+4,""))
B5: =IFERROR(VLOOKUP(Table9[[#This Row],[NAME]],Aggregate!$B:$M,11,FALSE()),"") -> 1 | C5: =Aggregate!B3 -> Josh Allen | D5: =VLOOKUP(Table9[[#This Row],[NAME]],Aggregate!B:M,4,FALSE()) -> BUF/7 | E5: =IFERROR(VLOOKUP(Table9[[#This Row],[NAME]],Aggregate!$B:$M,8,FALSE()),"") -> 324.97794 | F5: =IF(Scoring!$K$6="Auction",IFERROR(VLOOKUP(Table9[[#This Row],[NAME]],Aggregate!$B:$M,10,FALSE()),""),IFERROR(VLOOKUP(Table9[[#This Row],[NAME]],Aggregate!$B:$M,9,FALSE()),"")) -> 56.598576 | G5: =SUMIFS(J6:$J$44,I6:$I$44,"<>x",I6:$I$44,"<>o",J6:$J$44,">0")/Aggregate!$J$1 -> 0.59269413 | H5: =VLOOKUP(Table9[[#This Row],[NAME]],ECR!C:E,3,FALSE()) -> QB1 | J5: =VLOOKUP(C5,Aggregate!B:J,9,FALSE()) -> 56.598576 | L5: =IFERROR(VLOOKUP(Table10[[#This Row],[NAME]],Aggregate!$P:$AA,11,FALSE()),"") -> 1 | M5: =Aggregate!P3 -> Jahmyr Gibbs | N5: =VLOOKUP(Table10[[#This Row],[NAME]],Aggregate!P:AA,4,FALSE()) -> DET/6 | O5: =IFERROR(VLOOKUP(Table10[[#This Row],[NAME]],Aggregate!$P:$AA,8,FALSE()),"") -> 291.35319 | P5: =IF(Scoring!$K$6="Auction",IFERROR(VLOOKUP(Table10[[#This Row],[NAME]],Aggregate!$P:$AA,10,FALSE()),""),IFERROR(VLOOKUP(Table10[[#This Row],[NAME]],Aggregate!$P:$AA,9,FALSE()),"")) -> 163.80745 | Q5: =SUMIFS(T6:$T$84,S6:$S$84,"<>x",S6:$S$84,"<>o",T6:$T$84,">0")/Aggregate!$X$1 -> 0.91151838 | R5: =VLOOKUP(Table10[[#This Row],[NAME]],ECR!C:E,3,FALSE()) -> RB1 | T5: =VLOOKUP(M5,Aggregate!P:X,9,FALSE()) -> 163.80745 | V5: =IFERROR(VLOOKUP(Table11[[#This Row],[NAME]],Aggregate!$AD:$AO,11,FALSE()),"") -> 1 | W5: =Aggregate!AD4 -> Puka Nacua | X5: =VLOOKUP(Table11[[#This Row],[NAME]],Aggregate!AD:AO,4,FALSE()) -> LAR/11 | Y5: =IFERROR(VLOOKUP(Table11[[#This Row],[NAME]],Aggregate!$AD:$AO,8,FALSE()),"") -> 248.43324 | Z5: =IF(Scoring!$K$6="Auction",IFERROR(VLOOKUP(Table11[[#This Row],[NAME]],Aggregate!$AD:$AO,10,FALSE()),""),IFERROR(VLOOKUP(Table11[[#This Row],[NAME]],Aggregate!$AD:$AO,9,FALSE()),"")) -> 122.75536 | AA5: =SUMIFS(AD6:$AD$84,AC6:$AC$84,"<>x",AC6:$AC$84,"<>o",AD6:$AD$84,">0")/Aggregate!$AL$1 -> 0.91194216 | AB5: =VLOOKUP(Table11[[#This Row],[NAME]],ECR!C:E,3,FALSE()) -> WR2 | AD5: =VLOOKUP(W5,Aggregate!AD:AL,9,FALSE()) -> 122.75536 | AF5: Name: | AG5: =IF($AG$2="","",IF(AH2<>"",INDEX(C:C,AH2),IF(AH3<>"",INDEX(M:M,AH3),IF(AH4<>"",INDEX(W:W,AH4),IF(AH5<>"",INDEX(C:C,AH5),""))))) | AH5: =IF($AG$2="","",IFERROR(MATCH("*"&$AG$2&"*",C48:C84,0)+47,""))
B6: =IFERROR(VLOOKUP(Table9[[#This Row],[NAME]],Aggregate!$B:$M,11,FALSE()),"") -> 2 | C6: =Aggregate!B4 -> Lamar Jackson | D6: =VLOOKUP(Table9[[#This Row],[NAME]],Aggregate!B:M,4,FALSE()) -> BAL/13 | E6: =IFERROR(VLOOKUP(Table9[[#This Row],[NAME]],Aggregate!$B:$M,8,FALSE()),"") -> 286.78631 | F6: =IF(Scoring!$K$6="Auction",IFERROR(VLOOKUP(Table9[[#This Row],[NAME]],Aggregate!$B:$M,10,FALSE()),""),IFERROR(VLOOKUP(Table9[[#This Row],[NAME]],Aggregate!$B:$M,9,FALSE()),"")) -> 18.406947 | G6: =SUMIFS(J7:$J$44,I7:$I$44,"<>x",I7:$I$44,"<>o",J7:$J$44,">0")/Aggregate!$J$1 -> 0.46023042 | H6: =VLOOKUP(Table9[[#This Row],[NAME]],ECR!C:E,3,FALSE()) -> QB2 | J6: =VLOOKUP(C6,Aggregate!B:J,9,FALSE()) -> 18.406947 | L6: =IFERROR(VLOOKUP(Table10[[#This Row],[NAME]],Aggregate!$P:$AA,11,FALSE()),"") -> 1 | M6: =Aggregate!P4 -> Bijan Robinson | N6: =VLOOKUP(Table10[[#This Row],[NAME]],Aggregate!P:AA,4,FALSE()) -> ATL/11 | O6: =IFERROR(VLOOKUP(Table10[[#This Row],[NAME]],Aggregate!$P:$AA,8,FALSE()),"") -> 270.34108 | P6: =IF(Scoring!$K$6="Auction",IFERROR(VLOOKUP(Table10[[#This Row],[NAME]],Aggregate!$P:$AA,10,FALSE()),""),IFERROR(VLOOKUP(Table10[[#This Row],[NAME]],Aggregate!$P:$AA,9,FALSE()),"")) -> 142.79534 | Q6: =SUMIFS(T7:$T$84,S7:$S$84,"<>x",S7:$S$84,"<>o",T7:$T$84,">0")/Aggregate!$X$1 -> 0.83438658 | R6: =VLOOKUP(Table10[[#This Row],[NAME]],ECR!C:E,3,FALSE()) -> RB2 | T6: =VLOOKUP(M6,Aggregate!P:X,9,FALSE()) -> 142.79534 | V6: =IFERROR(VLOOKUP(Table11[[#This Row],[NAME]],Aggregate!$AD:$AO,11,FALSE()),"") -> 1 | W6: =Aggregate!AD3 -> Ja'Marr Chase | X6: =VLOOKUP(Table11[[#This Row],[NAME]],Aggregate!AD:AO,4,FALSE()) -> CIN/6 | Y6: =IFERROR(VLOOKUP(Table11[[#This Row],[NAME]],Aggregate!$AD:$AO,8,FALSE()),"") -> 246.79195 | Z6: =IF(Scoring!$K$6="Auction",IFERROR(VLOOKUP(Table11[[#This Row],[NAME]],Aggregate!$AD:$AO,10,FALSE()),""),IFERROR(VLOOKUP(Table11[[#This Row],[NAME]],Aggregate!$AD:$AO,9,FALSE()),"")) -> 121.11407 | AA6: =SUMIFS(AD7:$AD$84,AC7:$AC$84,"<>x",AC7:$AC$84,"<>o",AD7:$AD$84,">0")/Aggregate!$AL$1 -> 0.8250617 | AB6: =VLOOKUP(Table11[[#This Row],[NAME]],ECR!C:E,3,FALSE()) -> WR1 | AD6: =VLOOKUP(W6,Aggregate!AD:AL,9,FALSE()) -> 121.11407 | AF6: TM/BYE: | AG6: =IF($AG$2="","",IF(AH2<>"",INDEX(D:D,AH2),IF(AH3<>"",INDEX(N:N,AH3),IF(AH4<>"",INDEX(X:X,AH4),IF(AH5<>"",INDEX(D:D,AH5),"")))))
B7: =IFERROR(VLOOKUP(Table9[[#This Row],[NAME]],Aggregate!$B:$M,11,FALSE()),"") -> 2 | C7: =Aggregate!B7 -> Jalen Hurts | D7: =VLOOKUP(Table9[[#This Row],[NAME]],Aggregate!B:M,4,FALSE()) -> PHI/10 | E7: =IFERROR(VLOOKUP(Table9[[#This Row],[NAME]],Aggregate!$B:$M,8,FALSE()),"") -> 284.31265 | F7: =IF(Scoring!$K$6="Auction",IFERROR(VLOOKUP(Table9[[#This Row],[NAME]],Aggregate!$B:$M,10,FALSE()),""),IFERROR(VLOOKUP(Table9[[#This Row],[NAME]],Aggregate!$B:$M,9,FALSE()),"")) -> 15.933283 | G7: =SUMIFS(J8:$J$44,I8:$I$44,"<>x",I8:$I$44,"<>o",J8:$J$44,">0")/Aggregate!$J$1 -> 0.34556818 | H7: =VLOOKUP(Table9[[#This Row],[NAME]],ECR!C:E,3,FALSE()) -> QB5 | J7: =VLOOKUP(C7,Aggregate!B:J,9,FALSE()) -> 15.933283 | L7: =IFERROR(VLOOKUP(Table10[[#This Row],[NAME]],Aggregate!$P:$AA,11,FALSE()),"") -> 2 | M7: =Aggregate!P5 -> Jonathan Taylor | N7: =VLOOKUP(Table10[[#This Row],[NAME]],Aggregate!P:AA,4,FALSE()) -> IND/13 | O7: =IFERROR(VLOOKUP(Table10[[#This Row],[NAME]],Aggregate!$P:$AA,8,FALSE()),"") -> 249.19215 | P7: =IF(Scoring!$K$6="Auction",IFERROR(VLOOKUP(Table10[[#This Row],[NAME]],Aggregate!$P:$AA,10,FALSE()),""),IFERROR(VLOOKUP(Table10[[#This Row],[NAME]],Aggregate!$P:$AA,9,FALSE()),"")) -> 121.64642 | Q7: =SUMIFS(T8:$T$84,S8:$S$84,"<>x",S8:$S$84,"<>o",T8:$T$84,">0")/Aggregate!$X$1 -> 0.7686785 | R7: =VLOOKUP(Table10[[#This Row],[NAME]],ECR!C:E,3,FALSE()) -> RB3 | T7: =VLOOKUP(M7,Aggregate!P:X,9,FALSE()) -> 121.64642 | V7: =IFERROR(VLOOKUP(Table11[[#This Row],[NAME]],Aggregate!$AD:$AO,11,FALSE()),"") -> 1 | W7: =Aggregate!AD5 -> Jaxon Smith-Njigba | X7: =VLOOKUP(Table11[[#This Row],[NAME]],Aggregate!AD:AO,4,FALSE()) -> SEA/11 | Y7: =IFERROR(VLOOKUP(Table11[[#This Row],[NAME]],Aggregate!$AD:$AO,8,FALSE()),"") -> 240.06534 | Z7: =IF(Scoring!$K$6="Auction",IFERROR(VLOOKUP(Table11[[#This Row],[NAME]],Aggregate!$AD:$AO,10,FALSE()),""),IFERROR(VLOOKUP(Table11[[#This Row],[NAME]],Aggregate!$AD:$AO,9,FALSE()),"")) -> 114.38746 | AA7: =SUMIFS(AD8:$AD$84,AC8:$AC$84,"<>x",AC8:$AC$84,"<>o",AD8:$AD$84,">0")/Aggregate!$AL$1 -> 0.74300653 | AB7: =VLOOKUP(Table11[[#This Row],[NAME]],ECR!C:E,3,FALSE()) -> WR3 | AD7: =VLOOKUP(W7,Aggregate!AD:AL,9,FALSE()) -> 114.38746 | AF7: PTS: | AG7: =IF($AG$2="","",IF(AH2<>"",INDEX(E:E,AH2),IF(AH3<>"",INDEX(O:O,AH3),IF(AH4<>"",INDEX(Y:Y,AH4),IF(AH5<>"",INDEX(E:E,AH5),"")))))
B8: =IFERROR(VLOOKUP(Table9[[#This Row],[NAME]],Aggregate!$B:$M,11,FALSE()),"") -> 3 | C8: =Aggregate!B5 -> Drake Maye | D8: =VLOOKUP(Table9[[#This Row],[NAME]],Aggregate!B:M,4,FALSE()) -> NE/11 | E8: =IFERROR(VLOOKUP(Table9[[#This Row],[NAME]],Aggregate!$B:$M,8,FALSE()),"") -> 282.82321 | F8: =IF(Scoring!$K$6="Auction",IFERROR(VLOOKUP(Table9[[#This Row],[NAME]],Aggregate!$B:$M,10,FALSE()),""),IFERROR(VLOOKUP(Table9[[#This Row],[NAME]],Aggregate!$B:$M,9,FALSE()),"")) -> 14.443841 | G8: =SUMIFS(J9:$J$44,I9:$I$44,"<>x",I9:$I$44,"<>o",J9:$J$44,">0")/Aggregate!$J$1 -> 0.24162456 | H8: =VLOOKUP(Table9[[#This Row],[NAME]],ECR!C:E,3,FALSE()) -> QB3 | J8: =VLOOKUP(C8,Aggregate!B:J,9,FALSE()) -> 14.443841 | L8: =IFERROR(VLOOKUP(Table10[[#This Row],[NAME]],Aggregate!$P:$AA,11,FALSE()),"") -> 2 | M8: =Aggregate!P6 -> Christian McCaffrey | N8: =VLOOKUP(Table10[[#This Row],[NAME]],Aggregate!P:AA,4,FALSE()) -> SF/8 | O8: =IFERROR(VLOOKUP(Table10[[#This Row],[NAME]],Aggregate!$P:$AA,8,FALSE()),"") -> 248.89741 | P8: =IF(Scoring!$K$6="Auction",IFERROR(VLOOKUP(Table10[[#This Row],[NAME]],Aggregate!$P:$AA,10,FALSE()),""),IFERROR(VLOOKUP(Table10[[#This Row],[NAME]],Aggregate!$P:$AA,9,FALSE()),"")) -> 121.35168 | Q8: =SUMIFS(T9:$T$84,S9:$S$84,"<>x",S9:$S$84,"<>o",T9:$T$84,">0")/Aggregate!$X$1 -> 0.70312963 | R8: =VLOOKUP(Table10[[#This Row],[NAME]],ECR!C:E,3,FALSE()) -> RB4 | T8: =VLOOKUP(M8,Aggregate!P:X,9,FALSE()) -> 121.35168 | V8: =IFERROR(VLOOKUP(Table11[[#This Row],[NAME]],Aggregate!$AD:$AO,11,FALSE()),"") -> 2 | W8: =Aggregate!AD6 -> Amon-Ra St. Brown | X8: =VLOOKUP(Table11[[#This Row],[NAME]],Aggregate!AD:AO,4,FALSE()) -> DET/6 | Y8: =IFERROR(VLOOKUP(Table11[[#This Row],[NAME]],Aggregate!$AD:$AO,8,FALSE()),"") -> 230.24461 | Z8: =IF(Scoring!$K$6="Auction",IFERROR(VLOOKUP(Table11[[#This Row],[NAME]],Aggregate!$AD:$AO,10,FALSE()),""),IFERROR(VLOOKUP(Table11[[#This Row],[NAME]],Aggregate!$AD:$AO,9,FALSE()),"")) -> 104.56673 | AA8: =SUMIFS(AD9:$AD$84,AC9:$AC$84,"<>x",AC9:$AC$84,"<>o",AD9:$AD$84,">0")/Aggregate!$AL$1 -> 0.6679962 | AB8: =VLOOKUP(Table11[[#This Row],[NAME]],ECR!C:E,3,FALSE()) -> WR4 | AD8: =VLOOKUP(W8,Aggregate!AD:AL,9,FALSE()) -> 104.56673 | AF8: VALUE: | AG8: =IF($AG$2="","",IF(AH2<>"",INDEX(F:F,AH2),IF(AH3<>"",INDEX(P:P,AH3),IF(AH4<>"",INDEX(Z:Z,AH4),IF(AH5<>"",INDEX(F:F,AH5),"")))))
B9: =IFERROR(VLOOKUP(Table9[[#This Row],[NAME]],Aggregate!$B:$M,11,FALSE()),"") -> 3 | C9: =Aggregate!B8 -> Jayden Daniels | D9: =VLOOKUP(Table9[[#This Row],[NAME]],Aggregate!B:M,4,FALSE()) -> WAS/7 | E9: =IFERROR(VLOOKUP(Table9[[#This Row],[NAME]],Aggregate!$B:$M,8,FALSE()),"") -> 282.1602 | F9: =IF(Scoring!$K$6="Auction",IFERROR(VLOOKUP(Table9[[#This Row],[NAME]],Aggregate!$B:$M,10,FALSE()),""),IFERROR(VLOOKUP(Table9[[#This Row],[NAME]],Aggregate!$B:$M,9,FALSE()),"")) -> 13.780832 | G9: =SUMIFS(J10:$J$44,I10:$I$44,"<>x",I10:$I$44,"<>o",J10:$J$44,">0")/Aggregate!$J$1 -> 0.14245221 | H9: =VLOOKUP(Table9[[#This Row],[NAME]],ECR!C:E,3,FALSE()) -> QB6 | J9: =VLOOKUP(C9,Aggregate!B:J,9,FALSE()) -> 13.780832 | L9: =IFERROR(VLOOKUP(Table10[[#This Row],[NAME]],Aggregate!$P:$AA,11,FALSE()),"") -> 3 | M9: =Aggregate!P7 -> James Cook III | N9: =VLOOKUP(Table10[[#This Row],[NAME]],Aggregate!P:AA,4,FALSE()) -> BUF/7 | O9: =IFERROR(VLOOKUP(Table10[[#This Row],[NAME]],Aggregate!$P:$AA,8,FALSE()),"") -> 218.4356 | P9: =IF(Scoring!$K$6="Auction",IFERROR(VLOOKUP(Table10[[#This Row],[NAME]],Aggregate!$P:$AA,10,FALSE()),""),IFERROR(VLOOKUP(Table10[[#This Row],[NAME]],Aggregate!$P:$AA,9,FALSE()),"")) -> 90.889864 | Q9: =SUMIFS(T10:$T$84,S10:$S$84,"<>x",S10:$S$84,"<>o",T10:$T$84,">0")/Aggregate!$X$1 -> 0.6540349 | R9: =VLOOKUP(Table10[[#This Row],[NAME]],ECR!C:E,3,FALSE()) -> RB5 | T9: =VLOOKUP(M9,Aggregate!P:X,9,FALSE()) -> 90.889864 | V9: =IFERROR(VLOOKUP(Table11[[#This Row],[NAME]],Aggregate!$AD:$AO,11,FALSE()),"") -> 3 | W9: =Aggregate!AD8 -> Justin Jefferson | X9: =VLOOKUP(Table11[[#This Row],[NAME]],Aggregate!AD:AO,4,FALSE()) -> MIN/6 | Y9: =IFERROR(VLOOKUP(Table11[[#This Row],[NAME]],Aggregate!$AD:$AO,8,FALSE()),"") -> 195.85264 | Z9: =IF(Scoring!$K$6="Auction",IFERROR(VLOOKUP(Table11[[#This Row],[NAME]],Aggregate!$AD:$AO,10,FALSE()),""),IFERROR(VLOOKUP(Table11[[#This Row],[NAME]],Aggregate!$AD:$AO,9,FALSE()),"")) -> 70.174765 | AA9: =SUMIFS(AD10:$AD$84,AC10:$AC$84,"<>x",AC10:$AC$84,"<>o",AD10:$AD$84,">0")/Aggregate!$AL$1 -> 0.61765674 | AB9: =VLOOKUP(Table11[[#This Row],[NAME]],ECR!C:E,3,FALSE()) -> WR6 | AD9: =VLOOKUP(W9,Aggregate!AD:AL,9,FALSE()) -> 70.174765 | AF9: PS: | AG9: =IF($AG$2="","",IF(AH2<>"",INDEX(G:G,AH2),IF(AH3<>"",INDEX(Q:Q,AH3),IF(AH4<>"",INDEX(AA:AA,AH4),IF(AH5<>"",INDEX(G:G,AH5),"")))))
B10: =IFERROR(VLOOKUP(Table9[[#This Row],[NAME]],Aggregate!$B:$M,11,FALSE()),"") -> 4 | C10: =Aggregate!B6 -> Joe Burrow | D10: =VLOOKUP(Table9[[#This Row],[NAME]],Aggregate!B:M,4,FALSE()) -> CIN/6 | E10: =IFERROR(VLOOKUP(Table9[[#This Row],[NAME]],Aggregate!$B:$M,8,FALSE()),"") -> 278.52258 | F10: =IF(Scoring!$K$6="Auction",IFERROR(VLOOKUP(Table9[[#This Row],[NAME]],Aggregate!$B:$M,10,FALSE()),""),IFERROR(VLOOKUP(Table9[[#This Row],[NAME]],Aggregate!$B:$M,9,FALSE()),"")) -> 10.143214 | G10: =SUMIFS(J11:$J$44,I11:$I$44,"<>x",I11:$I$44,"<>o",J11:$J$44,">0")/Aggregate!$J$1 -> 0.069457609 | H10: =VLOOKUP(Table9[[#This Row],[NAME]],ECR!C:E,3,FALSE()) -> QB4 | J10: =VLOOKUP(C10,Aggregate!B:J,9,FALSE()) -> 10.143214 | L10: =IFERROR(VLOOKUP(Table10[[#This Row],[NAME]],Aggregate!$P:$AA,11,FALSE()),"") -> 3 | M10: =Aggregate!P10 -> De'Von Achane | N10: =VLOOKUP(Table10[[#This Row],[NAME]],Aggregate!P:AA,4,FALSE()) -> MIA/6 | O10: =IFERROR(VLOOKUP(Table10[[#This Row],[NAME]],Aggregate!$P:$AA,8,FALSE()),"") -> 218.14299 | P10: =IF(Scoring!$K$6="Auction",IFERROR(VLOOKUP(Table10[[#This Row],[NAME]],Aggregate!$P:$AA,10,FALSE()),""),IFERROR(VLOOKUP(Table10[[#This Row],[NAME]],Aggregate!$P:$AA,9,FALSE()),"")) -> 90.597251 | Q10: =SUMIFS(T11:$T$84,S11:$S$84,"<>x",S11:$S$84,"<>o",T11:$T$84,">0")/Aggregate!$X$1 -> 0.60509823 | R10: =VLOOKUP(Table10[[#This Row],[NAME]],ECR!C:E,3,FALSE()) -> RB8 | T10: =VLOOKUP(M10,Aggregate!P:X,9,FALSE()) -> 90.597251 | V10: =IFERROR(VLOOKUP(Table11[[#This Row],[NAME]],Aggregate!$AD:$AO,11,FALSE()),"") -> 3 | W10: =Aggregate!AD7 -> CeeDee Lamb | X10: =VLOOKUP(Table11[[#This Row],[NAME]],Aggregate!AD:AO,4,FALSE()) -> DAL/14 | Y10: =IFERROR(VLOOKUP(Table11[[#This Row],[NAME]],Aggregate!$AD:$AO,8,FALSE()),"") -> 195.04431 | Z10: =IF(Scoring!$K$6="Auction",IFERROR(VLOOKUP(Table11[[#This Row],[NAME]],Aggregate!$AD:$AO,10,FALSE()),""),IFERROR(VLOOKUP(Table11[[#This Row],[NAME]],Aggregate!$AD:$AO,9,FALSE()),"")) -> 69.366434 | AA10: =SUMIFS(AD11:$AD$84,AC11:$AC$84,"<>x",AC11:$AC$84,"<>o",AD11:$AD$84,">0")/Aggregate!$AL$1 -> 0.56789714 | AB10: =VLOOKUP(Table11[[#This Row],[NAME]],ECR!C:E,3,FALSE()) -> WR5 | AD10: =VLOOKUP(W10,Aggregate!AD:AL,9,FALSE()) -> 69.366434 | AF10: ECR: | AG10: =IF($AG$2="","",IF(AH2<>"",INDEX(H:H,AH2),IF(AH3<>"",INDEX(R:R,AH3),IF(AH4<>"",INDEX(AB:AB,AH4),IF(AH5<>"",INDEX(H:H,AH5),"")))))
B11: =IFERROR(VLOOKUP(Table9[[#This Row],[NAME]],Aggregate!$B:$M,11,FALSE()),"") -> 5 | C11: =Aggregate!B11 -> Trevor Lawrence | D11: =VLOOKUP(Table9[[#This Row],[NAME]],Aggregate!B:M,4,FALSE()) -> JAC/7 | E11: =IFERROR(VLOOKUP(Table9[[#This Row],[NAME]],Aggregate!$B:$M,8,FALSE()),"") -> 272.07268 | F11: =IF(Scoring!$K$6="Auction",IFERROR(VLOOKUP(Table9[[#This Row],[NAME]],Aggregate!$B:$M,10,FALSE()),""),IFERROR(VLOOKUP(Table9[[#This Row],[NAME]],Aggregate!$B:$M,9,FALSE()),"")) -> 3.6933111 | G11: =SUMIFS(J12:$J$44,I12:$I$44,"<>x",I12:$I$44,"<>o",J12:$J$44,">0")/Aggregate!$J$1 -> 0.042879073 | H11: =VLOOKUP(Table9[[#This Row],[NAME]],ECR!C:E,3,FALSE()) -> QB9 | J11: =VLOOKUP(C11,Aggregate!B:J,9,FALSE()) -> 3.6933111 | L11: =IFERROR(VLOOKUP(Table10[[#This Row],[NAME]],Aggregate!$P:$AA,11,FALSE()),"") -> 3 | M11: =Aggregate!P13 -> Derrick Henry | N11: =VLOOKUP(Table10[[#This Row],[NAME]],Aggregate!P:AA,4,FALSE()) -> BAL/13 | O11: =IFERROR(VLOOKUP(Table10[[#This Row],[NAME]],Aggregate!$P:$AA,8,FALSE()),"") -> 215.59352 | P11: =IF(Scoring!$K$6="Auction",IFERROR(VLOOKUP(Table10[[#This Row],[NAME]],Aggregate!$P:$AA,10,FALSE()),""),IFERROR(VLOOKUP(Table10[[#This Row],[NAME]],Aggregate!$P:$AA,9,FALSE()),"")) -> 88.04778 | Q11: =SUMIFS(T12:$T$84,S12:$S$84,"<>x",S12:$S$84,"<>o",T12:$T$84,">0")/Aggregate!$X$1 -> 0.55753867 | R11: =VLOOKUP(Table10[[#This Row],[NAME]],ECR!C:E,3,FALSE()) -> RB11 | T11: =VLOOKUP(M11,Aggregate!P:X,9,FALSE()) -> 88.04778 | V11: =IFERROR(VLOOKUP(Table11[[#This Row],[NAME]],Aggregate!$AD:$AO,11,FALSE()),"") -> 3 | W11: =Aggregate!AD10 -> Drake London | X11: =VLOOKUP(Table11[[#This Row],[NAME]],Aggregate!AD:AO,4,FALSE()) -> ATL/11 | Y11: =IFERROR(VLOOKUP(Table11[[#This Row],[NAME]],Aggregate!$AD:$AO,8,FALSE()),"") -> 190.37802 | Z11: =IF(Scoring!$K$6="Auction",IFERROR(VLOOKUP(Table11[[#This Row],[NAME]],Aggregate!$AD:$AO,10,FALSE()),""),IFERROR(VLOOKUP(Table11[[#This Row],[NAME]],Aggregate!$AD:$AO,9,FALSE()),"")) -> 64.700141 | AA11: =SUMIFS(AD12:$AD$84,AC12:$AC$84,"<>x",AC12:$AC$84,"<>o",AD12:$AD$84,">0")/Aggregate!$AL$1 -> 0.52148488 | AB11: =VLOOKUP(Table11[[#This Row],[NAME]],ECR!C:E,3,FALSE()) -> WR8 | AD11: =VLOOKUP(W11,Aggregate!AD:AL,9,FALSE()) -> 64.700141 | AF11: Drafted?: | AG11: =IF($AG$2="","",IF(AH2<>"",IF(INDEX(I:I,AH2)="","Available",INDEX(I:I,AH2)),IF(AH3<>"",IF(INDEX(S:S,AH3)="","Available",INDEX(S:S,AH3)),IF(AH4<>"",IF(INDEX(AC:AC,AH4)="","Available",INDEX(AC:AC,AH4)),IF(AH5<>"",IF(INDEX(I:I,AH5)="","Available",INDEX(I:I,AH5)),"")))))
B12: =IFERROR(VLOOKUP(Table9[[#This Row],[NAME]],Aggregate!$B:$M,11,FALSE()),"") -> 5 | C12: =Aggregate!B12 -> Dak Prescott | D12: =VLOOKUP(Table9[[#This Row],[NAME]],Aggregate!B:M,4,FALSE()) -> DAL/14 | E12: =IFERROR(VLOOKUP(Table9[[#This Row],[NAME]],Aggregate!$B:$M,8,FALSE()),"") -> 270.40003 | F12: =IF(Scoring!$K$6="Auction",IFERROR(VLOOKUP(Table9[[#This Row],[NAME]],Aggregate!$B:$M,10,FALSE()),""),IFERROR(VLOOKUP(Table9[[#This Row],[NAME]],Aggregate!$B:$M,9,FALSE()),"")) -> 2.0206634 | G12: =SUMIFS(J13:$J$44,I13:$I$44,"<>x",I13:$I$44,"<>o",J13:$J$44,">0")/Aggregate!$J$1 -> 0.028337576 | H12: =VLOOKUP(Table9[[#This Row],[NAME]],ECR!C:E,3,FALSE()) -> QB10 | J12: =VLOOKUP(C12,Aggregate!B:J,9,FALSE()) -> 2.0206634 | L12: =IFERROR(VLOOKUP(Table10[[#This Row],[NAME]],Aggregate!$P:$AA,11,FALSE()),"") -> 3 | M12: =Aggregate!P8 -> Chase Brown | N12: =VLOOKUP(Table10[[#This Row],[NAME]],Aggregate!P:AA,4,FALSE()) -> CIN/6 | O12: =IFERROR(VLOOKUP(Table10[[#This Row],[NAME]],Aggregate!$P:$AA,8,FALSE()),"") -> 213.43189 | P12: =IF(Scoring!$K$6="Auction",IFERROR(VLOOKUP(Table10[[#This Row],[NAME]],Aggregate!$P:$AA,10,FALSE()),""),IFERROR(VLOOKUP(Table10[[#This Row],[NAME]],Aggregate!$P:$AA,9,FALSE()),"")) -> 85.88615 | Q12: =SUMIFS(T13:$T$84,S13:$S$84,"<>x",S13:$S$84,"<>o",T13:$T$84,">0")/Aggregate!$X$1 -> 0.51114673 | R12: =VLOOKUP(Table10[[#This Row],[NAME]],ECR!C:E,3,FALSE()) -> RB6 | T12: =VLOOKUP(M12,Aggregate!P:X,9,FALSE()) -> 85.88615 | V12: =IFERROR(VLOOKUP(Table11[[#This Row],[NAME]],Aggregate!$AD:$AO,11,FALSE()),"") -> 3 | W12: =Aggregate!AD9 -> A.J. Brown | X12: =VLOOKUP(Table11[[#This Row],[NAME]],Aggregate!AD:AO,4,FALSE()) -> NE/11 | Y12: =IFERROR(VLOOKUP(Table11[[#This Row],[NAME]],Aggregate!$AD:$AO,8,FALSE()),"") -> 188.45387 | Z12: =IF(Scoring!$K$6="Auction",IFERROR(VLOOKUP(Table11[[#This Row],[NAME]],Aggregate!$AD:$AO,10,FALSE()),""),IFERROR(VLOOKUP(Table11[[#This Row],[NAME]],Aggregate!$AD:$AO,9,FALSE()),"")) -> 62.775988 | AA12: =SUMIFS(AD13:$AD$84,AC13:$AC$84,"<>x",AC13:$AC$84,"<>o",AD13:$AD$84,">0")/Aggregate!$AL$1 -> 0.47645289 | AB12: =VLOOKUP(Table11[[#This Row],[NAME]],ECR!C:E,3,FALSE()) -> WR7 | AD12: =VLOOKUP(W12,Aggregate!AD:AL,9,FALSE()) -> 62.775988
B13: =IFERROR(VLOOKUP(Table9[[#This Row],[NAME]],Aggregate!$B:$M,11,FALSE()),"") -> 5 | C13: =Aggregate!B15 -> Jaxson Dart | D13: =VLOOKUP(Table9[[#This Row],[NAME]],Aggregate!B:M,4,FALSE()) -> NYG/8 | E13: =IFERROR(VLOOKUP(Table9[[#This Row],[NAME]],Aggregate!$B:$M,8,FALSE()),"") -> 269.87614 | F13: =IF(Scoring!$K$6="Auction",IFERROR(VLOOKUP(Table9[[#This Row],[NAME]],Aggregate!$B:$M,10,FALSE()),""),IFERROR(VLOOKUP(Table9[[#This Row],[NAME]],Aggregate!$B:$M,9,FALSE()),"")) -> 1.4967769 | G13: =SUMIFS(J14:$J$44,I14:$I$44,"<>x",I14:$I$44,"<>o",J14:$J$44,">0")/Aggregate!$J$1 -> 0.017566174 | H13: =VLOOKUP(Table9[[#This Row],[NAME]],ECR!C:E,3,FALSE()) -> QB13 | J13: =VLOOKUP(C13,Aggregate!B:J,9,FALSE()) -> 1.4967769 | L13: =IFERROR(VLOOKUP(Table10[[#This Row],[NAME]],Aggregate!$P:$AA,11,FALSE()),"") -> 3 | M13: =Aggregate!P9 -> Saquon Barkley | N13: =VLOOKUP(Table10[[#This Row],[NAME]],Aggregate!P:AA,4,FALSE()) -> PHI/10 | O13: =IFERROR(VLOOKUP(Table10[[#This Row],[NAME]],Aggregate!$P:$AA,8,FALSE()),"") -> 210.11738 | P13: =IF(Scoring!$K$6="Auction",IFERROR(VLOOKUP(Table10[[#This Row],[NAME]],Aggregate!$P:$AA,10,FALSE()),""),IFERROR(VLOOKUP(Table10[[#This Row],[NAME]],Aggregate!$P:$AA,9,FALSE()),"")) -> 82.571639 | Q13: =SUMIFS(T14:$T$84,S14:$S$84,"<>x",S14:$S$84,"<>o",T14:$T$84,">0")/Aggregate!$X$1 -> 0.46654514 | R13: =VLOOKUP(Table10[[#This Row],[NAME]],ECR!C:E,3,FALSE()) -> RB7 | T13: =VLOOKUP(M13,Aggregate!P:X,9,FALSE()) -> 82.571639 | V13: =IFERROR(VLOOKUP(Table11[[#This Row],[NAME]],Aggregate!$AD:$AO,11,FALSE()),"") -> 3 | W13: =Aggregate!AD13 -> Chris Olave | X13: =VLOOKUP(Table11[[#This Row],[NAME]],Aggregate!AD:AO,4,FALSE()) -> NO/8 | Y13: =IFERROR(VLOOKUP(Table11[[#This Row],[NAME]],Aggregate!$AD:$AO,8,FALSE()),"") -> 184.33494 | Z13: =IF(Scoring!$K$6="Auction",IFERROR(VLOOKUP(Table11[[#This Row],[NAME]],Aggregate!$AD:$AO,10,FALSE()),""),IFERROR(VLOOKUP(Table11[[#This Row],[NAME]],Aggregate!$AD:$AO,9,FALSE()),"")) -> 58.657057 | AA13: =SUMIFS(AD14:$AD$84,AC14:$AC$84,"<>x",AC14:$AC$84,"<>o",AD14:$AD$84,">0")/Aggregate!$AL$1 -> 0.4343756 | AB13: =VLOOKUP(Table11[[#This Row],[NAME]],ECR!C:E,3,FALSE()) -> WR11 | AD13: =VLOOKUP(W13,Aggregate!AD:AL,9,FALSE()) -> 58.657057
B14: =IFERROR(VLOOKUP(Table9[[#This Row],[NAME]],Aggregate!$B:$M,11,FALSE()),"") -> 5 | C14: =Aggregate!B13 -> Brock Purdy | D14: =VLOOKUP(Table9[[#This Row],[NAME]],Aggregate!B:M,4,FALSE()) -> SF/8 | E14: =IFERROR(VLOOKUP(Table9[[#This Row],[NAME]],Aggregate!$B:$M,8,FALSE()),"") -> 269.87395 | F14: =IF(Scoring!$K$6="Auction",IFERROR(VLOOKUP(Table9[[#This Row],[NAME]],Aggregate!$B:$M,10,FALSE()),""),IFERROR(VLOOKUP(Table9[[#This Row],[NAME]],Aggregate!$B:$M,9,FALSE()),"")) -> 1.4945889 | G14: =SUMIFS(J15:$J$44,I15:$I$44,"<>x",I15:$I$44,"<>o",J15:$J$44,">0")/Aggregate!$J$1 -> 0.0068105172 | H14: =VLOOKUP(Table9[[#This Row],[NAME]],ECR!C:E,3,FALSE()) -> QB11 | J14: =VLOOKUP(C14,Aggregate!B:J,9,FALSE()) -> 1.4945889 | L14: =IFERROR(VLOOKUP(Table10[[#This Row],[NAME]],Aggregate!$P:$AA,11,FALSE()),"") -> 3 | M14: =Aggregate!P11 -> Kenneth Walker III | N14: =VLOOKUP(Table10[[#This Row],[NAME]],Aggregate!P:AA,4,FALSE()) -> KC/5 | O14: =IFERROR(VLOOKUP(Table10[[#This Row],[NAME]],Aggregate!$P:$AA,8,FALSE()),"") -> 201.89785 | P14: =IF(Scoring!$K$6="Auction",IFERROR(VLOOKUP(Table10[[#This Row],[NAME]],Aggregate!$P:$AA,10,FALSE()),""),IFERROR(VLOOKUP(Table10[[#This Row],[NAME]],Aggregate!$P:$AA,9,FALSE()),"")) -> 74.352109 | Q14: =SUMIFS(T15:$T$84,S15:$S$84,"<>x",S15:$S$84,"<>o",T15:$T$84,">0")/Aggregate!$X$1 -> 0.42638338 | R14: =VLOOKUP(Table10[[#This Row],[NAME]],ECR!C:E,3,FALSE()) -> RB9 | T14: =VLOOKUP(M14,Aggregate!P:X,9,FALSE()) -> 74.352109 | V14: =IFERROR(VLOOKUP(Table11[[#This Row],[NAME]],Aggregate!$AD:$AO,11,FALSE()),"") -> 3 | W14: =Aggregate!AD12 -> George Pickens | X14: =VLOOKUP(Table11[[#This Row],[NAME]],Aggregate!AD:AO,4,FALSE()) -> DAL/14 | Y14: =IFERROR(VLOOKUP(Table11[[#This Row],[NAME]],Aggregate!$AD:$AO,8,FALSE()),"") -> 183.66791 | Z14: =IF(Scoring!$K$6="Auction",IFERROR(VLOOKUP(Table11[[#This Row],[NAME]],Aggregate!$AD:$AO,10,FALSE()),""),IFERROR(VLOOKUP(Table11[[#This Row],[NAME]],Aggregate!$AD:$AO,9,FALSE()),"")) -> 57.990028 | AA14: =SUMIFS(AD15:$AD$84,AC15:$AC$84,"<>x",AC15:$AC$84,"<>o",AD15:$AD$84,">0")/Aggregate!$AL$1 -> 0.39277679 | AB14: =VLOOKUP(Table11[[#This Row],[NAME]],ECR!C:E,3,FALSE()) -> WR10 | AD14: =VLOOKUP(W14,Aggregate!AD:AL,9,FALSE()) -> 57.990028
B15: =IFERROR(VLOOKUP(Table9[[#This Row],[NAME]],Aggregate!$B:$M,11,FALSE()),"") -> 5 | C15: =Aggregate!B9 -> Caleb Williams | D15: =VLOOKUP(Table9[[#This Row],[NAME]],Aggregate!B:M,4,FALSE()) -> CHI/10 | E15: =IFERROR(VLOOKUP(Table9[[#This Row],[NAME]],Aggregate!$B:$M,8,FALSE()),"") -> 269.32574 | F15: =IF(Scoring!$K$6="Auction",IFERROR(VLOOKUP(Table9[[#This Row],[NAME]],Aggregate!$B:$M,10,FALSE()),""),IFERROR(VLOOKUP(Table9[[#This Row],[NAME]],Aggregate!$B:$M,9,FALSE()),"")) -> 0.94637866 | G15: =SUMIFS(J16:$J$44,I16:$I$44,"<>x",I16:$I$44,"<>o",J16:$J$44,">0")/Aggregate!$J$1 -> 0 | H15: =VLOOKUP(Table9[[#This Row],[NAME]],ECR!C:E,3,FALSE()) -> QB7 | J15: =VLOOKUP(C15,Aggregate!B:J,9,FALSE()) -> 0.94637866 | L15: =IFERROR(VLOOKUP(Table10[[#This Row],[NAME]],Aggregate!$P:$AA,11,FALSE()),"") -> 4 | M15: =Aggregate!P14 -> Ashton Jeanty | N15: =VLOOKUP(Table10[[#This Row],[NAME]],Aggregate!P:AA,4,FALSE()) -> LV/13 | O15: =IFERROR(VLOOKUP(Table10[[#This Row],[NAME]],Aggregate!$P:$AA,8,FALSE()),"") -> 196.03024 | P15: =IF(Scoring!$K$6="Auction",IFERROR(VLOOKUP(Table10[[#This Row],[NAME]],Aggregate!$P:$AA,10,FALSE()),""),IFERROR(VLOOKUP(Table10[[#This Row],[NAME]],Aggregate!$P:$AA,9,FALSE()),"")) -> 68.484497 | Q15: =SUMIFS(T16:$T$84,S16:$S$84,"<>x",S16:$S$84,"<>o",T16:$T$84,">0")/Aggregate!$X$1 -> 0.38939105 | R15: =VLOOKUP(Table10[[#This Row],[NAME]],ECR!C:E,3,FALSE()) -> RB12 | T15: =VLOOKUP(M15,Aggregate!P:X,9,FALSE()) -> 68.484497 | V15: =IFERROR(VLOOKUP(Table11[[#This Row],[NAME]],Aggregate!$AD:$AO,11,FALSE()),"") -> 3 | W15: =Aggregate!AD11 -> Nico Collins | X15: =VLOOKUP(Table11[[#This Row],[NAME]],Aggregate!AD:AO,4,FALSE()) -> HOU/8 | Y15: =IFERROR(VLOOKUP(Table11[[#This Row],[NAME]],Aggregate!$AD:$AO,8,FALSE()),"") -> 182.92873 | Z15: =IF(Scoring!$K$6="Auction",IFERROR(VLOOKUP(Table11[[#This Row],[NAME]],Aggregate!$AD:$AO,10,FALSE()),""),IFERROR(VLOOKUP(Table11[[#This Row],[NAME]],Aggregate!$AD:$AO,9,FALSE()),"")) -> 57.250847 | AA15: =SUMIFS(AD16:$AD$84,AC16:$AC$84,"<>x",AC16:$AC$84,"<>o",AD16:$AD$84,">0")/Aggregate!$AL$1 -> 0.35170823 | AB15: =VLOOKUP(Table11[[#This Row],[NAME]],ECR!C:E,3,FALSE()) -> WR9 | AD15: =VLOOKUP(W15,Aggregate!AD:AL,9,FALSE()) -> 57.250847
B16: =IFERROR(VLOOKUP(Table9[[#This Row],[NAME]],Aggregate!$B:$M,11,FALSE()),"") -> 6 | C16: =Aggregate!B10 -> Justin Herbert | D16: =VLOOKUP(Table9[[#This Row],[NAME]],Aggregate!B:M,4,FALSE()) -> LAC/7 | E16: =IFERROR(VLOOKUP(Table9[[#This Row],[NAME]],Aggregate!$B:$M,8,FALSE()),"") -> 268.37937 | F16: =IF(Scoring!$K$6="Auction",IFERROR(VLOOKUP(Table9[[#This Row],[NAME]],Aggregate!$B:$M,10,FALSE()),""),IFERROR(VLOOKUP(Table9[[#This Row],[NAME]],Aggregate!$B:$M,9,FALSE()),"")) -> 0 | G16: =SUMIFS(J17:$J$44,I17:$I$44,"<>x",I17:$I$44,"<>o",J17:$J$44,">0")/Aggregate!$J$1 -> 0 | H16: =VLOOKUP(Table9[[#This Row],[NAME]],ECR!C:E,3,FALSE()) -> QB8 | J16: =VLOOKUP(C16,Aggregate!B:J,9,FALSE()) -> 0 | L16: =IFERROR(VLOOKUP(Table10[[#This Row],[NAME]],Aggregate!$P:$AA,11,FALSE()),"") -> 4 | M16: =Aggregate!P12 -> Omarion Hampton | N16: =VLOOKUP(Table10[[#This Row],[NAME]],Aggregate!P:AA,4,FALSE()) -> LAC/7 | O16: =IFERROR(VLOOKUP(Table10[[#This Row],[NAME]],Aggregate!$P:$AA,8,FALSE()),"") -> 195.37082 | P16: =IF(Scoring!$K$6="Auction",IFERROR(VLOOKUP(Table10[[#This Row],[NAME]],Aggregate!$P:$AA,10,FALSE()),""),IFERROR(VLOOKUP(Table10[[#This Row],[NAME]],Aggregate!$P:$AA,9,FALSE()),"")) -> 67.82508 | Q16: =SUMIFS(T17:$T$84,S17:$S$84,"<>x",S17:$S$84,"<>o",T17:$T$84,">0")/Aggregate!$X$1 -> 0.3527549 | R16: =VLOOKUP(Table10[[#This Row],[NAME]],ECR!C:E,3,FALSE()) -> RB10 | T16: =VLOOKUP(M16,Aggregate!P:X,9,FALSE()) -> 67.82508 | V16: =IFERROR(VLOOKUP(Table11[[#This Row],[NAME]],Aggregate!$AD:$AO,11,FALSE()),"") -> 3 | W16: =Aggregate!AD16 -> Rashee Rice | X16: =VLOOKUP(Table11[[#This Row],[NAME]],Aggregate!AD:AO,4,FALSE()) -> KC/5 | Y16: =IFERROR(VLOOKUP(Table11[[#This Row],[NAME]],Aggregate!$AD:$AO,8,FALSE()),"") -> 180.80471 | Z16: =IF(Scoring!$K$6="Auction",IFERROR(VLOOKUP(Table11[[#This Row],[NAME]],Aggregate!$AD:$AO,10,FALSE()),""),IFERROR(VLOOKUP(Table11[[#This Row],[NAME]],Aggregate!$AD:$AO,9,FALSE()),"")) -> 55.126827 | AA16: =SUMIFS(AD17:$AD$84,AC17:$AC$84,"<>x",AC17:$AC$84,"<>o",AD17:$AD$84,">0")/Aggregate!$AL$1 -> 0.31216333 | AB16: =VLOOKUP(Table11[[#This Row],[NAME]],ECR!C:E,3,FALSE()) -> WR14 | AD16: =VLOOKUP(W16,Aggregate!AD:AL,9,FALSE()) -> 55.126827
B17: =IFERROR(VLOOKUP(Table9[[#This Row],[NAME]],Aggregate!$B:$M,11,FALSE()),"") -> 7 | C17: =Aggregate!B16 -> Patrick Mahomes II | D17: =VLOOKUP(Table9[[#This Row],[NAME]],Aggregate!B:M,4,FALSE()) -> KC/5 | E17: =IFERROR(VLOOKUP(Table9[[#This Row],[NAME]],Aggregate!$B:$M,8,FALSE()),"") -> 264.65785 | F17: =IF(Scoring!$K$6="Auction",IFERROR(VLOOKUP(Table9[[#This Row],[NAME]],Aggregate!$B:$M,10,FALSE()),""),IFERROR(VLOOKUP(Table9[[#This Row],[NAME]],Aggregate!$B:$M,9,FALSE()),"")) -> -3.7215181 | G17: =SUMIFS(J18:$J$44,I18:$I$44,"<>x",I18:$I$44,"<>o",J18:$J$44,">0")/Aggregate!$J$1 -> 0 | H17: =VLOOKUP(Table9[[#This Row],[NAME]],ECR!C:E,3,FALSE()) -> QB14 | J17: =VLOOKUP(C17,Aggregate!B:J,9,FALSE()) -> -3.7215181 | L17: =IFERROR(VLOOKUP(Table10[[#This Row],[NAME]],Aggregate!$P:$AA,11,FALSE()),"") -> 4 | M17: =Aggregate!P18 -> Jeremiyah Love | N17: =VLOOKUP(Table10[[#This Row],[NAME]],Aggregate!P:AA,4,FALSE()) -> ARI/14 | O17: =IFERROR(VLOOKUP(Table10[[#This Row],[NAME]],Aggregate!$P:$AA,8,FALSE()),"") -> 191.58899 | P17: =IF(Scoring!$K$6="Auction",IFERROR(VLOOKUP(Table10[[#This Row],[NAME]],Aggregate!$P:$AA,10,FALSE()),""),IFERROR(VLOOKUP(Table10[[#This Row],[NAME]],Aggregate!$P:$AA,9,FALSE()),"")) -> 64.043251 | Q17: =SUMIFS(T18:$T$84,S18:$S$84,"<>x",S18:$S$84,"<>o",T18:$T$84,">0")/Aggregate!$X$1 -> 0.31816154 | R17: =VLOOKUP(Table10[[#This Row],[NAME]],ECR!C:E,3,FALSE()) -> RB16 | T17: =VLOOKUP(M17,Aggregate!P:X,9,FALSE()) -> 64.043251 | V17: =IFERROR(VLOOKUP(Table11[[#This Row],[NAME]],Aggregate!$AD:$AO,11,FALSE()),"") -> 4 | W17: =Aggregate!AD14 -> Malik Nabers | X17: =VLOOKUP(Table11[[#This Row],[NAME]],Aggregate!AD:AO,4,FALSE()) -> NYG/8 | Y17: =IFERROR(VLOOKUP(Table11[[#This Row],[NAME]],Aggregate!$AD:$AO,8,FALSE()),"") -> 174.92057 | Z17: =IF(Scoring!$K$6="Auction",IFERROR(VLOOKUP(Table11[[#This Row],[NAME]],Aggregate!$AD:$AO,10,FALSE()),""),IFERROR(VLOOKUP(Table11[[#This Row],[NAME]],Aggregate!$AD:$AO,9,FALSE()),"")) -> 49.242689 | AA17: =SUMIFS(AD18:$AD$84,AC18:$AC$84,"<>x",AC18:$AC$84,"<>o",AD18:$AD$84,">0")/Aggregate!$AL$1 -> 0.27683938 | AB17: =VLOOKUP(Table11[[#This Row],[NAME]],ECR!C:E,3,FALSE()) -> WR12 | AD17: =VLOOKUP(W17,Aggregate!AD:AL,9,FALSE()) -> 49.242689
B18: =IFERROR(VLOOKUP(Table9[[#This Row],[NAME]],Aggregate!$B:$M,11,FALSE()),"") -> 7 | C18: =Aggregate!B14 -> Bo Nix | D18: =VLOOKUP(Table9[[#This Row],[NAME]],Aggregate!B:M,4,FALSE()) -> DEN/10 | E18: =IFERROR(VLOOKUP(Table9[[#This Row],[NAME]],Aggregate!$B:$M,8,FALSE()),"") -> 262.33128 | F18: =IF(Scoring!$K$6="Auction",IFERROR(VLOOKUP(Table9[[#This Row],[NAME]],Aggregate!$B:$M,10,FALSE()),""),IFERROR(VLOOKUP(Table9[[#This Row],[NAME]],Aggregate!$B:$M,9,FALSE()),"")) -> -6.0480811 | G18: =SUMIFS(J19:$J$44,I19:$I$44,"<>x",I19:$I$44,"<>o",J19:$J$44,">0")/Aggregate!$J$1 -> 0 | H18: =VLOOKUP(Table9[[#This Row],[NAME]],ECR!C:E,3,FALSE()) -> QB12 | J18: =VLOOKUP(C18,Aggregate!B:J,9,FALSE()) -> -6.0480811 | L18: =IFERROR(VLOOKUP(Table10[[#This Row],[NAME]],Aggregate!$P:$AA,11,FALSE()),"") -> 4 | M18: =Aggregate!P16 -> Javonte Williams | N18: =VLOOKUP(Table10[[#This Row],[NAME]],Aggregate!P:AA,4,FALSE()) -> DAL/14 | O18: =IFERROR(VLOOKUP(Table10[[#This Row],[NAME]],Aggregate!$P:$AA,8,FALSE()),"") -> 188.87935 | P18: =IF(Scoring!$K$6="Auction",IFERROR(VLOOKUP(Table10[[#This Row],[NAME]],Aggregate!$P:$AA,10,FALSE()),""),IFERROR(VLOOKUP(Table10[[#This Row],[NAME]],Aggregate!$P:$AA,9,FALSE()),"")) -> 61.33361 | Q18: =SUMIFS(T19:$T$84,S19:$S$84,"<>x",S19:$S$84,"<>o",T19:$T$84,">0")/Aggregate!$X$1 -> 0.28503181 | R18: =VLOOKUP(Table10[[#This Row],[NAME]],ECR!C:E,3,FALSE()) -> RB14 | T18: =VLOOKUP(M18,Aggregate!P:X,9,FALSE()) -> 61.33361 | V18: =IFERROR(VLOOKUP(Table11[[#This Row],[NAME]],Aggregate!$AD:$AO,11,FALSE()),"") -> 4 | W18: =Aggregate!AD17 -> Zay Flowers | X18: =VLOOKUP(Table11[[#This Row],[NAME]],Aggregate!AD:AO,4,FALSE()) -> BAL/13 | Y18: =IFERROR(VLOOKUP(Table11[[#This Row],[NAME]],Aggregate!$AD:$AO,8,FALSE()),"") -> 167.44822 | Z18: =IF(Scoring!$K$6="Auction",IFERROR(VLOOKUP(Table11[[#This Row],[NAME]],Aggregate!$AD:$AO,10,FALSE()),""),IFERROR(VLOOKUP(Table11[[#This Row],[NAME]],Aggregate!$AD:$AO,9,FALSE()),"")) -> 41.770337 | AA18: =SUMIFS(AD19:$AD$84,AC19:$AC$84,"<>x",AC19:$AC$84,"<>o",AD19:$AD$84,">0")/Aggregate!$AL$1 -> 0.24687567 | AB18: =VLOOKUP(Table11[[#This Row],[NAME]],ECR!C:E,3,FALSE()) -> WR15 | AD18: =VLOOKUP(W18,Aggregate!AD:AL,9,FALSE()) -> 41.770337
B19: =IFERROR(VLOOKUP(Table9[[#This Row],[NAME]],Aggregate!$B:$M,11,FALSE()),"") -> 8 | C19: =Aggregate!B18 -> Matthew Stafford | D19: =VLOOKUP(Table9[[#This Row],[NAME]],Aggregate!B:M,4,FALSE()) -> LAR/11 | E19: =IFERROR(VLOOKUP(Table9[[#This Row],[NAME]],Aggregate!$B:$M,8,FALSE()),"") -> 252.56179 | F19: =IF(Scoring!$K$6="Auction",IFERROR(VLOOKUP(Table9[[#This Row],[NAME]],Aggregate!$B:$M,10,FALSE()),""),IFERROR(VLOOKUP(Table9[[#This Row],[NAME]],Aggregate!$B:$M,9,FALSE()),"")) -> -15.817578 | G19: =SUMIFS(J20:$J$44,I20:$I$44,"<>x",I20:$I$44,"<>o",J20:$J$44,">0")/Aggregate!$J$1 -> 0 | H19: =VLOOKUP(Table9[[#This Row],[NAME]],ECR!C:E,3,FALSE()) -> QB16 | J19: =VLOOKUP(C19,Aggregate!B:J,9,FALSE()) -> -15.817578 | L19: =IFERROR(VLOOKUP(Table10[[#This Row],[NAME]],Aggregate!$P:$AA,11,FALSE()),"") -> 4 | M19: =Aggregate!P15 -> Kyren Williams | N19: =VLOOKUP(Table10[[#This Row],[NAME]],Aggregate!P:AA,4,FALSE()) -> LAR/11 | O19: =IFERROR(VLOOKUP(Table10[[#This Row],[NAME]],Aggregate!$P:$AA,8,FALSE()),"") -> 188.28482 | P19: =IF(Scoring!$K$6="Auction",IFERROR(VLOOKUP(Table10[[#This Row],[NAME]],Aggregate!$P:$AA,10,FALSE()),""),IFERROR(VLOOKUP(Table10[[#This Row],[NAME]],Aggregate!$P:$AA,9,FALSE()),"")) -> 60.739083 | Q19: =SUMIFS(T20:$T$84,S20:$S$84,"<>x",S20:$S$84,"<>o",T20:$T$84,">0")/Aggregate!$X$1 -> 0.25222321 | R19: =VLOOKUP(Table10[[#This Row],[NAME]],ECR!C:E,3,FALSE()) -> RB13 | T19: =VLOOKUP(M19,Aggregate!P:X,9,FALSE()) -> 60.739083 | V19: =IFERROR(VLOOKUP(Table11[[#This Row],[NAME]],Aggregate!$AD:$AO,11,FALSE()),"") -> 4 | W19: =Aggregate!AD15 -> DeVonta Smith | X19: =VLOOKUP(Table11[[#This Row],[NAME]],Aggregate!AD:AO,4,FALSE()) -> PHI/10 | Y19: =IFERROR(VLOOKUP(Table11[[#This Row],[NAME]],Aggregate!$AD:$AO,8,FALSE()),"") -> 165.73653 | Z19: =IF(Scoring!$K$6="Auction",IFERROR(VLOOKUP(Table11[[#This Row],[NAME]],Aggregate!$AD:$AO,10,FALSE()),""),IFERROR(VLOOKUP(Table11[[#This Row],[NAME]],Aggregate!$AD:$AO,9,FALSE()),"")) -> 40.058654 | AA19: =SUMIFS(AD20:$AD$84,AC20:$AC$84,"<>x",AC20:$AC$84,"<>o",AD20:$AD$84,">0")/Aggregate!$AL$1 -> 0.21813983 | AB19: =VLOOKUP(Table11[[#This Row],[NAME]],ECR!C:E,3,FALSE()) -> WR13 | AD19: =VLOOKUP(W19,Aggregate!AD:AL,9,FALSE()) -> 40.058654
B20: =IFERROR(VLOOKUP(Table9[[#This Row],[NAME]],Aggregate!$B:$M,11,FALSE()),"") -> 8 | C20: =Aggregate!B17 -> Jared Goff | D20: =VLOOKUP(Table9[[#This Row],[NAME]],Aggregate!B:M,4,FALSE()) -> DET/6 | E20: =IFERROR(VLOOKUP(Table9[[#This Row],[NAME]],Aggregate!$B:$M,8,FALSE()),"") -> 251.81997 | F20: =IF(Scoring!$K$6="Auction",IFERROR(VLOOKUP(Table9[[#This Row],[NAME]],Aggregate!$B:$M,10,FALSE()),""),IFERROR(VLOOKUP(Table9[[#This Row],[NAME]],Aggregate!$B:$M,9,FALSE()),"")) -> -16.559392 | G20: =SUMIFS(J21:$J$44,I21:$I$44,"<>x",I21:$I$44,"<>o",J21:$J$44,">0")/Aggregate!$J$1 -> 0 | H20: =VLOOKUP(Table9[[#This Row],[NAME]],ECR!C:E,3,FALSE()) -> QB15 | J20: =VLOOKUP(C20,Aggregate!B:J,9,FALSE()) -> -16.559392 | L20: =IFERROR(VLOOKUP(Table10[[#This Row],[NAME]],Aggregate!$P:$AA,11,FALSE()),"") -> 4 | M20: =Aggregate!P17 -> Breece Hall | N20: =VLOOKUP(Table10[[#This Row],[NAME]],Aggregate!P:AA,4,FALSE()) -> NYJ/13 | O20: =IFERROR(VLOOKUP(Table10[[#This Row],[NAME]],Aggregate!$P:$AA,8,FALSE()),"") -> 187.19772 | P20: =IF(Scoring!$K$6="Auction",IFERROR(VLOOKUP(Table10[[#This Row],[NAME]],Aggregate!$P:$AA,10,FALSE()),""),IFERROR(VLOOKUP(Table10[[#This Row],[NAME]],Aggregate!$P:$AA,9,FALSE()),"")) -> 59.651982 | Q20: =SUMIFS(T21:$T$84,S21:$S$84,"<>x",S21:$S$84,"<>o",T21:$T$84,">0")/Aggregate!$X$1 -> 0.22000182 | R20: =VLOOKUP(Table10[[#This Row],[NAME]],ECR!C:E,3,FALSE()) -> RB15 | T20: =VLOOKUP(M20,Aggregate!P:X,9,FALSE()) -> 59.651982 | V20: =IFERROR(VLOOKUP(Table11[[#This Row],[NAME]],Aggregate!$AD:$AO,11,FALSE()),"") -> 4 | W20: =Aggregate!AD21 -> Garrett Wilson | X20: =VLOOKUP(Table11[[#This Row],[NAME]],Aggregate!AD:AO,4,FALSE()) -> NYJ/13 | Y20: =IFERROR(VLOOKUP(Table11[[#This Row],[NAME]],Aggregate!$AD:$AO,8,FALSE()),"") -> 159.2144 | Z20: =IF(Scoring!$K$6="Auction",IFERROR(VLOOKUP(Table11[[#This Row],[NAME]],Aggregate!$AD:$AO,10,FALSE()),""),IFERROR(VLOOKUP(Table11[[#This Row],[NAME]],Aggregate!$AD:$AO,9,FALSE()),"")) -> 33.536519 | AA20: =SUMIFS(AD21:$AD$84,AC21:$AC$84,"<>x",AC21:$AC$84,"<>o",AD21:$AD$84,">0")/Aggregate!$AL$1 -> 0.19408261 | AB20: =VLOOKUP(Table11[[#This Row],[NAME]],ECR!C:E,3,FALSE()) -> WR19 | AD20: =VLOOKUP(W20,Aggregate!AD:AL,9,FALSE()) -> 33.536519
B21: =IFERROR(VLOOKUP(Table9[[#This Row],[NAME]],Aggregate!$B:$M,11,FALSE()),"") -> 8 | C21: =Aggregate!B19 -> Kyler Murray | D21: =VLOOKUP(Table9[[#This Row],[NAME]],Aggregate!B:M,4,FALSE()) -> MIN/6 | E21: =IFERROR(VLOOKUP(Table9[[#This Row],[NAME]],Aggregate!$B:$M,8,FALSE()),"") -> 250.55691 | F21: =IF(Scoring!$K$6="Auction",IFERROR(VLOOKUP(Table9[[#This Row],[NAME]],Aggregate!$B:$M,10,FALSE()),""),IFERROR(VLOOKUP(Table9[[#This Row],[NAME]],Aggregate!$B:$M,9,FALSE()),"")) -> -17.822452 | G21: =SUMIFS(J22:$J$44,I22:$I$44,"<>x",I22:$I$44,"<>o",J22:$J$44,">0")/Aggregate!$J$1 -> 0 | H21: =VLOOKUP(Table9[[#This Row],[NAME]],ECR!C:E,3,FALSE()) -> QB17 | J21: =VLOOKUP(C21,Aggregate!B:J,9,FALSE()) -> -17.822452 | L21: =IFERROR(VLOOKUP(Table10[[#This Row],[NAME]],Aggregate!$P:$AA,11,FALSE()),"") -> 4 | M21: =Aggregate!P19 -> Travis Etienne Jr. | N21: =VLOOKUP(Table10[[#This Row],[NAME]],Aggregate!P:AA,4,FALSE()) -> NO/8 | O21: =IFERROR(VLOOKUP(Table10[[#This Row],[NAME]],Aggregate!$P:$AA,8,FALSE()),"") -> 181.29835 | P21: =IF(Scoring!$K$6="Auction",IFERROR(VLOOKUP(Table10[[#This Row],[NAME]],Aggregate!$P:$AA,10,FALSE()),""),IFERROR(VLOOKUP(Table10[[#This Row],[NAME]],Aggregate!$P:$AA,9,FALSE()),"")) -> 53.752614 | Q21: =SUMIFS(T22:$T$84,S22:$S$84,"<>x",S22:$S$84,"<>o",T22:$T$84,">0")/Aggregate!$X$1 -> 0.190967 | R21: =VLOOKUP(Table10[[#This Row],[NAME]],ECR!C:E,3,FALSE()) -> RB17 | T21: =VLOOKUP(M21,Aggregate!P:X,9,FALSE()) -> 53.752614 | V21: =IFERROR(VLOOKUP(Table11[[#This Row],[NAME]],Aggregate!$AD:$AO,11,FALSE()),"") -> 4 | W21: =Aggregate!AD18 -> Tee Higgins | X21: =VLOOKUP(Table11[[#This Row],[NAME]],Aggregate!AD:AO,4,FALSE()) -> CIN/6 | Y21: =IFERROR(VLOOKUP(Table11[[#This Row],[NAME]],Aggregate!$AD:$AO,8,FALSE()),"") -> 158.12437 | Z21: =IF(Scoring!$K$6="Auction",IFERROR(VLOOKUP(Table11[[#This Row],[NAME]],Aggregate!$AD:$AO,10,FALSE()),""),IFERROR(VLOOKUP(Table11[[#This Row],[NAME]],Aggregate!$AD:$AO,9,FALSE()),"")) -> 32.446492 | AA21: =SUMIFS(AD22:$AD$84,AC22:$AC$84,"<>x",AC22:$AC$84,"<>o",AD22:$AD$84,">0")/Aggregate!$AL$1 -> 0.17080731 | AB21: =VLOOKUP(Table11[[#This Row],[NAME]],ECR!C:E,3,FALSE()) -> WR16 | AD21: =VLOOKUP(W21,Aggregate!AD:AL,9,FALSE()) -> 32.446492
B22: =IFERROR(VLOOKUP(Table9[[#This Row],[NAME]],Aggregate!$B:$M,11,FALSE()),"") -> 9 | C22: =Aggregate!B21 -> Baker Mayfield | D22: =VLOOKUP(Table9[[#This Row],[NAME]],Aggregate!B:M,4,FALSE()) -> TB/10 | E22: =IFERROR(VLOOKUP(Table9[[#This Row],[NAME]],Aggregate!$B:$M,8,FALSE()),"") -> 238.99228 | F22: =IF(Scoring!$K$6="Auction",IFERROR(VLOOKUP(Table9[[#This Row],[NAME]],Aggregate!$B:$M,10,FALSE()),""),IFERROR(VLOOKUP(Table9[[#This Row],[NAME]],Aggregate!$B:$M,9,FALSE()),"")) -> -29.387087 | G22: =SUMIFS(J23:$J$44,I23:$I$44,"<>x",I23:$I$44,"<>o",J23:$J$44,">0")/Aggregate!$J$1 -> 0 | H22: =VLOOKUP(Table9[[#This Row],[NAME]],ECR!C:E,3,FALSE()) -> QB19 | J22: =VLOOKUP(C22,Aggregate!B:J,9,FALSE()) -> -29.387087 | L22: =IFERROR(VLOOKUP(Table10[[#This Row],[NAME]],Aggregate!$P:$AA,11,FALSE()),"") -> 4 | M22: =Aggregate!P22 -> Cam Skattebo | N22: =VLOOKUP(Table10[[#This Row],[NAME]],Aggregate!P:AA,4,FALSE()) -> NYG/8 | O22: =IFERROR(VLOOKUP(Table10[[#This Row],[NAME]],Aggregate!$P:$AA,8,FALSE()),"") -> 175.00966 | P22: =IF(Scoring!$K$6="Auction",IFERROR(VLOOKUP(Table10[[#This Row],[NAME]],Aggregate!$P:$AA,10,FALSE()),""),IFERROR(VLOOKUP(Table10[[#This Row],[NAME]],Aggregate!$P:$AA,9,FALSE()),"")) -> 47.463921 | Q22: =SUMIFS(T23:$T$84,S23:$S$84,"<>x",S23:$S$84,"<>o",T23:$T$84,">0")/Aggregate!$X$1 -> 0.16532907 | R22: =VLOOKUP(Table10[[#This Row],[NAME]],ECR!C:E,3,FALSE()) -> RB20 | T22: =VLOOKUP(M22,Aggregate!P:X,9,FALSE()) -> 47.463921 | V22: =IFERROR(VLOOKUP(Table11[[#This Row],[NAME]],Aggregate!$AD:$AO,11,FALSE()),"") -> 4 | W22: =Aggregate!AD22 -> Tetairoa McMillan | X22: =VLOOKUP(Table11[[#This Row],[NAME]],Aggregate!AD:AO,4,FALSE()) -> CAR/5 | Y22: =IFERROR(VLOOKUP(Table11[[#This Row],[NAME]],Aggregate!$AD:$AO,8,FALSE()),"") -> 157.05231 | Z22: =IF(Scoring!$K$6="Auction",IFERROR(VLOOKUP(Table11[[#This Row],[NAME]],Aggregate!$AD:$AO,10,FALSE()),""),IFERROR(VLOOKUP(Table11[[#This Row],[NAME]],Aggregate!$AD:$AO,9,FALSE()),"")) -> 31.374431 | AA22: =SUMIFS(AD23:$AD$84,AC23:$AC$84,"<>x",AC23:$AC$84,"<>o",AD23:$AD$84,">0")/Aggregate!$AL$1 -> 0.14830105 | AB22: =VLOOKUP(Table11[[#This Row],[NAME]],ECR!C:E,3,FALSE()) -> WR20 | AD22: =VLOOKUP(W22,Aggregate!AD:AL,9,FALSE()) -> 31.374431
B23: =IFERROR(VLOOKUP(Table9[[#This Row],[NAME]],Aggregate!$B:$M,11,FALSE()),"") -> 9 | C23: =Aggregate!B22 -> Tyler Shough | D23: =VLOOKUP(Table9[[#This Row],[NAME]],Aggregate!B:M,4,FALSE()) -> NO/8 | E23: =IFERROR(VLOOKUP(Table9[[#This Row],[NAME]],Aggregate!$B:$M,8,FALSE()),"") -> 237.57109 | F23: =IF(Scoring!$K$6="Auction",IFERROR(VLOOKUP(Table9[[#This Row],[NAME]],Aggregate!$B:$M,10,FALSE()),""),IFERROR(VLOOKUP(Table9[[#This Row],[NAME]],Aggregate!$B:$M,9,FALSE()),"")) -> -30.808274 | G23: =SUMIFS(J24:$J$44,I24:$I$44,"<>x",I24:$I$44,"<>o",J24:$J$44,">0")/Aggregate!$J$1 -> 0 | H23: =VLOOKUP(Table9[[#This Row],[NAME]],ECR!C:E,3,FALSE()) -> QB20 | J23: =VLOOKUP(C23,Aggregate!B:J,9,FALSE()) -> -30.808274 | L23: =IFERROR(VLOOKUP(Table10[[#This Row],[NAME]],Aggregate!$P:$AA,11,FALSE()),"") -> 5 | M23: =Aggregate!P20 -> D'Andre Swift | N23: =VLOOKUP(Table10[[#This Row],[NAME]],Aggregate!P:AA,4,FALSE()) -> CHI/10 | O23: =IFERROR(VLOOKUP(Table10[[#This Row],[NAME]],Aggregate!$P:$AA,8,FALSE()),"") -> 174.37801 | P23: =IF(Scoring!$K$6="Auction",IFERROR(VLOOKUP(Table10[[#This Row],[NAME]],Aggregate!$P:$AA,10,FALSE()),""),IFERROR(VLOOKUP(Table10[[#This Row],[NAME]],Aggregate!$P:$AA,9,FALSE()),"")) -> 46.832275 | Q23: =SUMIFS(T24:$T$84,S24:$S$84,"<>x",S24:$S$84,"<>o",T24:$T$84,">0")/Aggregate!$X$1 -> 0.14003232 | R23: =VLOOKUP(Table10[[#This Row],[NAME]],ECR!C:E,3,FALSE()) -> RB18 | T23: =VLOOKUP(M23,Aggregate!P:X,9,FALSE()) -> 46.832275 | V23: =IFERROR(VLOOKUP(Table11[[#This Row],[NAME]],Aggregate!$AD:$AO,11,FALSE()),"") -> 5 | W23: =Aggregate!AD23 -> Emeka Egbuka | X23: =VLOOKUP(Table11[[#This Row],[NAME]],Aggregate!AD:AO,4,FALSE()) -> TB/10 | Y23: =IFERROR(VLOOKUP(Table11[[#This Row],[NAME]],Aggregate!$AD:$AO,8,FALSE()),"") -> 154.47706 | Z23: =IF(Scoring!$K$6="Auction",IFERROR(VLOOKUP(Table11[[#This Row],[NAME]],Aggregate!$AD:$AO,10,FALSE()),""),IFERROR(VLOOKUP(Table11[[#This Row],[NAME]],Aggregate!$AD:$AO,9,FALSE()),"")) -> 28.799183 | AA23: =SUMIFS(AD24:$AD$84,AC24:$AC$84,"<>x",AC24:$AC$84,"<>o",AD24:$AD$84,">0")/Aggregate!$AL$1 -> 0.12764212 | AB23: =VLOOKUP(Table11[[#This Row],[NAME]],ECR!C:E,3,FALSE()) -> WR21 | AD23: =VLOOKUP(W23,Aggregate!AD:AL,9,FALSE()) -> 28.799183
B24: =IFERROR(VLOOKUP(Table9[[#This Row],[NAME]],Aggregate!$B:$M,11,FALSE()),"") -> 9 | C24: =Aggregate!B20 -> Jordan Love | D24: =VLOOKUP(Table9[[#This Row],[NAME]],Aggregate!B:M,4,FALSE()) -> GB/11 | E24: =IFERROR(VLOOKUP(Table9[[#This Row],[NAME]],Aggregate!$B:$M,8,FALSE()),"") -> 235.88159 | F24: =IF(Scoring!$K$6="Auction",IFERROR(VLOOKUP(Table9[[#This Row],[NAME]],Aggregate!$B:$M,10,FALSE()),""),IFERROR(VLOOKUP(Table9[[#This Row],[NAME]],Aggregate!$B:$M,9,FALSE()),"")) -> -32.497775 | G24: =SUMIFS(J25:$J$44,I25:$I$44,"<>x",I25:$I$44,"<>o",J25:$J$44,">0")/Aggregate!$J$1 -> 0 | H24: =VLOOKUP(Table9[[#This Row],[NAME]],ECR!C:E,3,FALSE()) -> QB18 | J24: =VLOOKUP(C24,Aggregate!B:J,9,FALSE()) -> -32.497775 | L24: =IFERROR(VLOOKUP(Table10[[#This Row],[NAME]],Aggregate!$P:$AA,11,FALSE()),"") -> 5 | M24: =Aggregate!P21 -> Bucky Irving | N24: =VLOOKUP(Table10[[#This Row],[NAME]],Aggregate!P:AA,4,FALSE()) -> TB/10 | O24: =IFERROR(VLOOKUP(Table10[[#This Row],[NAME]],Aggregate!$P:$AA,8,FALSE()),"") -> 169.99665 | P24: =IF(Scoring!$K$6="Auction",IFERROR(VLOOKUP(Table10[[#This Row],[NAME]],Aggregate!$P:$AA,10,FALSE()),""),IFERROR(VLOOKUP(Table10[[#This Row],[NAME]],Aggregate!$P:$AA,9,FALSE()),"")) -> 42.450915 | Q24: =SUMIFS(T25:$T$84,S25:$S$84,"<>x",S25:$S$84,"<>o",T25:$T$84,">0")/Aggregate!$X$1 -> 0.11710219 | R24: =VLOOKUP(Table10[[#This Row],[NAME]],ECR!C:E,3,FALSE()) -> RB19 | T24: =VLOOKUP(M24,Aggregate!P:X,9,FALSE()) -> 42.450915 | V24: =IFERROR(VLOOKUP(Table11[[#This Row],[NAME]],Aggregate!$AD:$AO,11,FALSE()),"") -> 5 | W24: =Aggregate!AD20 -> Ladd McConkey | X24: =VLOOKUP(Table11[[#This Row],[NAME]],Aggregate!AD:AO,4,FALSE()) -> LAC/7 | Y24: =IFERROR(VLOOKUP(Table11[[#This Row],[NAME]],Aggregate!$AD:$AO,8,FALSE()),"") -> 150.91398 | Z24: =IF(Scoring!$K$6="Auction",IFERROR(VLOOKUP(Table11[[#This Row],[NAME]],Aggregate!$AD:$AO,10,FALSE()),""),IFERROR(VLOOKUP(Table11[[#This Row],[NAME]],Aggregate!$AD:$AO,9,FALSE()),"")) -> 25.236104 | AA24: =SUMIFS(AD25:$AD$84,AC25:$AC$84,"<>x",AC25:$AC$84,"<>o",AD25:$AD$84,">0")/Aggregate!$AL$1 -> 0.10953915 | AB24: =VLOOKUP(Table11[[#This Row],[NAME]],ECR!C:E,3,FALSE()) -> WR18 | AD24: =VLOOKUP(W24,Aggregate!AD:AL,9,FALSE()) -> 25.236104
B25: =IFERROR(VLOOKUP(Table9[[#This Row],[NAME]],Aggregate!$B:$M,11,FALSE()),"") -> 10 | C25: =Aggregate!B23 -> Malik Willis | D25: =VLOOKUP(Table9[[#This Row],[NAME]],Aggregate!B:M,4,FALSE()) -> MIA/6 | E25: =IFERROR(VLOOKUP(Table9[[#This Row],[NAME]],Aggregate!$B:$M,8,FALSE()),"") -> 226.15984 | F25: =IF(Scoring!$K$6="Auction",IFERROR(VLOOKUP(Table9[[#This Row],[NAME]],Aggregate!$B:$M,10,FALSE()),""),IFERROR(VLOOKUP(Table9[[#This Row],[NAME]],Aggregate!$B:$M,9,FALSE()),"")) -> -42.219526 | G25: =SUMIFS(J26:$J$44,I26:$I$44,"<>x",I26:$I$44,"<>o",J26:$J$44,">0")/Aggregate!$J$1 -> 0 | H25: =VLOOKUP(Table9[[#This Row],[NAME]],ECR!C:E,3,FALSE()) -> QB21 | J25: =VLOOKUP(C25,Aggregate!B:J,9,FALSE()) -> -42.219526 | L25: =IFERROR(VLOOKUP(Table10[[#This Row],[NAME]],Aggregate!$P:$AA,11,FALSE()),"") -> 5 | M25: =Aggregate!P24 -> Quinshon Judkins | N25: =VLOOKUP(Table10[[#This Row],[NAME]],Aggregate!P:AA,4,FALSE()) -> CLE/11 | O25: =IFERROR(VLOOKUP(Table10[[#This Row],[NAME]],Aggregate!$P:$AA,8,FALSE()),"") -> 166.43142 | P25: =IF(Scoring!$K$6="Auction",IFERROR(VLOOKUP(Table10[[#This Row],[NAME]],Aggregate!$P:$AA,10,FALSE()),""),IFERROR(VLOOKUP(Table10[[#This Row],[NAME]],Aggregate!$P:$AA,9,FALSE()),"")) -> 38.885682 | Q25: =SUMIFS(T26:$T$84,S26:$S$84,"<>x",S26:$S$84,"<>o",T26:$T$84,">0")/Aggregate!$X$1 -> 0.09609785 | R25: =VLOOKUP(Table10[[#This Row],[NAME]],ECR!C:E,3,FALSE()) -> RB22 | T25: =VLOOKUP(M25,Aggregate!P:X,9,FALSE()) -> 38.885682 | V25: =IFERROR(VLOOKUP(Table11[[#This Row],[NAME]],Aggregate!$AD:$AO,11,FALSE()),"") -> 5 | W25: =Aggregate!AD25 -> Davante Adams | X25: =VLOOKUP(Table11[[#This Row],[NAME]],Aggregate!AD:AO,4,FALSE()) -> LAR/11 | Y25: =IFERROR(VLOOKUP(Table11[[#This Row],[NAME]],Aggregate!$AD:$AO,8,FALSE()),"") -> 150.38957 | Z25: =IF(Scoring!$K$6="Auction",IFERROR(VLOOKUP(Table11[[#This Row],[NAME]],Aggregate!$AD:$AO,10,FALSE()),""),IFERROR(VLOOKUP(Table11[[#This Row],[NAME]],Aggregate!$AD:$AO,9,FALSE()),"")) -> 24.711692 | AA25: =SUMIFS(AD26:$AD$84,AC26:$AC$84,"<>x",AC26:$AC$84,"<>o",AD26:$AD$84,">0")/Aggregate!$AL$1 -> 0.091812364 | AB25: =VLOOKUP(Table11[[#This Row],[NAME]],ECR!C:E,3,FALSE()) -> WR23 | AD25: =VLOOKUP(W25,Aggregate!AD:AL,9,FALSE()) -> 24.711692
B26: =IFERROR(VLOOKUP(Table9[[#This Row],[NAME]],Aggregate!$B:$M,11,FALSE()),"") -> 11 | C26: =Aggregate!B26 -> Daniel Jones | D26: =VLOOKUP(Table9[[#This Row],[NAME]],Aggregate!B:M,4,FALSE()) -> IND/13 | E26: =IFERROR(VLOOKUP(Table9[[#This Row],[NAME]],Aggregate!$B:$M,8,FALSE()),"") -> 219.8708 | F26: =IF(Scoring!$K$6="Auction",IFERROR(VLOOKUP(Table9[[#This Row],[NAME]],Aggregate!$B:$M,10,FALSE()),""),IFERROR(VLOOKUP(Table9[[#This Row],[NAME]],Aggregate!$B:$M,9,FALSE()),"")) -> -48.508566 | G26: =SUMIFS(J27:$J$44,I27:$I$44,"<>x",I27:$I$44,"<>o",J27:$J$44,">0")/Aggregate!$J$1 -> 0 | H26: =VLOOKUP(Table9[[#This Row],[NAME]],ECR!C:E,3,FALSE()) -> QB24 | J26: =VLOOKUP(C26,Aggregate!B:J,9,FALSE()) -> -48.508566 | L26: =IFERROR(VLOOKUP(Table10[[#This Row],[NAME]],Aggregate!$P:$AA,11,FALSE()),"") -> 5 | M26: =Aggregate!P25 -> Bhayshul Tuten | N26: =VLOOKUP(Table10[[#This Row],[NAME]],Aggregate!P:AA,4,FALSE()) -> JAC/7 | O26: =IFERROR(VLOOKUP(Table10[[#This Row],[NAME]],Aggregate!$P:$AA,8,FALSE()),"") -> 163.07169 | P26: =IF(Scoring!$K$6="Auction",IFERROR(VLOOKUP(Table10[[#This Row],[NAME]],Aggregate!$P:$AA,10,FALSE()),""),IFERROR(VLOOKUP(Table10[[#This Row],[NAME]],Aggregate!$P:$AA,9,FALSE()),"")) -> 35.525956 | Q26: =SUMIFS(T27:$T$84,S27:$S$84,"<>x",S27:$S$84,"<>o",T27:$T$84,">0")/Aggregate!$X$1 -> 0.076908282 | R26: =VLOOKUP(Table10[[#This Row],[NAME]],ECR!C:E,3,FALSE()) -> RB23 | T26: =VLOOKUP(M26,Aggregate!P:X,9,FALSE()) -> 35.525956 | V26: =IFERROR(VLOOKUP(Table11[[#This Row],[NAME]],Aggregate!$AD:$AO,11,FALSE()),"") -> 5 | W26: =Aggregate!AD19 -> Jaylen Waddle | X26: =VLOOKUP(Table11[[#This Row],[NAME]],Aggregate!AD:AO,4,FALSE()) -> DEN/10 | Y26: =IFERROR(VLOOKUP(Table11[[#This Row],[NAME]],Aggregate!$AD:$AO,8,FALSE()),"") -> 149.20195 | Z26: =IF(Scoring!$K$6="Auction",IFERROR(VLOOKUP(Table11[[#This Row],[NAME]],Aggregate!$AD:$AO,10,FALSE()),""),IFERROR(VLOOKUP(Table11[[#This Row],[NAME]],Aggregate!$AD:$AO,9,FALSE()),"")) -> 23.524067 | AA26: =SUMIFS(AD27:$AD$84,AC27:$AC$84,"<>x",AC27:$AC$84,"<>o",AD27:$AD$84,">0")/Aggregate!$AL$1 -> 0.074937513 | AB26: =VLOOKUP(Table11[[#This Row],[NAME]],ECR!C:E,3,FALSE()) -> WR17 | AD26: =VLOOKUP(W26,Aggregate!AD:AL,9,FALSE()) -> 23.524067
B27: =IFERROR(VLOOKUP(Table9[[#This Row],[NAME]],Aggregate!$B:$M,11,FALSE()),"") -> 11 | C27: =Aggregate!B24 -> Sam Darnold | D27: =VLOOKUP(Table9[[#This Row],[NAME]],Aggregate!B:M,4,FALSE()) -> SEA/11 | E27: =IFERROR(VLOOKUP(Table9[[#This Row],[NAME]],Aggregate!$B:$M,8,FALSE()),"") -> 219.87059 | F27: =IF(Scoring!$K$6="Auction",IFERROR(VLOOKUP(Table9[[#This Row],[NAME]],Aggregate!$B:$M,10,FALSE()),""),IFERROR(VLOOKUP(Table9[[#This Row],[NAME]],Aggregate!$B:$M,9,FALSE()),"")) -> -48.508776 | G27: =SUMIFS(J28:$J$44,I28:$I$44,"<>x",I28:$I$44,"<>o",J28:$J$44,">0")/Aggregate!$J$1 -> 0 | H27: =VLOOKUP(Table9[[#This Row],[NAME]],ECR!C:E,3,FALSE()) -> QB22 | J27: =VLOOKUP(C27,Aggregate!B:J,9,FALSE()) -> -48.508776 | L27: =IFERROR(VLOOKUP(Table10[[#This Row],[NAME]],Aggregate!$P:$AA,11,FALSE()),"") -> 5 | M27: =Aggregate!P26 -> Jadarian Price | N27: =VLOOKUP(Table10[[#This Row],[NAME]],Aggregate!P:AA,4,FALSE()) -> SEA/11 | O27: =IFERROR(VLOOKUP(Table10[[#This Row],[NAME]],Aggregate!$P:$AA,8,FALSE()),"") -> 159.01824 | P27: =IF(Scoring!$K$6="Auction",IFERROR(VLOOKUP(Table10[[#This Row],[NAME]],Aggregate!$P:$AA,10,FALSE()),""),IFERROR(VLOOKUP(Table10[[#This Row],[NAME]],Aggregate!$P:$AA,9,FALSE()),"")) -> 31.472501 | Q27: =SUMIFS(T28:$T$84,S28:$S$84,"<>x",S28:$S$84,"<>o",T28:$T$84,">0")/Aggregate!$X$1 -> 0.059908213 | R27: =VLOOKUP(Table10[[#This Row],[NAME]],ECR!C:E,3,FALSE()) -> RB24 | T27: =VLOOKUP(M27,Aggregate!P:X,9,FALSE()) -> 31.472501 | V27: =IFERROR(VLOOKUP(Table11[[#This Row],[NAME]],Aggregate!$AD:$AO,11,FALSE()),"") -> 5 | W27: =Aggregate!AD27 -> Jameson Williams | X27: =VLOOKUP(Table11[[#This Row],[NAME]],Aggregate!AD:AO,4,FALSE()) -> DET/6 | Y27: =IFERROR(VLOOKUP(Table11[[#This Row],[NAME]],Aggregate!$AD:$AO,8,FALSE()),"") -> 145.97952 | Z27: =IF(Scoring!$K$6="Auction",IFERROR(VLOOKUP(Table11[[#This Row],[NAME]],Aggregate!$AD:$AO,10,FALSE()),""),IFERROR(VLOOKUP(Table11[[#This Row],[NAME]],Aggregate!$AD:$AO,9,FALSE()),"")) -> 20.301644 | AA27: =SUMIFS(AD28:$AD$84,AC28:$AC$84,"<>x",AC28:$AC$84,"<>o",AD28:$AD$84,">0")/Aggregate!$AL$1 -> 0.060374248 | AB27: =VLOOKUP(Table11[[#This Row],[NAME]],ECR!C:E,3,FALSE()) -> WR25 | AD27: =VLOOKUP(W27,Aggregate!AD:AL,9,FALSE()) -> 20.301644
B28: =IFERROR(VLOOKUP(Table9[[#This Row],[NAME]],Aggregate!$B:$M,11,FALSE()),"") -> 12 | C28: =Aggregate!B25 -> C.J. Stroud | D28: =VLOOKUP(Table9[[#This Row],[NAME]],Aggregate!B:M,4,FALSE()) -> HOU/8 | E28: =IFERROR(VLOOKUP(Table9[[#This Row],[NAME]],Aggregate!$B:$M,8,FALSE()),"") -> 214.51287 | F28: =IF(Scoring!$K$6="Auction",IFERROR(VLOOKUP(Table9[[#This Row],[NAME]],Aggregate!$B:$M,10,FALSE()),""),IFERROR(VLOOKUP(Table9[[#This Row],[NAME]],Aggregate!$B:$M,9,FALSE()),"")) -> -53.866492 | G28: =SUMIFS(J29:$J$44,I29:$I$44,"<>x",I29:$I$44,"<>o",J29:$J$44,">0")/Aggregate!$J$1 -> 0 | H28: =VLOOKUP(Table9[[#This Row],[NAME]],ECR!C:E,3,FALSE()) -> QB23 | J28: =VLOOKUP(C28,Aggregate!B:J,9,FALSE()) -> -53.866492 | L28: =IFERROR(VLOOKUP(Table10[[#This Row],[NAME]],Aggregate!$P:$AA,11,FALSE()),"") -> 5 | M28: =Aggregate!P23 -> David Montgomery | N28: =VLOOKUP(Table10[[#This Row],[NAME]],Aggregate!P:AA,4,FALSE()) -> HOU/8 | O28: =IFERROR(VLOOKUP(Table10[[#This Row],[NAME]],Aggregate!$P:$AA,8,FALSE()),"") -> 158.11561 | P28: =IF(Scoring!$K$6="Auction",IFERROR(VLOOKUP(Table10[[#This Row],[NAME]],Aggregate!$P:$AA,10,FALSE()),""),IFERROR(VLOOKUP(Table10[[#This Row],[NAME]],Aggregate!$P:$AA,9,FALSE()),"")) -> 30.569875 | Q28: =SUMIFS(T29:$T$84,S29:$S$84,"<>x",S29:$S$84,"<>o",T29:$T$84,">0")/Aggregate!$X$1 -> 0.043395703 | R28: =VLOOKUP(Table10[[#This Row],[NAME]],ECR!C:E,3,FALSE()) -> RB21 | T28: =VLOOKUP(M28,Aggregate!P:X,9,FALSE()) -> 30.569875 | V28: =IFERROR(VLOOKUP(Table11[[#This Row],[NAME]],Aggregate!$AD:$AO,11,FALSE()),"") -> 5 | W28: =Aggregate!AD26 -> Terry McLaurin | X28: =VLOOKUP(Table11[[#This Row],[NAME]],Aggregate!AD:AO,4,FALSE()) -> WAS/7 | Y28: =IFERROR(VLOOKUP(Table11[[#This Row],[NAME]],Aggregate!$AD:$AO,8,FALSE()),"") -> 143.83584 | Z28: =IF(Scoring!$K$6="Auction",IFERROR(VLOOKUP(Table11[[#This Row],[NAME]],Aggregate!$AD:$AO,10,FALSE()),""),IFERROR(VLOOKUP(Table11[[#This Row],[NAME]],Aggregate!$AD:$AO,9,FALSE()),"")) -> 18.157963 | AA28: =SUMIFS(AD29:$AD$84,AC29:$AC$84,"<>x",AC29:$AC$84,"<>o",AD29:$AD$84,">0")/Aggregate!$AL$1 -> 0.04734874 | AB28: =VLOOKUP(Table11[[#This Row],[NAME]],ECR!C:E,3,FALSE()) -> WR24 | AD28: =VLOOKUP(W28,Aggregate!AD:AL,9,FALSE()) -> 18.157963
B29: =IFERROR(VLOOKUP(Table9[[#This Row],[NAME]],Aggregate!$B:$M,11,FALSE()),"") -> 13 | C29: =Aggregate!B28 -> Bryce Young | D29: =VLOOKUP(Table9[[#This Row],[NAME]],Aggregate!B:M,4,FALSE()) -> CAR/5 | E29: =IFERROR(VLOOKUP(Table9[[#This Row],[NAME]],Aggregate!$B:$M,8,FALSE()),"") -> 202.31991 | F29: =IF(Scoring!$K$6="Auction",IFERROR(VLOOKUP(Table9[[#This Row],[NAME]],Aggregate!$B:$M,10,FALSE()),""),IFERROR(VLOOKUP(Table9[[#This Row],[NAME]],Aggregate!$B:$M,9,FALSE()),"")) -> -66.05946 | G29: =SUMIFS(J30:$J$44,I30:$I$44,"<>x",I30:$I$44,"<>o",J30:$J$44,">0")/Aggregate!$J$1 -> 0 | H29: =VLOOKUP(Table9[[#This Row],[NAME]],ECR!C:E,3,FALSE()) -> QB26 | J29: =VLOOKUP(C29,Aggregate!B:J,9,FALSE()) -> -66.05946 | L29: =IFERROR(VLOOKUP(Table10[[#This Row],[NAME]],Aggregate!$P:$AA,11,FALSE()),"") -> 6 | M29: =Aggregate!P27 -> TreVeyon Henderson | N29: =VLOOKUP(Table10[[#This Row],[NAME]],Aggregate!P:AA,4,FALSE()) -> NE/11 | O29: =IFERROR(VLOOKUP(Table10[[#This Row],[NAME]],Aggregate!$P:$AA,8,FALSE()),"") -> 145.41956 | P29: =IF(Scoring!$K$6="Auction",IFERROR(VLOOKUP(Table10[[#This Row],[NAME]],Aggregate!$P:$AA,10,FALSE()),""),IFERROR(VLOOKUP(Table10[[#This Row],[NAME]],Aggregate!$P:$AA,9,FALSE()),"")) -> 17.873822 | Q29: =SUMIFS(T30:$T$84,S30:$S$84,"<>x",S30:$S$84,"<>o",T30:$T$84,">0")/Aggregate!$X$1 -> 0.033741046 | R29: =VLOOKUP(Table10[[#This Row],[NAME]],ECR!C:E,3,FALSE()) -> RB25 | T29: =VLOOKUP(M29,Aggregate!P:X,9,FALSE()) -> 17.873822 | V29: =IFERROR(VLOOKUP(Table11[[#This Row],[NAME]],Aggregate!$AD:$AO,11,FALSE()),"") -> 5 | W29: =Aggregate!AD24 -> Luther Burden III | X29: =VLOOKUP(Table11[[#This Row],[NAME]],Aggregate!AD:AO,4,FALSE()) -> CHI/10 | Y29: =IFERROR(VLOOKUP(Table11[[#This Row],[NAME]],Aggregate!$AD:$AO,8,FALSE()),"") -> 143.41115 | Z29: =IF(Scoring!$K$6="Auction",IFERROR(VLOOKUP(Table11[[#This Row],[NAME]],Aggregate!$AD:$AO,10,FALSE()),""),IFERROR(VLOOKUP(Table11[[#This Row],[NAME]],Aggregate!$AD:$AO,9,FALSE()),"")) -> 17.733269 | AA29: =SUMIFS(AD30:$AD$84,AC30:$AC$84,"<>x",AC30:$AC$84,"<>o",AD30:$AD$84,">0")/Aggregate!$AL$1 -> 0.034627884 | AB29: =VLOOKUP(Table11[[#This Row],[NAME]],ECR!C:E,3,FALSE()) -> WR22 | AD29: =VLOOKUP(W29,Aggregate!AD:AL,9,FALSE()) -> 17.733269
B30: =IFERROR(VLOOKUP(Table9[[#This Row],[NAME]],Aggregate!$B:$M,11,FALSE()),"") -> 14 | C30: =Aggregate!B27 -> Cam Ward | D30: =VLOOKUP(Table9[[#This Row],[NAME]],Aggregate!B:M,4,FALSE()) -> TEN/9 | E30: =IFERROR(VLOOKUP(Table9[[#This Row],[NAME]],Aggregate!$B:$M,8,FALSE()),"") -> 194.52696 | F30: =IF(Scoring!$K$6="Auction",IFERROR(VLOOKUP(Table9[[#This Row],[NAME]],Aggregate!$B:$M,10,FALSE()),""),IFERROR(VLOOKUP(Table9[[#This Row],[NAME]],Aggregate!$B:$M,9,FALSE()),"")) -> -73.852401 | G30: =SUMIFS(J31:$J$44,I31:$I$44,"<>x",I31:$I$44,"<>o",J31:$J$44,">0")/Aggregate!$J$1 -> 0 | H30: =VLOOKUP(Table9[[#This Row],[NAME]],ECR!C:E,3,FALSE()) -> QB25 | J30: =VLOOKUP(C30,Aggregate!B:J,9,FALSE()) -> -73.852401 | L30: =IFERROR(VLOOKUP(Table10[[#This Row],[NAME]],Aggregate!$P:$AA,11,FALSE()),"") -> 6 | M30: =Aggregate!P29 -> Jaylen Warren | N30: =VLOOKUP(Table10[[#This Row],[NAME]],Aggregate!P:AA,4,FALSE()) -> PIT/9 | O30: =IFERROR(VLOOKUP(Table10[[#This Row],[NAME]],Aggregate!$P:$AA,8,FALSE()),"") -> 143.97151 | P30: =IF(Scoring!$K$6="Auction",IFERROR(VLOOKUP(Table10[[#This Row],[NAME]],Aggregate!$P:$AA,10,FALSE()),""),IFERROR(VLOOKUP(Table10[[#This Row],[NAME]],Aggregate!$P:$AA,9,FALSE()),"")) -> 16.425767 | Q30: =SUMIFS(T31:$T$84,S31:$S$84,"<>x",S31:$S$84,"<>o",T31:$T$84,">0")/Aggregate!$X$1 -> 0.024868565 | R30: =VLOOKUP(Table10[[#This Row],[NAME]],ECR!C:E,3,FALSE()) -> RB27 | T30: =VLOOKUP(M30,Aggregate!P:X,9,FALSE()) -> 16.425767 | V30: =IFERROR(VLOOKUP(Table11[[#This Row],[NAME]],Aggregate!$AD:$AO,11,FALSE()),"") -> 5 | W30: =Aggregate!AD28 -> DJ Moore | X30: =VLOOKUP(Table11[[#This Row],[NAME]],Aggregate!AD:AO,4,FALSE()) -> BUF/7 | Y30: =IFERROR(VLOOKUP(Table11[[#This Row],[NAME]],Aggregate!$AD:$AO,8,FALSE()),"") -> 139.48911 | Z30: =IF(Scoring!$K$6="Auction",IFERROR(VLOOKUP(Table11[[#This Row],[NAME]],Aggregate!$AD:$AO,10,FALSE()),""),IFERROR(VLOOKUP(Table11[[#This Row],[NAME]],Aggregate!$AD:$AO,9,FALSE()),"")) -> 13.811232 | AA30: =SUMIFS(AD31:$AD$84,AC31:$AC$84,"<>x",AC31:$AC$84,"<>o",AD31:$AD$84,">0")/Aggregate!$AL$1 -> 0.024720478 | AB30: =VLOOKUP(Table11[[#This Row],[NAME]],ECR!C:E,3,FALSE()) -> WR26 | AD30: =VLOOKUP(W30,Aggregate!AD:AL,9,FALSE()) -> 13.811232
B31: =IFERROR(VLOOKUP(Table9[[#This Row],[NAME]],Aggregate!$B:$M,11,FALSE()),"") -> 15 | C31: =Aggregate!B29 -> Jacoby Brissett | D31: =VLOOKUP(Table9[[#This Row],[NAME]],Aggregate!B:M,4,FALSE()) -> ARI/14 | E31: =IFERROR(VLOOKUP(Table9[[#This Row],[NAME]],Aggregate!$B:$M,8,FALSE()),"") -> 187.23407 | F31: =IF(Scoring!$K$6="Auction",IFERROR(VLOOKUP(Table9[[#This Row],[NAME]],Aggregate!$B:$M,10,FALSE()),""),IFERROR(VLOOKUP(Table9[[#This Row],[NAME]],Aggregate!$B:$M,9,FALSE()),"")) -> -81.145295 | G31: =SUMIFS(J32:$J$44,I32:$I$44,"<>x",I32:$I$44,"<>o",J32:$J$44,">0")/Aggregate!$J$1 -> 0 | H31: =VLOOKUP(Table9[[#This Row],[NAME]],ECR!C:E,3,FALSE()) -> QB27 | J31: =VLOOKUP(C31,Aggregate!B:J,9,FALSE()) -> -81.145295 | L31: =IFERROR(VLOOKUP(Table10[[#This Row],[NAME]],Aggregate!$P:$AA,11,FALSE()),"") -> 6 | M31: =Aggregate!P28 -> Rhamondre Stevenson | N31: =VLOOKUP(Table10[[#This Row],[NAME]],Aggregate!P:AA,4,FALSE()) -> NE/11 | O31: =IFERROR(VLOOKUP(Table10[[#This Row],[NAME]],Aggregate!$P:$AA,8,FALSE()),"") -> 142.51983 | P31: =IF(Scoring!$K$6="Auction",IFERROR(VLOOKUP(Table10[[#This Row],[NAME]],Aggregate!$P:$AA,10,FALSE()),""),IFERROR(VLOOKUP(Table10[[#This Row],[NAME]],Aggregate!$P:$AA,9,FALSE()),"")) -> 14.974089 | Q31: =SUMIFS(T32:$T$84,S32:$S$84,"<>x",S32:$S$84,"<>o",T32:$T$84,">0")/Aggregate!$X$1 -> 0.016780217 | R31: =VLOOKUP(Table10[[#This Row],[NAME]],ECR!C:E,3,FALSE()) -> RB26 | T31: =VLOOKUP(M31,Aggregate!P:X,9,FALSE()) -> 14.974089 | V31: =IFERROR(VLOOKUP(Table11[[#This Row],[NAME]],Aggregate!$AD:$AO,11,FALSE()),"") -> 5 | W31: =Aggregate!AD30 -> Rome Odunze | X31: =VLOOKUP(Table11[[#This Row],[NAME]],Aggregate!AD:AO,4,FALSE()) -> CHI/10 | Y31: =IFERROR(VLOOKUP(Table11[[#This Row],[NAME]],Aggregate!$AD:$AO,8,FALSE()),"") -> 137.65801 | Z31: =IF(Scoring!$K$6="Auction",IFERROR(VLOOKUP(Table11[[#This Row],[NAME]],Aggregate!$AD:$AO,10,FALSE()),""),IFERROR(VLOOKUP(Table11[[#This Row],[NAME]],Aggregate!$AD:$AO,9,FALSE()),"")) -> 11.980131 | AA31: =SUMIFS(AD32:$AD$84,AC32:$AC$84,"<>x",AC32:$AC$84,"<>o",AD32:$AD$84,">0")/Aggregate!$AL$1 -> 0.016126602 | AB31: =VLOOKUP(Table11[[#This Row],[NAME]],ECR!C:E,3,FALSE()) -> WR28 | AD31: =VLOOKUP(W31,Aggregate!AD:AL,9,FALSE()) -> 11.980131
B32: =IFERROR(VLOOKUP(Table9[[#This Row],[NAME]],Aggregate!$B:$M,11,FALSE()),"") -> 15 | C32: =Aggregate!B31 -> Geno Smith | D32: =VLOOKUP(Table9[[#This Row],[NAME]],Aggregate!B:M,4,FALSE()) -> NYJ/13 | E32: =IFERROR(VLOOKUP(Table9[[#This Row],[NAME]],Aggregate!$B:$M,8,FALSE()),"") -> 186.63715 | F32: =IF(Scoring!$K$6="Auction",IFERROR(VLOOKUP(Table9[[#This Row],[NAME]],Aggregate!$B:$M,10,FALSE()),""),IFERROR(VLOOKUP(Table9[[#This Row],[NAME]],Aggregate!$B:$M,9,FALSE()),"")) -> -81.742213 | G32: =SUMIFS(J33:$J$44,I33:$I$44,"<>x",I33:$I$44,"<>o",J33:$J$44,">0")/Aggregate!$J$1 -> 0 | H32: =VLOOKUP(Table9[[#This Row],[NAME]],ECR!C:E,3,FALSE()) -> QB29 | J32: =VLOOKUP(C32,Aggregate!B:J,9,FALSE()) -> -81.742213 | L32: =IFERROR(VLOOKUP(Table10[[#This Row],[NAME]],Aggregate!$P:$AA,11,FALSE()),"") -> 6 | M32: =Aggregate!P30 -> Tony Pollard | N32: =VLOOKUP(Table10[[#This Row],[NAME]],Aggregate!P:AA,4,FALSE()) -> TEN/9 | O32: =IFERROR(VLOOKUP(Table10[[#This Row],[NAME]],Aggregate!$P:$AA,8,FALSE()),"") -> 141.90546 | P32: =IF(Scoring!$K$6="Auction",IFERROR(VLOOKUP(Table10[[#This Row],[NAME]],Aggregate!$P:$AA,10,FALSE()),""),IFERROR(VLOOKUP(Table10[[#This Row],[NAME]],Aggregate!$P:$AA,9,FALSE()),"")) -> 14.359719 | Q32: =SUMIFS(T33:$T$84,S33:$S$84,"<>x",S33:$S$84,"<>o",T33:$T$84,">0")/Aggregate!$X$1 -> 0.0090237242 | R32: =VLOOKUP(Table10[[#This Row],[NAME]],ECR!C:E,3,FALSE()) -> RB28 | T32: =VLOOKUP(M32,Aggregate!P:X,9,FALSE()) -> 14.359719 | V32: =IFERROR(VLOOKUP(Table11[[#This Row],[NAME]],Aggregate!$AD:$AO,11,FALSE()),"") -> 5 | W32: =Aggregate!AD29 -> Christian Watson | X32: =VLOOKUP(Table11[[#This Row],[NAME]],Aggregate!AD:AO,4,FALSE()) -> GB/11 | Y32: =IFERROR(VLOOKUP(Table11[[#This Row],[NAME]],Aggregate!$AD:$AO,8,FALSE()),"") -> 136.94331 | Z32: =IF(Scoring!$K$6="Auction",IFERROR(VLOOKUP(Table11[[#This Row],[NAME]],Aggregate!$AD:$AO,10,FALSE()),""),IFERROR(VLOOKUP(Table11[[#This Row],[NAME]],Aggregate!$AD:$AO,9,FALSE()),"")) -> 11.265427 | AA32: =SUMIFS(AD33:$AD$84,AC33:$AC$84,"<>x",AC33:$AC$84,"<>o",AD33:$AD$84,">0")/Aggregate!$AL$1 -> 0.0080454146 | AB32: =VLOOKUP(Table11[[#This Row],[NAME]],ECR!C:E,3,FALSE()) -> WR27 | AD32: =VLOOKUP(W32,Aggregate!AD:AL,9,FALSE()) -> 11.265427
B33: =IFERROR(VLOOKUP(Table9[[#This Row],[NAME]],Aggregate!$B:$M,11,FALSE()),"") -> 15 | C33: =Aggregate!B30 -> Aaron Rodgers | D33: =VLOOKUP(Table9[[#This Row],[NAME]],Aggregate!B:M,4,FALSE()) -> PIT/9 | E33: =IFERROR(VLOOKUP(Table9[[#This Row],[NAME]],Aggregate!$B:$M,8,FALSE()),"") -> 182.12212 | F33: =IF(Scoring!$K$6="Auction",IFERROR(VLOOKUP(Table9[[#This Row],[NAME]],Aggregate!$B:$M,10,FALSE()),""),IFERROR(VLOOKUP(Table9[[#This Row],[NAME]],Aggregate!$B:$M,9,FALSE()),"")) -> -86.257248 | G33: =SUMIFS(J34:$J$44,I34:$I$44,"<>x",I34:$I$44,"<>o",J34:$J$44,">0")/Aggregate!$J$1 -> 0 | H33: =VLOOKUP(Table9[[#This Row],[NAME]],ECR!C:E,3,FALSE()) -> QB28 | J33: =VLOOKUP(C33,Aggregate!B:J,9,FALSE()) -> -86.257248 | L33: =IFERROR(VLOOKUP(Table10[[#This Row],[NAME]],Aggregate!$P:$AA,11,FALSE()),"") -> 6 | M33: =Aggregate!P31 -> Rico Dowdle | N33: =VLOOKUP(Table10[[#This Row],[NAME]],Aggregate!P:AA,4,FALSE()) -> PIT/9 | O33: =IFERROR(VLOOKUP(Table10[[#This Row],[NAME]],Aggregate!$P:$AA,8,FALSE()),"") -> 137.54797 | P33: =IF(Scoring!$K$6="Auction",IFERROR(VLOOKUP(Table10[[#This Row],[NAME]],Aggregate!$P:$AA,10,FALSE()),""),IFERROR(VLOOKUP(Table10[[#This Row],[NAME]],Aggregate!$P:$AA,9,FALSE()),"")) -> 10.002229 | Q33: =SUMIFS(T34:$T$84,S34:$S$84,"<>x",S34:$S$84,"<>o",T34:$T$84,">0")/Aggregate!$X$1 -> 0.0036209572 | R33: =VLOOKUP(Table10[[#This Row],[NAME]],ECR!C:E,3,FALSE()) -> RB29 | T33: =VLOOKUP(M33,Aggregate!P:X,9,FALSE()) -> 10.002229 | V33: =IFERROR(VLOOKUP(Table11[[#This Row],[NAME]],Aggregate!$AD:$AO,11,FALSE()),"") -> 6 | W33: =Aggregate!AD31 -> Mike Evans | X33: =VLOOKUP(Table11[[#This Row],[NAME]],Aggregate!AD:AO,4,FALSE()) -> SF/8 | Y33: =IFERROR(VLOOKUP(Table11[[#This Row],[NAME]],Aggregate!$AD:$AO,8,FALSE()),"") -> 129.4416 | Z33: =IF(Scoring!$K$6="Auction",IFERROR(VLOOKUP(Table11[[#This Row],[NAME]],Aggregate!$AD:$AO,10,FALSE()),""),IFERROR(VLOOKUP(Table11[[#This Row],[NAME]],Aggregate!$AD:$AO,9,FALSE()),"")) -> 3.7637235 | AA33: =SUMIFS(AD34:$AD$84,AC34:$AC$84,"<>x",AC34:$AC$84,"<>o",AD34:$AD$84,">0")/Aggregate!$AL$1 -> 0.0053455298 | AB33: =VLOOKUP(Table11[[#This Row],[NAME]],ECR!C:E,3,FALSE()) -> WR29 | AD33: =VLOOKUP(W33,Aggregate!AD:AL,9,FALSE()) -> 3.7637235
B34: =IFERROR(VLOOKUP(Table9[[#This Row],[NAME]],Aggregate!$B:$M,11,FALSE()),"") -> 15 | C34: =Aggregate!B32 -> Fernando Mendoza | D34: =VLOOKUP(Table9[[#This Row],[NAME]],Aggregate!B:M,4,FALSE()) -> LV/13 | E34: =IFERROR(VLOOKUP(Table9[[#This Row],[NAME]],Aggregate!$B:$M,8,FALSE()),"") -> 155.55144 | F34: =IF(Scoring!$K$6="Auction",IFERROR(VLOOKUP(Table9[[#This Row],[NAME]],Aggregate!$B:$M,10,FALSE()),""),IFERROR(VLOOKUP(Table9[[#This Row],[NAME]],Aggregate!$B:$M,9,FALSE()),"")) -> -112.82793 | G34: =SUMIFS(J35:$J$44,I35:$I$44,"<>x",I35:$I$44,"<>o",J35:$J$44,">0")/Aggregate!$J$1 -> 0 | H34: =VLOOKUP(Table9[[#This Row],[NAME]],ECR!C:E,3,FALSE()) -> QB30 | J34: =VLOOKUP(C34,Aggregate!B:J,9,FALSE()) -> -112.82793 | L34: =IFERROR(VLOOKUP(Table10[[#This Row],[NAME]],Aggregate!$P:$AA,11,FALSE()),"") -> 6 | M34: =Aggregate!P33 -> J.K. Dobbins | N34: =VLOOKUP(Table10[[#This Row],[NAME]],Aggregate!P:AA,4,FALSE()) -> DEN/10 | O34: =IFERROR(VLOOKUP(Table10[[#This Row],[NAME]],Aggregate!$P:$AA,8,FALSE()),"") -> 134.24927 | P34: =IF(Scoring!$K$6="Auction",IFERROR(VLOOKUP(Table10[[#This Row],[NAME]],Aggregate!$P:$AA,10,FALSE()),""),IFERROR(VLOOKUP(Table10[[#This Row],[NAME]],Aggregate!$P:$AA,9,FALSE()),"")) -> 6.7035364 | Q34: =SUMIFS(T35:$T$84,S35:$S$84,"<>x",S35:$S$84,"<>o",T35:$T$84,">0")/Aggregate!$X$1 -> 0 | R34: =VLOOKUP(Table10[[#This Row],[NAME]],ECR!C:E,3,FALSE()) -> RB31 | T34: =VLOOKUP(M34,Aggregate!P:X,9,FALSE()) -> 6.7035364 | V34: =IFERROR(VLOOKUP(Table11[[#This Row],[NAME]],Aggregate!$AD:$AO,11,FALSE()),"") -> 6 | W34: =Aggregate!AD33 -> Marvin Harrison Jr. | X34: =VLOOKUP(Table11[[#This Row],[NAME]],Aggregate!AD:AO,4,FALSE()) -> ARI/14 | Y34: =IFERROR(VLOOKUP(Table11[[#This Row],[NAME]],Aggregate!$AD:$AO,8,FALSE()),"") -> 128.56144 | Z34: =IF(Scoring!$K$6="Auction",IFERROR(VLOOKUP(Table11[[#This Row],[NAME]],Aggregate!$AD:$AO,10,FALSE()),""),IFERROR(VLOOKUP(Table11[[#This Row],[NAME]],Aggregate!$AD:$AO,9,FALSE()),"")) -> 2.8835639 | AA34: =SUMIFS(AD35:$AD$84,AC35:$AC$84,"<>x",AC35:$AC$84,"<>o",AD35:$AD$84,">0")/Aggregate!$AL$1 -> 0.0032770222 | AB34: =VLOOKUP(Table11[[#This Row],[NAME]],ECR!C:E,3,FALSE()) -> WR31 | AD34: =VLOOKUP(W34,Aggregate!AD:AL,9,FALSE()) -> 2.8835639
B35: =IFERROR(VLOOKUP(Table9[[#This Row],[NAME]],Aggregate!$B:$M,11,FALSE()),"") -> 15 | C35: =Aggregate!B34 -> Tua Tagovailoa | D35: =VLOOKUP(Table9[[#This Row],[NAME]],Aggregate!B:M,4,FALSE()) -> ATL/11 | E35: =IFERROR(VLOOKUP(Table9[[#This Row],[NAME]],Aggregate!$B:$M,8,FALSE()),"") -> 112.93325 | F35: =IF(Scoring!$K$6="Auction",IFERROR(VLOOKUP(Table9[[#This Row],[NAME]],Aggregate!$B:$M,10,FALSE()),""),IFERROR(VLOOKUP(Table9[[#This Row],[NAME]],Aggregate!$B:$M,9,FALSE()),"")) -> -155.44612 | G35: =SUMIFS(J36:$J$44,I36:$I$44,"<>x",I36:$I$44,"<>o",J36:$J$44,">0")/Aggregate!$J$1 -> 0 | H35: =VLOOKUP(Table9[[#This Row],[NAME]],ECR!C:E,3,FALSE()) -> QB32 | J35: =VLOOKUP(C35,Aggregate!B:J,9,FALSE()) -> -155.44612 | L35: =IFERROR(VLOOKUP(Table10[[#This Row],[NAME]],Aggregate!$P:$AA,11,FALSE()),"") -> 6 | M35: =Aggregate!P32 -> Jonathon Brooks | N35: =VLOOKUP(Table10[[#This Row],[NAME]],Aggregate!P:AA,4,FALSE()) -> CAR/5 | O35: =IFERROR(VLOOKUP(Table10[[#This Row],[NAME]],Aggregate!$P:$AA,8,FALSE()),"") -> 127.54574 | P35: =IF(Scoring!$K$6="Auction",IFERROR(VLOOKUP(Table10[[#This Row],[NAME]],Aggregate!$P:$AA,10,FALSE()),""),IFERROR(VLOOKUP(Table10[[#This Row],[NAME]],Aggregate!$P:$AA,9,FALSE()),"")) -> 0 | Q35: =SUMIFS(T36:$T$84,S36:$S$84,"<>x",S36:$S$84,"<>o",T36:$T$84,">0")/Aggregate!$X$1 -> 0 | R35: =VLOOKUP(Table10[[#This Row],[NAME]],ECR!C:E,3,FALSE()) -> RB30 | T35: =VLOOKUP(M35,Aggregate!P:X,9,FALSE()) -> 0 | V35: =IFERROR(VLOOKUP(Table11[[#This Row],[NAME]],Aggregate!$AD:$AO,11,FALSE()),"") -> 6 | W35: =Aggregate!AD34 -> Carnell Tate | X35: =VLOOKUP(Table11[[#This Row],[NAME]],Aggregate!AD:AO,4,FALSE()) -> TEN/9 | Y35: =IFERROR(VLOOKUP(Table11[[#This Row],[NAME]],Aggregate!$AD:$AO,8,FALSE()),"") -> 128.03009 | Z35: =IF(Scoring!$K$6="Auction",IFERROR(VLOOKUP(Table11[[#This Row],[NAME]],Aggregate!$AD:$AO,10,FALSE()),""),IFERROR(VLOOKUP(Table11[[#This Row],[NAME]],Aggregate!$AD:$AO,9,FALSE()),"")) -> 2.3522161 | AA35: =SUMIFS(AD36:$AD$84,AC36:$AC$84,"<>x",AC36:$AC$84,"<>o",AD36:$AD$84,">0")/Aggregate!$AL$1 -> 0.0015896739 | AB35: =VLOOKUP(Table11[[#This Row],[NAME]],ECR!C:E,3,FALSE()) -> WR32 | AD35: =VLOOKUP(W35,Aggregate!AD:AL,9,FALSE()) -> 2.3522161
B36: =IFERROR(VLOOKUP(Table9[[#This Row],[NAME]],Aggregate!$B:$M,11,FALSE()),"") -> 15 | C36: =Aggregate!B33 -> Michael Penix Jr. | D36: =VLOOKUP(Table9[[#This Row],[NAME]],Aggregate!B:M,4,FALSE()) -> ATL/11 | E36: =IFERROR(VLOOKUP(Table9[[#This Row],[NAME]],Aggregate!$B:$M,8,FALSE()),"") -> 91.619553 | F36: =IF(Scoring!$K$6="Auction",IFERROR(VLOOKUP(Table9[[#This Row],[NAME]],Aggregate!$B:$M,10,FALSE()),""),IFERROR(VLOOKUP(Table9[[#This Row],[NAME]],Aggregate!$B:$M,9,FALSE()),"")) -> -176.75981 | G36: =SUMIFS(J37:$J$44,I37:$I$44,"<>x",I37:$I$44,"<>o",J37:$J$44,">0")/Aggregate!$J$1 -> 0 | H36: =VLOOKUP(Table9[[#This Row],[NAME]],ECR!C:E,3,FALSE()) -> QB31 | J36: =VLOOKUP(C36,Aggregate!B:J,9,FALSE()) -> -176.75981 | L36: =IFERROR(VLOOKUP(Table10[[#This Row],[NAME]],Aggregate!$P:$AA,11,FALSE()),"") -> 6 | M36: =Aggregate!P36 -> Chuba Hubbard | N36: =VLOOKUP(Table10[[#This Row],[NAME]],Aggregate!P:AA,4,FALSE()) -> CAR/5 | O36: =IFERROR(VLOOKUP(Table10[[#This Row],[NAME]],Aggregate!$P:$AA,8,FALSE()),"") -> 125.45271 | P36: =IF(Scoring!$K$6="Auction",IFERROR(VLOOKUP(Table10[[#This Row],[NAME]],Aggregate!$P:$AA,10,FALSE()),""),IFERROR(VLOOKUP(Table10[[#This Row],[NAME]],Aggregate!$P:$AA,9,FALSE()),"")) -> -2.093028 | Q36: =SUMIFS(T37:$T$84,S37:$S$84,"<>x",S37:$S$84,"<>o",T37:$T$84,">0")/Aggregate!$X$1 -> 0 | R36: =VLOOKUP(Table10[[#This Row],[NAME]],ECR!C:E,3,FALSE()) -> RB34 | T36: =VLOOKUP(M36,Aggregate!P:X,9,FALSE()) -> -2.093028 | V36: =IFERROR(VLOOKUP(Table11[[#This Row],[NAME]],Aggregate!$AD:$AO,11,FALSE()),"") -> 6 | W36: =Aggregate!AD35 -> DK Metcalf | X36: =VLOOKUP(Table11[[#This Row],[NAME]],Aggregate!AD:AO,4,FALSE()) -> PIT/9 | Y36: =IFERROR(VLOOKUP(Table11[[#This Row],[NAME]],Aggregate!$AD:$AO,8,FALSE()),"") -> 127.89393 | Z36: =IF(Scoring!$K$6="Auction",IFERROR(VLOOKUP(Table11[[#This Row],[NAME]],Aggregate!$AD:$AO,10,FALSE()),""),IFERROR(VLOOKUP(Table11[[#This Row],[NAME]],Aggregate!$AD:$AO,9,FALSE()),"")) -> 2.2160548 | AA36: =SUMIFS(AD37:$AD$84,AC37:$AC$84,"<>x",AC37:$AC$84,"<>o",AD37:$AD$84,">0")/Aggregate!$AL$1 -> 0 | AB36: =VLOOKUP(Table11[[#This Row],[NAME]],ECR!C:E,3,FALSE()) -> WR33 | AD36: =VLOOKUP(W36,Aggregate!AD:AL,9,FALSE()) -> 2.2160548
B37: =IFERROR(VLOOKUP(Table9[[#This Row],[NAME]],Aggregate!$B:$M,11,FALSE()),"") -> 15 | C37: =Aggregate!B37 -> Deshaun Watson | D37: =VLOOKUP(Table9[[#This Row],[NAME]],Aggregate!B:M,4,FALSE()) -> CLE/11 | E37: =IFERROR(VLOOKUP(Table9[[#This Row],[NAME]],Aggregate!$B:$M,8,FALSE()),"") -> 86.203188 | F37: =IF(Scoring!$K$6="Auction",IFERROR(VLOOKUP(Table9[[#This Row],[NAME]],Aggregate!$B:$M,10,FALSE()),""),IFERROR(VLOOKUP(Table9[[#This Row],[NAME]],Aggregate!$B:$M,9,FALSE()),"")) -> -182.17618 | G37: =SUMIFS(J38:$J$44,I38:$I$44,"<>x",I38:$I$44,"<>o",J38:$J$44,">0")/Aggregate!$J$1 -> 0 | H37: =VLOOKUP(Table9[[#This Row],[NAME]],ECR!C:E,3,FALSE()) -> QB35 | J37: =VLOOKUP(C37,Aggregate!B:J,9,FALSE()) -> -182.17618 | L37: =IFERROR(VLOOKUP(Table10[[#This Row],[NAME]],Aggregate!$P:$AA,11,FALSE()),"") -> 7 | M37: =Aggregate!P35 -> MarShawn Lloyd | N37: =VLOOKUP(Table10[[#This Row],[NAME]],Aggregate!P:AA,4,FALSE()) -> GB/11 | O37: =IFERROR(VLOOKUP(Table10[[#This Row],[NAME]],Aggregate!$P:$AA,8,FALSE()),"") -> 123.43281 | P37: =IF(Scoring!$K$6="Auction",IFERROR(VLOOKUP(Table10[[#This Row],[NAME]],Aggregate!$P:$AA,10,FALSE()),""),IFERROR(VLOOKUP(Table10[[#This Row],[NAME]],Aggregate!$P:$AA,9,FALSE()),"")) -> -4.1129275 | Q37: =SUMIFS(T38:$T$84,S38:$S$84,"<>x",S38:$S$84,"<>o",T38:$T$84,">0")/Aggregate!$X$1 -> 0 | R37: =VLOOKUP(Table10[[#This Row],[NAME]],ECR!C:E,3,FALSE()) -> RB33 | T37: =VLOOKUP(M37,Aggregate!P:X,9,FALSE()) -> -4.1129275 | V37: =IFERROR(VLOOKUP(Table11[[#This Row],[NAME]],Aggregate!$AD:$AO,11,FALSE()),"") -> 6 | W37: =Aggregate!AD38 -> Courtland Sutton | X37: =VLOOKUP(Table11[[#This Row],[NAME]],Aggregate!AD:AO,4,FALSE()) -> DEN/10 | Y37: =IFERROR(VLOOKUP(Table11[[#This Row],[NAME]],Aggregate!$AD:$AO,8,FALSE()),"") -> 125.67788 | Z37: =IF(Scoring!$K$6="Auction",IFERROR(VLOOKUP(Table11[[#This Row],[NAME]],Aggregate!$AD:$AO,10,FALSE()),""),IFERROR(VLOOKUP(Table11[[#This Row],[NAME]],Aggregate!$AD:$AO,9,FALSE()),"")) -> 0 | AA37: =SUMIFS(AD38:$AD$84,AC38:$AC$84,"<>x",AC38:$AC$84,"<>o",AD38:$AD$84,">0")/Aggregate!$AL$1 -> 0 | AB37: =VLOOKUP(Table11[[#This Row],[NAME]],ECR!C:E,3,FALSE()) -> WR36 | AD37: =VLOOKUP(W37,Aggregate!AD:AL,9,FALSE()) -> 0
B38: =IFERROR(VLOOKUP(Table9[[#This Row],[NAME]],Aggregate!$B:$M,11,FALSE()),"") -> 15 | C38: =Aggregate!B36 -> Shedeur Sanders | D38: =VLOOKUP(Table9[[#This Row],[NAME]],Aggregate!B:M,4,FALSE()) -> CLE/11 | E38: =IFERROR(VLOOKUP(Table9[[#This Row],[NAME]],Aggregate!$B:$M,8,FALSE()),"") -> 81.5856 | F38: =IF(Scoring!$K$6="Auction",IFERROR(VLOOKUP(Table9[[#This Row],[NAME]],Aggregate!$B:$M,10,FALSE()),""),IFERROR(VLOOKUP(Table9[[#This Row],[NAME]],Aggregate!$B:$M,9,FALSE()),"")) -> -186.79377 | G38: =SUMIFS(J39:$J$44,I39:$I$44,"<>x",I39:$I$44,"<>o",J39:$J$44,">0")/Aggregate!$J$1 -> 0 | H38: =VLOOKUP(Table9[[#This Row],[NAME]],ECR!C:E,3,FALSE()) -> QB34 | J38: =VLOOKUP(C38,Aggregate!B:J,9,FALSE()) -> -186.79377 | L38: =IFERROR(VLOOKUP(Table10[[#This Row],[NAME]],Aggregate!$P:$AA,11,FALSE()),"") -> 7 | M38: =Aggregate!P40 -> Kenny Gainwell | N38: =VLOOKUP(Table10[[#This Row],[NAME]],Aggregate!P:AA,4,FALSE()) -> TB/10 | O38: =IFERROR(VLOOKUP(Table10[[#This Row],[NAME]],Aggregate!$P:$AA,8,FALSE()),"") -> 116.60266 | P38: =IF(Scoring!$K$6="Auction",IFERROR(VLOOKUP(Table10[[#This Row],[NAME]],Aggregate!$P:$AA,10,FALSE()),""),IFERROR(VLOOKUP(Table10[[#This Row],[NAME]],Aggregate!$P:$AA,9,FALSE()),"")) -> -10.943074 | Q38: =SUMIFS(T39:$T$84,S39:$S$84,"<>x",S39:$S$84,"<>o",T39:$T$84,">0")/Aggregate!$X$1 -> 0 | R38: =VLOOKUP(Table10[[#This Row],[NAME]],ECR!C:E,3,FALSE()) -> RB38 | T38: =VLOOKUP(M38,Aggregate!P:X,9,FALSE()) -> -10.943074 | V38: =IFERROR(VLOOKUP(Table11[[#This Row],[NAME]],Aggregate!$AD:$AO,11,FALSE()),"") -> 6 | W38: =Aggregate!AD32 -> Parker Washington | X38: =VLOOKUP(Table11[[#This Row],[NAME]],Aggregate!AD:AO,4,FALSE()) -> JAC/7 | Y38: =IFERROR(VLOOKUP(Table11[[#This Row],[NAME]],Aggregate!$AD:$AO,8,FALSE()),"") -> 124.73651 | Z38: =IF(Scoring!$K$6="Auction",IFERROR(VLOOKUP(Table11[[#This Row],[NAME]],Aggregate!$AD:$AO,10,FALSE()),""),IFERROR(VLOOKUP(Table11[[#This Row],[NAME]],Aggregate!$AD:$AO,9,FALSE()),"")) -> -0.94136398 | AA38: =SUMIFS(AD39:$AD$84,AC39:$AC$84,"<>x",AC39:$AC$84,"<>o",AD39:$AD$84,">0")/Aggregate!$AL$1 -> 0 | AB38: =VLOOKUP(Table11[[#This Row],[NAME]],ECR!C:E,3,FALSE()) -> WR30 | AD38: =VLOOKUP(W38,Aggregate!AD:AL,9,FALSE()) -> -0.94136398
B39: =IFERROR(VLOOKUP(Table9[[#This Row],[NAME]],Aggregate!$B:$M,11,FALSE()),"") -> 15 | C39: =Aggregate!B35 -> Kirk Cousins | D39: =VLOOKUP(Table9[[#This Row],[NAME]],Aggregate!B:M,4,FALSE()) -> LV/13 | E39: =IFERROR(VLOOKUP(Table9[[#This Row],[NAME]],Aggregate!$B:$M,8,FALSE()),"") -> 54.029435 | F39: =IF(Scoring!$K$6="Auction",IFERROR(VLOOKUP(Table9[[#This Row],[NAME]],Aggregate!$B:$M,10,FALSE()),""),IFERROR(VLOOKUP(Table9[[#This Row],[NAME]],Aggregate!$B:$M,9,FALSE()),"")) -> -214.34993 | G39: =SUMIFS(J40:$J$44,I40:$I$44,"<>x",I40:$I$44,"<>o",J40:$J$44,">0")/Aggregate!$J$1 -> 0 | H39: =VLOOKUP(Table9[[#This Row],[NAME]],ECR!C:E,3,FALSE()) -> QB33 | J39: =VLOOKUP(C39,Aggregate!B:J,9,FALSE()) -> -214.34993 | L39: =IFERROR(VLOOKUP(Table10[[#This Row],[NAME]],Aggregate!$P:$AA,11,FALSE()),"") -> 7 | M39: =Aggregate!P37 -> RJ Harvey | N39: =VLOOKUP(Table10[[#This Row],[NAME]],Aggregate!P:AA,4,FALSE()) -> DEN/10 | O39: =IFERROR(VLOOKUP(Table10[[#This Row],[NAME]],Aggregate!$P:$AA,8,FALSE()),"") -> 115.74526 | P39: =IF(Scoring!$K$6="Auction",IFERROR(VLOOKUP(Table10[[#This Row],[NAME]],Aggregate!$P:$AA,10,FALSE()),""),IFERROR(VLOOKUP(Table10[[#This Row],[NAME]],Aggregate!$P:$AA,9,FALSE()),"")) -> -11.800476 | Q39: =SUMIFS(T40:$T$84,S40:$S$84,"<>x",S40:$S$84,"<>o",T40:$T$84,">0")/Aggregate!$X$1 -> 0 | R39: =VLOOKUP(Table10[[#This Row],[NAME]],ECR!C:E,3,FALSE()) -> RB35 | T39: =VLOOKUP(M39,Aggregate!P:X,9,FALSE()) -> -11.800476 | V39: =IFERROR(VLOOKUP(Table11[[#This Row],[NAME]],Aggregate!$AD:$AO,11,FALSE()),"") -> 6 | W39: =Aggregate!AD42 -> Alec Pierce | X39: =VLOOKUP(Table11[[#This Row],[NAME]],Aggregate!AD:AO,4,FALSE()) -> IND/13 | Y39: =IFERROR(VLOOKUP(Table11[[#This Row],[NAME]],Aggregate!$AD:$AO,8,FALSE()),"") -> 123.23267 | Z39: =IF(Scoring!$K$6="Auction",IFERROR(VLOOKUP(Table11[[#This Row],[NAME]],Aggregate!$AD:$AO,10,FALSE()),""),IFERROR(VLOOKUP(Table11[[#This Row],[NAME]],Aggregate!$AD:$AO,9,FALSE()),"")) -> -2.4452065 | AA39: =SUMIFS(AD40:$AD$84,AC40:$AC$84,"<>x",AC40:$AC$84,"<>o",AD40:$AD$84,">0")/Aggregate!$AL$1 -> 0 | AB39: =VLOOKUP(Table11[[#This Row],[NAME]],ECR!C:E,3,FALSE()) -> WR40 | AD39: =VLOOKUP(W39,Aggregate!AD:AL,9,FALSE()) -> -2.4452065
B40: =IFERROR(VLOOKUP(Table9[[#This Row],[NAME]],Aggregate!$B:$M,11,FALSE()),"") -> 15 | C40: =Aggregate!B38 -> Carson Beck | D40: =VLOOKUP(Table9[[#This Row],[NAME]],Aggregate!B:M,4,FALSE()) -> ARI/14 | E40: =IFERROR(VLOOKUP(Table9[[#This Row],[NAME]],Aggregate!$B:$M,8,FALSE()),"") -> 24.173271 | F40: =IF(Scoring!$K$6="Auction",IFERROR(VLOOKUP(Table9[[#This Row],[NAME]],Aggregate!$B:$M,10,FALSE()),""),IFERROR(VLOOKUP(Table9[[#This Row],[NAME]],Aggregate!$B:$M,9,FALSE()),"")) -> -244.2061 | G40: =SUMIFS(J41:$J$44,I41:$I$44,"<>x",I41:$I$44,"<>o",J41:$J$44,">0")/Aggregate!$J$1 -> 0 | H40: =VLOOKUP(Table9[[#This Row],[NAME]],ECR!C:E,3,FALSE()) -> QB36 | J40: =VLOOKUP(C40,Aggregate!B:J,9,FALSE()) -> -244.2061 | L40: =IFERROR(VLOOKUP(Table10[[#This Row],[NAME]],Aggregate!$P:$AA,11,FALSE()),"") -> 7 | M40: =Aggregate!P41 -> Kyle Monangai | N40: =VLOOKUP(Table10[[#This Row],[NAME]],Aggregate!P:AA,4,FALSE()) -> CHI/10 | O40: =IFERROR(VLOOKUP(Table10[[#This Row],[NAME]],Aggregate!$P:$AA,8,FALSE()),"") -> 115.19276 | P40: =IF(Scoring!$K$6="Auction",IFERROR(VLOOKUP(Table10[[#This Row],[NAME]],Aggregate!$P:$AA,10,FALSE()),""),IFERROR(VLOOKUP(Table10[[#This Row],[NAME]],Aggregate!$P:$AA,9,FALSE()),"")) -> -12.35298 | Q40: =SUMIFS(T41:$T$84,S41:$S$84,"<>x",S41:$S$84,"<>o",T41:$T$84,">0")/Aggregate!$X$1 -> 0 | R40: =VLOOKUP(Table10[[#This Row],[NAME]],ECR!C:E,3,FALSE()) -> RB39 | T40: =VLOOKUP(M40,Aggregate!P:X,9,FALSE()) -> -12.35298 | V40: =IFERROR(VLOOKUP(Table11[[#This Row],[NAME]],Aggregate!$AD:$AO,11,FALSE()),"") -> 6 | W40: =Aggregate!AD36 -> Brian Thomas Jr. | X40: =VLOOKUP(Table11[[#This Row],[NAME]],Aggregate!AD:AO,4,FALSE()) -> JAC/7 | Y40: =IFERROR(VLOOKUP(Table11[[#This Row],[NAME]],Aggregate!$AD:$AO,8,FALSE()),"") -> 122.0554 | Z40: =IF(Scoring!$K$6="Auction",IFERROR(VLOOKUP(Table11[[#This Row],[NAME]],Aggregate!$AD:$AO,10,FALSE()),""),IFERROR(VLOOKUP(Table11[[#This Row],[NAME]],Aggregate!$AD:$AO,9,FALSE()),"")) -> -3.6224749 | AA40: =SUMIFS(AD41:$AD$84,AC41:$AC$84,"<>x",AC41:$AC$84,"<>o",AD41:$AD$84,">0")/Aggregate!$AL$1 -> 0 | AB40: =VLOOKUP(Table11[[#This Row],[NAME]],ECR!C:E,3,FALSE()) -> WR34 | AD40: =VLOOKUP(W40,Aggregate!AD:AL,9,FALSE()) -> -3.6224749
B41: =IFERROR(VLOOKUP(Table9[[#This Row],[NAME]],Aggregate!$B:$M,11,FALSE()),"") -> 15 | C41: =Aggregate!B42 -> Ty Simpson | D41: =VLOOKUP(Table9[[#This Row],[NAME]],Aggregate!B:M,4,FALSE()) -> LAR/11 | E41: =IFERROR(VLOOKUP(Table9[[#This Row],[NAME]],Aggregate!$B:$M,8,FALSE()),"") -> 14.698894 | F41: =IF(Scoring!$K$6="Auction",IFERROR(VLOOKUP(Table9[[#This Row],[NAME]],Aggregate!$B:$M,10,FALSE()),""),IFERROR(VLOOKUP(Table9[[#This Row],[NAME]],Aggregate!$B:$M,9,FALSE()),"")) -> -253.68047 | G41: =SUMIFS(J42:$J$44,I42:$I$44,"<>x",I42:$I$44,"<>o",J42:$J$44,">0")/Aggregate!$J$1 -> 0 | H41: =VLOOKUP(Table9[[#This Row],[NAME]],ECR!C:E,3,FALSE()) -> QB40 | J41: =VLOOKUP(C41,Aggregate!B:J,9,FALSE()) -> -253.68047 | L41: =IFERROR(VLOOKUP(Table10[[#This Row],[NAME]],Aggregate!$P:$AA,11,FALSE()),"") -> 7 | M41: =Aggregate!P34 -> Blake Corum | N41: =VLOOKUP(Table10[[#This Row],[NAME]],Aggregate!P:AA,4,FALSE()) -> LAR/11 | O41: =IFERROR(VLOOKUP(Table10[[#This Row],[NAME]],Aggregate!$P:$AA,8,FALSE()),"") -> 114.92305 | P41: =IF(Scoring!$K$6="Auction",IFERROR(VLOOKUP(Table10[[#This Row],[NAME]],Aggregate!$P:$AA,10,FALSE()),""),IFERROR(VLOOKUP(Table10[[#This Row],[NAME]],Aggregate!$P:$AA,9,FALSE()),"")) -> -12.622684 | Q41: =SUMIFS(T42:$T$84,S42:$S$84,"<>x",S42:$S$84,"<>o",T42:$T$84,">0")/Aggregate!$X$1 -> 0 | R41: =VLOOKUP(Table10[[#This Row],[NAME]],ECR!C:E,3,FALSE()) -> RB32 | T41: =VLOOKUP(M41,Aggregate!P:X,9,FALSE()) -> -12.622684 | V41: =IFERROR(VLOOKUP(Table11[[#This Row],[NAME]],Aggregate!$AD:$AO,11,FALSE()),"") -> 6 | W41: =Aggregate!AD51 -> De'Zhaun Stribling | X41: =VLOOKUP(Table11[[#This Row],[NAME]],Aggregate!AD:AO,4,FALSE()) -> SF/8 | Y41: =IFERROR(VLOOKUP(Table11[[#This Row],[NAME]],Aggregate!$AD:$AO,8,FALSE()),"") -> 116.81847 | Z41: =IF(Scoring!$K$6="Auction",IFERROR(VLOOKUP(Table11[[#This Row],[NAME]],Aggregate!$AD:$AO,10,FALSE()),""),IFERROR(VLOOKUP(Table11[[#This Row],[NAME]],Aggregate!$AD:$AO,9,FALSE()),"")) -> -8.8594133 | AA41: =SUMIFS(AD42:$AD$84,AC42:$AC$84,"<>x",AC42:$AC$84,"<>o",AD42:$AD$84,">0")/Aggregate!$AL$1 -> 0 | AB41: =VLOOKUP(Table11[[#This Row],[NAME]],ECR!C:E,3,FALSE()) -> WR49 | AD41: =VLOOKUP(W41,Aggregate!AD:AL,9,FALSE()) -> -8.8594133
B42: =IFERROR(VLOOKUP(Table9[[#This Row],[NAME]],Aggregate!$B:$M,11,FALSE()),"") -> 15 | C42: =Aggregate!B40 -> J.J. McCarthy | D42: =VLOOKUP(Table9[[#This Row],[NAME]],Aggregate!B:M,4,FALSE()) -> MIN/6 | E42: =IFERROR(VLOOKUP(Table9[[#This Row],[NAME]],Aggregate!$B:$M,8,FALSE()),"") -> 11.659918 | F42: =IF(Scoring!$K$6="Auction",IFERROR(VLOOKUP(Table9[[#This Row],[NAME]],Aggregate!$B:$M,10,FALSE()),""),IFERROR(VLOOKUP(Table9[[#This Row],[NAME]],Aggregate!$B:$M,9,FALSE()),"")) -> -256.71945 | G42: =SUMIFS(J43:$J$44,I43:$I$44,"<>x",I43:$I$44,"<>o",J43:$J$44,">0")/Aggregate!$J$1 -> 0 | H42: =VLOOKUP(Table9[[#This Row],[NAME]],ECR!C:E,3,FALSE()) -> QB38 | J42: =VLOOKUP(C42,Aggregate!B:J,9,FALSE()) -> -256.71945 | L42: =IFERROR(VLOOKUP(Table10[[#This Row],[NAME]],Aggregate!$P:$AA,11,FALSE()),"") -> 7 | M42: =Aggregate!P39 -> Jacory Croskey-Merritt | N42: =VLOOKUP(Table10[[#This Row],[NAME]],Aggregate!P:AA,4,FALSE()) -> WAS/7 | O42: =IFERROR(VLOOKUP(Table10[[#This Row],[NAME]],Aggregate!$P:$AA,8,FALSE()),"") -> 114.15448 | P42: =IF(Scoring!$K$6="Auction",IFERROR(VLOOKUP(Table10[[#This Row],[NAME]],Aggregate!$P:$AA,10,FALSE()),""),IFERROR(VLOOKUP(Table10[[#This Row],[NAME]],Aggregate!$P:$AA,9,FALSE()),"")) -> -13.39126 | Q42: =SUMIFS(T43:$T$84,S43:$S$84,"<>x",S43:$S$84,"<>o",T43:$T$84,">0")/Aggregate!$X$1 -> 0 | R42: =VLOOKUP(Table10[[#This Row],[NAME]],ECR!C:E,3,FALSE()) -> RB37 | T42: =VLOOKUP(M42,Aggregate!P:X,9,FALSE()) -> -13.39126 | V42: =IFERROR(VLOOKUP(Table11[[#This Row],[NAME]],Aggregate!$AD:$AO,11,FALSE()),"") -> 6 | W42: =Aggregate!AD40 -> Michael Pittman Jr. | X42: =VLOOKUP(Table11[[#This Row],[NAME]],Aggregate!AD:AO,4,FALSE()) -> PIT/9 | Y42: =IFERROR(VLOOKUP(Table11[[#This Row],[NAME]],Aggregate!$AD:$AO,8,FALSE()),"") -> 116.27568 | Z42: =IF(Scoring!$K$6="Auction",IFERROR(VLOOKUP(Table11[[#This Row],[NAME]],Aggregate!$AD:$AO,10,FALSE()),""),IFERROR(VLOOKUP(Table11[[#This Row],[NAME]],Aggregate!$AD:$AO,9,FALSE()),"")) -> -9.4021999 | AA42: =SUMIFS(AD43:$AD$84,AC43:$AC$84,"<>x",AC43:$AC$84,"<>o",AD43:$AD$84,">0")/Aggregate!$AL$1 -> 0 | AB42: =VLOOKUP(Table11[[#This Row],[NAME]],ECR!C:E,3,FALSE()) -> WR38 | AD42: =VLOOKUP(W42,Aggregate!AD:AL,9,FALSE()) -> -9.4021999
B43: =IFERROR(VLOOKUP(Table9[[#This Row],[NAME]],Aggregate!$B:$M,11,FALSE()),"") -> 15 | C43: =Aggregate!B39 -> Mac Jones | D43: =VLOOKUP(Table9[[#This Row],[NAME]],Aggregate!B:M,4,FALSE()) -> SF/8 | E43: =IFERROR(VLOOKUP(Table9[[#This Row],[NAME]],Aggregate!$B:$M,8,FALSE()),"") -> 10.778071 | F43: =IF(Scoring!$K$6="Auction",IFERROR(VLOOKUP(Table9[[#This Row],[NAME]],Aggregate!$B:$M,10,FALSE()),""),IFERROR(VLOOKUP(Table9[[#This Row],[NAME]],Aggregate!$B:$M,9,FALSE()),"")) -> -257.6013 | G43: =SUMIFS(J44:$J$44,I44:$I$44,"<>x",I44:$I$44,"<>o",J44:$J$44,">0")/Aggregate!$J$1 -> 0 | H43: =VLOOKUP(Table9[[#This Row],[NAME]],ECR!C:E,3,FALSE()) -> QB37 | J43: =VLOOKUP(C43,Aggregate!B:J,9,FALSE()) -> -257.6013 | L43: =IFERROR(VLOOKUP(Table10[[#This Row],[NAME]],Aggregate!$P:$AA,11,FALSE()),"") -> 7 | M43: =Aggregate!P42 -> Rachaad White | N43: =VLOOKUP(Table10[[#This Row],[NAME]],Aggregate!P:AA,4,FALSE()) -> WAS/7 | O43: =IFERROR(VLOOKUP(Table10[[#This Row],[NAME]],Aggregate!$P:$AA,8,FALSE()),"") -> 114.0576 | P43: =IF(Scoring!$K$6="Auction",IFERROR(VLOOKUP(Table10[[#This Row],[NAME]],Aggregate!$P:$AA,10,FALSE()),""),IFERROR(VLOOKUP(Table10[[#This Row],[NAME]],Aggregate!$P:$AA,9,FALSE()),"")) -> -13.488141 | Q43: =SUMIFS(T44:$T$84,S44:$S$84,"<>x",S44:$S$84,"<>o",T44:$T$84,">0")/Aggregate!$X$1 -> 0 | R43: =VLOOKUP(Table10[[#This Row],[NAME]],ECR!C:E,3,FALSE()) -> RB40 | T43: =VLOOKUP(M43,Aggregate!P:X,9,FALSE()) -> -13.488141 | V43: =IFERROR(VLOOKUP(Table11[[#This Row],[NAME]],Aggregate!$AD:$AO,11,FALSE()),"") -> 6 | W43: =Aggregate!AD50 -> KC Concepcion | X43: =VLOOKUP(Table11[[#This Row],[NAME]],Aggregate!AD:AO,4,FALSE()) -> CLE/11 | Y43: =IFERROR(VLOOKUP(Table11[[#This Row],[NAME]],Aggregate!$AD:$AO,8,FALSE()),"") -> 114.7039 | Z43: =IF(Scoring!$K$6="Auction",IFERROR(VLOOKUP(Table11[[#This Row],[NAME]],Aggregate!$AD:$AO,10,FALSE()),""),IFERROR(VLOOKUP(Table11[[#This Row],[NAME]],Aggregate!$AD:$AO,9,FALSE()),"")) -> -10.973981 | AA43: =SUMIFS(AD44:$AD$84,AC44:$AC$84,"<>x",AC44:$AC$84,"<>o",AD44:$AD$84,">0")/Aggregate!$AL$1 -> 0 | AB43: =VLOOKUP(Table11[[#This Row],[NAME]],ECR!C:E,3,FALSE()) -> WR48 | AD43: =VLOOKUP(W43,Aggregate!AD:AL,9,FALSE()) -> -10.973981
B44: =IFERROR(VLOOKUP(Table9[[#This Row],[NAME]],Aggregate!$B:$M,11,FALSE()),"") -> 15 | C44: =Aggregate!B41 -> Justin Fields | D44: =VLOOKUP(Table9[[#This Row],[NAME]],Aggregate!B:M,4,FALSE()) -> KC/5 | E44: =IFERROR(VLOOKUP(Table9[[#This Row],[NAME]],Aggregate!$B:$M,8,FALSE()),"") -> 10.217682 | F44: =IF(Scoring!$K$6="Auction",IFERROR(VLOOKUP(Table9[[#This Row],[NAME]],Aggregate!$B:$M,10,FALSE()),""),IFERROR(VLOOKUP(Table9[[#This Row],[NAME]],Aggregate!$B:$M,9,FALSE()),"")) -> -258.16168 | G44: =SUMIFS(J$44:$J45,I$44:$I45,"<>x",I$44:$I45,"<>o",J$44:$J45,">0")/Aggregate!$J$1 -> 0 | H44: =VLOOKUP(Table9[[#This Row],[NAME]],ECR!C:E,3,FALSE()) -> QB39 | J44: =VLOOKUP(C44,Aggregate!B:J,9,FALSE()) -> -258.16168 | L44: =IFERROR(VLOOKUP(Table10[[#This Row],[NAME]],Aggregate!$P:$AA,11,FALSE()),"") -> 7 | M44: =Aggregate!P38 -> Jordan Mason | N44: =VLOOKUP(Table10[[#This Row],[NAME]],Aggregate!P:AA,4,FALSE()) -> MIN/6 | O44: =IFERROR(VLOOKUP(Table10[[#This Row],[NAME]],Aggregate!$P:$AA,8,FALSE()),"") -> 112.67656 | P44: =IF(Scoring!$K$6="Auction",IFERROR(VLOOKUP(Table10[[#This Row],[NAME]],Aggregate!$P:$AA,10,FALSE()),""),IFERROR(VLOOKUP(Table10[[#This Row],[NAME]],Aggregate!$P:$AA,9,FALSE()),"")) -> -14.869183 | Q44: =SUMIFS(T45:$T$84,S45:$S$84,"<>x",S45:$S$84,"<>o",T45:$T$84,">0")/Aggregate!$X$1 -> 0 | R44: =VLOOKUP(Table10[[#This Row],[NAME]],ECR!C:E,3,FALSE()) -> RB36 | T44: =VLOOKUP(M44,Aggregate!P:X,9,FALSE()) -> -14.869183 | V44: =IFERROR(VLOOKUP(Table11[[#This Row],[NAME]],Aggregate!$AD:$AO,11,FALSE()),"") -> 6 | W44: =Aggregate!AD39 -> Quentin Johnston | X44: =VLOOKUP(Table11[[#This Row],[NAME]],Aggregate!AD:AO,4,FALSE()) -> LAC/7 | Y44: =IFERROR(VLOOKUP(Table11[[#This Row],[NAME]],Aggregate!$AD:$AO,8,FALSE()),"") -> 114.41158 | Z44: =IF(Scoring!$K$6="Auction",IFERROR(VLOOKUP(Table11[[#This Row],[NAME]],Aggregate!$AD:$AO,10,FALSE()),""),IFERROR(VLOOKUP(Table11[[#This Row],[NAME]],Aggregate!$AD:$AO,9,FALSE()),"")) -> -11.266298 | AA44: =SUMIFS(AD45:$AD$84,AC45:$AC$84,"<>x",AC45:$AC$84,"<>o",AD45:$AD$84,">0")/Aggregate!$AL$1 -> 0 | AB44: =VLOOKUP(Table11[[#This Row],[NAME]],ECR!C:E,3,FALSE()) -> WR37 | AD44: =VLOOKUP(W44,Aggregate!AD:AL,9,FALSE()) -> -11.266298
L45: =IFERROR(VLOOKUP(Table10[[#This Row],[NAME]],Aggregate!$P:$AA,11,FALSE()),"") -> 7 | M45: =Aggregate!P43 -> Aaron Jones Sr. | N45: =VLOOKUP(Table10[[#This Row],[NAME]],Aggregate!P:AA,4,FALSE()) -> MIN/6 | O45: =IFERROR(VLOOKUP(Table10[[#This Row],[NAME]],Aggregate!$P:$AA,8,FALSE()),"") -> 111.97475 | P45: =IF(Scoring!$K$6="Auction",IFERROR(VLOOKUP(Table10[[#This Row],[NAME]],Aggregate!$P:$AA,10,FALSE()),""),IFERROR(VLOOKUP(Table10[[#This Row],[NAME]],Aggregate!$P:$AA,9,FALSE()),"")) -> -15.570984 | Q45: =SUMIFS(T46:$T$84,S46:$S$84,"<>x",S46:$S$84,"<>o",T46:$T$84,">0")/Aggregate!$X$1 -> 0 | R45: =VLOOKUP(Table10[[#This Row],[NAME]],ECR!C:E,3,FALSE()) -> RB41 | T45: =VLOOKUP(M45,Aggregate!P:X,9,FALSE()) -> -15.570984 | V45: =IFERROR(VLOOKUP(Table11[[#This Row],[NAME]],Aggregate!$AD:$AO,11,FALSE()),"") -> 6 | W45: =Aggregate!AD37 -> Chris Godwin Jr. | X45: =VLOOKUP(Table11[[#This Row],[NAME]],Aggregate!AD:AO,4,FALSE()) -> TB/10 | Y45: =IFERROR(VLOOKUP(Table11[[#This Row],[NAME]],Aggregate!$AD:$AO,8,FALSE()),"") -> 114.11041 | Z45: =IF(Scoring!$K$6="Auction",IFERROR(VLOOKUP(Table11[[#This Row],[NAME]],Aggregate!$AD:$AO,10,FALSE()),""),IFERROR(VLOOKUP(Table11[[#This Row],[NAME]],Aggregate!$AD:$AO,9,FALSE()),"")) -> -11.567472 | AA45: =SUMIFS(AD46:$AD$84,AC46:$AC$84,"<>x",AC46:$AC$84,"<>o",AD46:$AD$84,">0")/Aggregate!$AL$1 -> 0 | AB45: =VLOOKUP(Table11[[#This Row],[NAME]],ECR!C:E,3,FALSE()) -> WR35 | AD45: =VLOOKUP(W45,Aggregate!AD:AL,9,FALSE()) -> -11.567472
B46: TIGHT END | L46: =IFERROR(VLOOKUP(Table10[[#This Row],[NAME]],Aggregate!$P:$AA,11,FALSE()),"") -> 8 | M46: =Aggregate!P49 -> Mike Washington Jr. | N46: =VLOOKUP(Table10[[#This Row],[NAME]],Aggregate!P:AA,4,FALSE()) -> LV/13 | O46: =IFERROR(VLOOKUP(Table10[[#This Row],[NAME]],Aggregate!$P:$AA,8,FALSE()),"") -> 97.575485 | P46: =IF(Scoring!$K$6="Auction",IFERROR(VLOOKUP(Table10[[#This Row],[NAME]],Aggregate!$P:$AA,10,FALSE()),""),IFERROR(VLOOKUP(Table10[[#This Row],[NAME]],Aggregate!$P:$AA,9,FALSE()),"")) -> -29.970253 | Q46: =SUMIFS(T47:$T$84,S47:$S$84,"<>x",S47:$S$84,"<>o",T47:$T$84,">0")/Aggregate!$X$1 -> 0 | R46: =VLOOKUP(Table10[[#This Row],[NAME]],ECR!C:E,3,FALSE()) -> RB47 | T46: =VLOOKUP(M46,Aggregate!P:X,9,FALSE()) -> -29.970253 | V46: =IFERROR(VLOOKUP(Table11[[#This Row],[NAME]],Aggregate!$AD:$AO,11,FALSE()),"") -> 6 | W46: =Aggregate!AD41 -> Michael Wilson | X46: =VLOOKUP(Table11[[#This Row],[NAME]],Aggregate!AD:AO,4,FALSE()) -> ARI/14 | Y46: =IFERROR(VLOOKUP(Table11[[#This Row],[NAME]],Aggregate!$AD:$AO,8,FALSE()),"") -> 113.65432 | Z46: =IF(Scoring!$K$6="Auction",IFERROR(VLOOKUP(Table11[[#This Row],[NAME]],Aggregate!$AD:$AO,10,FALSE()),""),IFERROR(VLOOKUP(Table11[[#This Row],[NAME]],Aggregate!$AD:$AO,9,FALSE()),"")) -> -12.023554 | AA46: =SUMIFS(AD47:$AD$84,AC47:$AC$84,"<>x",AC47:$AC$84,"<>o",AD47:$AD$84,">0")/Aggregate!$AL$1 -> 0 | AB46: =VLOOKUP(Table11[[#This Row],[NAME]],ECR!C:E,3,FALSE()) -> WR39 | AD46: =VLOOKUP(W46,Aggregate!AD:AL,9,FALSE()) -> -12.023554
B47: TIER | C47: NAME | D47: TM/BYE | E47: PTS | F47: VALUE | G47: PS | H47: ECR | I47: DRAFT | L47: =IFERROR(VLOOKUP(Table10[[#This Row],[NAME]],Aggregate!$P:$AA,11,FALSE()),"") -> 8 | M47: =Aggregate!P46 -> Woody Marks | N47: =VLOOKUP(Table10[[#This Row],[NAME]],Aggregate!P:AA,4,FALSE()) -> HOU/8 | O47: =IFERROR(VLOOKUP(Table10[[#This Row],[NAME]],Aggregate!$P:$AA,8,FALSE()),"") -> 92.374831 | P47: =IF(Scoring!$K$6="Auction",IFERROR(VLOOKUP(Table10[[#This Row],[NAME]],Aggregate!$P:$AA,10,FALSE()),""),IFERROR(VLOOKUP(Table10[[#This Row],[NAME]],Aggregate!$P:$AA,9,FALSE()),"")) -> -35.170907 | Q47: =SUMIFS(T48:$T$84,S48:$S$84,"<>x",S48:$S$84,"<>o",T48:$T$84,">0")/Aggregate!$X$1 -> 0 | R47: =VLOOKUP(Table10[[#This Row],[NAME]],ECR!C:E,3,FALSE()) -> RB44 | T47: =VLOOKUP(M47,Aggregate!P:X,9,FALSE()) -> -35.170907 | V47: =IFERROR(VLOOKUP(Table11[[#This Row],[NAME]],Aggregate!$AD:$AO,11,FALSE()),"") -> 6 | W47: =Aggregate!AD46 -> Jayden Reed | X47: =VLOOKUP(Table11[[#This Row],[NAME]],Aggregate!AD:AO,4,FALSE()) -> GB/11 | Y47: =IFERROR(VLOOKUP(Table11[[#This Row],[NAME]],Aggregate!$AD:$AO,8,FALSE()),"") -> 112.50289 | Z47: =IF(Scoring!$K$6="Auction",IFERROR(VLOOKUP(Table11[[#This Row],[NAME]],Aggregate!$AD:$AO,10,FALSE()),""),IFERROR(VLOOKUP(Table11[[#This Row],[NAME]],Aggregate!$AD:$AO,9,FALSE()),"")) -> -13.174986 | AA47: =SUMIFS(AD48:$AD$84,AC48:$AC$84,"<>x",AC48:$AC$84,"<>o",AD48:$AD$84,">0")/Aggregate!$AL$1 -> 0 | AB47: =VLOOKUP(Table11[[#This Row],[NAME]],ECR!C:E,3,FALSE()) -> WR44 | AD47: =VLOOKUP(W47,Aggregate!AD:AL,9,FALSE()) -> -13.174986
B48: =IFERROR(VLOOKUP(Table12[[#This Row],[NAME]],Aggregate!$AR:$BC,11,FALSE()),"") -> 1 | C48: =Aggregate!AR3 -> Brock Bowers | D48: =VLOOKUP(Table12[[#This Row],[NAME]],Aggregate!AR:BD,4,FALSE()) -> LV/13 | E48: =IFERROR(VLOOKUP(Table12[[#This Row],[NAME]],Aggregate!$AR:$BC,8,FALSE()),"") -> 173.64043 | F48: =IF(Scoring!$K$6="Auction",IFERROR(VLOOKUP($C48,Aggregate!$AR:$BC,10,FALSE()),""),IFERROR(VLOOKUP($C48,Aggregate!$AR:$BC,9,FALSE()),"")) -> 61.066829 | G48: =SUMIFS(J49:$J$84,I49:$I$84,"<>x",I49:$I$84,"<>o",J49:$J$84,">0")/Aggregate!$AZ$1 -> 0.74250254 | H48: =VLOOKUP(Table12[[#This Row],[NAME]],ECR!C:E,3,FALSE()) -> TE1 | J48: =VLOOKUP(C48,Aggregate!AR:AZ,9,FALSE()) -> 61.066829 | L48: =IFERROR(VLOOKUP(Table10[[#This Row],[NAME]],Aggregate!$P:$AA,11,FALSE()),"") -> 8 | M48: =Aggregate!P48 -> Tyjae Spears | N48: =VLOOKUP(Table10[[#This Row],[NAME]],Aggregate!P:AA,4,FALSE()) -> TEN/9 | O48: =IFERROR(VLOOKUP(Table10[[#This Row],[NAME]],Aggregate!$P:$AA,8,FALSE()),"") -> 90.219987 | P48: =IF(Scoring!$K$6="Auction",IFERROR(VLOOKUP(Table10[[#This Row],[NAME]],Aggregate!$P:$AA,10,FALSE()),""),IFERROR(VLOOKUP(Table10[[#This Row],[NAME]],Aggregate!$P:$AA,9,FALSE()),"")) -> -37.325751 | Q48: =SUMIFS(T49:$T$84,S49:$S$84,"<>x",S49:$S$84,"<>o",T49:$T$84,">0")/Aggregate!$X$1 -> 0 | R48: =VLOOKUP(Table10[[#This Row],[NAME]],ECR!C:E,3,FALSE()) -> RB46 | T48: =VLOOKUP(M48,Aggregate!P:X,9,FALSE()) -> -37.325751 | V48: =IFERROR(VLOOKUP(Table11[[#This Row],[NAME]],Aggregate!$AD:$AO,11,FALSE()),"") -> 6 | W48: =Aggregate!AD48 -> Makai Lemon | X48: =VLOOKUP(Table11[[#This Row],[NAME]],Aggregate!AD:AO,4,FALSE()) -> PHI/10 | Y48: =IFERROR(VLOOKUP(Table11[[#This Row],[NAME]],Aggregate!$AD:$AO,8,FALSE()),"") -> 112.25666 | Z48: =IF(Scoring!$K$6="Auction",IFERROR(VLOOKUP(Table11[[#This Row],[NAME]],Aggregate!$AD:$AO,10,FALSE()),""),IFERROR(VLOOKUP(Table11[[#This Row],[NAME]],Aggregate!$AD:$AO,9,FALSE()),"")) -> -13.421214 | AA48: =SUMIFS(AD49:$AD$84,AC49:$AC$84,"<>x",AC49:$AC$84,"<>o",AD49:$AD$84,">0")/Aggregate!$AL$1 -> 0 | AB48: =VLOOKUP(Table11[[#This Row],[NAME]],ECR!C:E,3,FALSE()) -> WR46 | AD48: =VLOOKUP(W48,Aggregate!AD:AL,9,FALSE()) -> -13.421214
B49: =IFERROR(VLOOKUP(Table12[[#This Row],[NAME]],Aggregate!$AR:$BC,11,FALSE()),"") -> 1 | C49: =Aggregate!AR4 -> Trey McBride | D49: =VLOOKUP(Table12[[#This Row],[NAME]],Aggregate!AR:BD,4,FALSE()) -> ARI/14 | E49: =IFERROR(VLOOKUP($C49,Aggregate!$AR:$BC,8,FALSE()),"") -> 164.81305 | F49: =IF(Scoring!$K$6="Auction",IFERROR(VLOOKUP($C49,Aggregate!$AR:$BC,10,FALSE()),""),IFERROR(VLOOKUP($C49,Aggregate!$AR:$BC,9,FALSE()),"")) -> 52.239448 | G49: =SUMIFS(J50:$J$84,I50:$I$84,"<>x",I50:$I$84,"<>o",J50:$J$84,">0")/Aggregate!$AZ$1 -> 0.52222706 | H49: =VLOOKUP(Table12[[#This Row],[NAME]],ECR!C:E,3,FALSE()) -> TE2 | J49: =VLOOKUP(C49,Aggregate!AR:AZ,9,FALSE()) -> 52.239448 | L49: =IFERROR(VLOOKUP(Table10[[#This Row],[NAME]],Aggregate!$P:$AA,11,FALSE()),"") -> 8 | M49: =Aggregate!P59 -> Josh Jacobs | N49: =VLOOKUP(Table10[[#This Row],[NAME]],Aggregate!P:AA,4,FALSE()) -> GB/11 | O49: =IFERROR(VLOOKUP(Table10[[#This Row],[NAME]],Aggregate!$P:$AA,8,FALSE()),"") -> 86.511176 | P49: =IF(Scoring!$K$6="Auction",IFERROR(VLOOKUP(Table10[[#This Row],[NAME]],Aggregate!$P:$AA,10,FALSE()),""),IFERROR(VLOOKUP(Table10[[#This Row],[NAME]],Aggregate!$P:$AA,9,FALSE()),"")) -> -41.034562 | Q49: =SUMIFS(T50:$T$84,S50:$S$84,"<>x",S50:$S$84,"<>o",T50:$T$84,">0")/Aggregate!$X$1 -> 0 | R49: =VLOOKUP(Table10[[#This Row],[NAME]],ECR!C:E,3,FALSE()) -> RB57 | T49: =VLOOKUP(M49,Aggregate!P:X,9,FALSE()) -> -41.034562 | V49: =IFERROR(VLOOKUP(Table11[[#This Row],[NAME]],Aggregate!$AD:$AO,11,FALSE()),"") -> 7 | W49: =Aggregate!AD47 -> Jordan Addison | X49: =VLOOKUP(Table11[[#This Row],[NAME]],Aggregate!AD:AO,4,FALSE()) -> MIN/6 | Y49: =IFERROR(VLOOKUP(Table11[[#This Row],[NAME]],Aggregate!$AD:$AO,8,FALSE()),"") -> 110.29494 | Z49: =IF(Scoring!$K$6="Auction",IFERROR(VLOOKUP(Table11[[#This Row],[NAME]],Aggregate!$AD:$AO,10,FALSE()),""),IFERROR(VLOOKUP(Table11[[#This Row],[NAME]],Aggregate!$AD:$AO,9,FALSE()),"")) -> -15.382934 | AA49: =SUMIFS(AD50:$AD$84,AC50:$AC$84,"<>x",AC50:$AC$84,"<>o",AD50:$AD$84,">0")/Aggregate!$AL$1 -> 0 | AB49: =VLOOKUP(Table11[[#This Row],[NAME]],ECR!C:E,3,FALSE()) -> WR45 | AD49: =VLOOKUP(W49,Aggregate!AD:AL,9,FALSE()) -> -15.382934
B50: =IFERROR(VLOOKUP(Table12[[#This Row],[NAME]],Aggregate!$AR:$BC,11,FALSE()),"") -> 2 | C50: =Aggregate!AR5 -> Colston Loveland | D50: =VLOOKUP(Table12[[#This Row],[NAME]],Aggregate!AR:BD,4,FALSE()) -> CHI/10 | E50: =IFERROR(VLOOKUP($C50,Aggregate!$AR:$BC,8,FALSE()),"") -> 142.1439 | F50: =IF(Scoring!$K$6="Auction",IFERROR(VLOOKUP($C50,Aggregate!$AR:$BC,10,FALSE()),""),IFERROR(VLOOKUP($C50,Aggregate!$AR:$BC,9,FALSE()),"")) -> 29.570303 | G50: =SUMIFS(J51:$J$84,I51:$I$84,"<>x",I51:$I$84,"<>o",J51:$J$84,">0")/Aggregate!$AZ$1 -> 0.39753944 | H50: =VLOOKUP(Table12[[#This Row],[NAME]],ECR!C:E,3,FALSE()) -> TE3 | J50: =VLOOKUP(C50,Aggregate!AR:AZ,9,FALSE()) -> 29.570303 | L50: =IFERROR(VLOOKUP(Table10[[#This Row],[NAME]],Aggregate!$P:$AA,11,FALSE()),"") -> 8 | M50: =Aggregate!P44 -> Chris Rodriguez Jr. | N50: =VLOOKUP(Table10[[#This Row],[NAME]],Aggregate!P:AA,4,FALSE()) -> JAC/7 | O50: =IFERROR(VLOOKUP(Table10[[#This Row],[NAME]],Aggregate!$P:$AA,8,FALSE()),"") -> 85.472776 | P50: =IF(Scoring!$K$6="Auction",IFERROR(VLOOKUP(Table10[[#This Row],[NAME]],Aggregate!$P:$AA,10,FALSE()),""),IFERROR(VLOOKUP(Table10[[#This Row],[NAME]],Aggregate!$P:$AA,9,FALSE()),"")) -> -42.072963 | Q50: =SUMIFS(T51:$T$84,S51:$S$84,"<>x",S51:$S$84,"<>o",T51:$T$84,">0")/Aggregate!$X$1 -> 0 | R50: =VLOOKUP(Table10[[#This Row],[NAME]],ECR!C:E,3,FALSE()) -> RB42 | T50: =VLOOKUP(M50,Aggregate!P:X,9,FALSE()) -> -42.072963 | V50: =IFERROR(VLOOKUP(Table11[[#This Row],[NAME]],Aggregate!$AD:$AO,11,FALSE()),"") -> 7 | W50: =Aggregate!AD49 -> Jakobi Meyers | X50: =VLOOKUP(Table11[[#This Row],[NAME]],Aggregate!AD:AO,4,FALSE()) -> JAC/7 | Y50: =IFERROR(VLOOKUP(Table11[[#This Row],[NAME]],Aggregate!$AD:$AO,8,FALSE()),"") -> 110.08139 | Z50: =IF(Scoring!$K$6="Auction",IFERROR(VLOOKUP(Table11[[#This Row],[NAME]],Aggregate!$AD:$AO,10,FALSE()),""),IFERROR(VLOOKUP(Table11[[#This Row],[NAME]],Aggregate!$AD:$AO,9,FALSE()),"")) -> -15.596486 | AA50: =SUMIFS(AD51:$AD$84,AC51:$AC$84,"<>x",AC51:$AC$84,"<>o",AD51:$AD$84,">0")/Aggregate!$AL$1 -> 0 | AB50: =VLOOKUP(Table11[[#This Row],[NAME]],ECR!C:E,3,FALSE()) -> WR47 | AD50: =VLOOKUP(W50,Aggregate!AD:AL,9,FALSE()) -> -15.596486
B51: =IFERROR(VLOOKUP(Table12[[#This Row],[NAME]],Aggregate!$AR:$BC,11,FALSE()),"") -> 3 | C51: =Aggregate!AR6 -> Tyler Warren | D51: =VLOOKUP(Table12[[#This Row],[NAME]],Aggregate!AR:BD,4,FALSE()) -> IND/13 | E51: =IFERROR(VLOOKUP($C51,Aggregate!$AR:$BC,8,FALSE()),"") -> 131.38707 | F51: =IF(Scoring!$K$6="Auction",IFERROR(VLOOKUP($C51,Aggregate!$AR:$BC,10,FALSE()),""),IFERROR(VLOOKUP($C51,Aggregate!$AR:$BC,9,FALSE()),"")) -> 18.81347 | G51: =SUMIFS(J52:$J$84,I52:$I$84,"<>x",I52:$I$84,"<>o",J52:$J$84,">0")/Aggregate!$AZ$1 -> 0.31820962 | H51: =VLOOKUP(Table12[[#This Row],[NAME]],ECR!C:E,3,FALSE()) -> TE4 | J51: =VLOOKUP(C51,Aggregate!AR:AZ,9,FALSE()) -> 18.81347 | L51: =IFERROR(VLOOKUP(Table10[[#This Row],[NAME]],Aggregate!$P:$AA,11,FALSE()),"") -> 8 | M51: =Aggregate!P67 -> Kaelon Black | N51: =VLOOKUP(Table10[[#This Row],[NAME]],Aggregate!P:AA,4,FALSE()) -> SF/8 | O51: =IFERROR(VLOOKUP(Table10[[#This Row],[NAME]],Aggregate!$P:$AA,8,FALSE()),"") -> 84.793325 | P51: =IF(Scoring!$K$6="Auction",IFERROR(VLOOKUP(Table10[[#This Row],[NAME]],Aggregate!$P:$AA,10,FALSE()),""),IFERROR(VLOOKUP(Table10[[#This Row],[NAME]],Aggregate!$P:$AA,9,FALSE()),"")) -> -42.752413 | Q51: =SUMIFS(T52:$T$84,S52:$S$84,"<>x",S52:$S$84,"<>o",T52:$T$84,">0")/Aggregate!$X$1 -> 0 | R51: =VLOOKUP(Table10[[#This Row],[NAME]],ECR!C:E,3,FALSE()) -> RB65 | T51: =VLOOKUP(M51,Aggregate!P:X,9,FALSE()) -> -42.752413 | V51: =IFERROR(VLOOKUP(Table11[[#This Row],[NAME]],Aggregate!$AD:$AO,11,FALSE()),"") -> 7 | W51: =Aggregate!AD45 -> Wan'Dale Robinson | X51: =VLOOKUP(Table11[[#This Row],[NAME]],Aggregate!AD:AO,4,FALSE()) -> TEN/9 | Y51: =IFERROR(VLOOKUP(Table11[[#This Row],[NAME]],Aggregate!$AD:$AO,8,FALSE()),"") -> 109.30001 | Z51: =IF(Scoring!$K$6="Auction",IFERROR(VLOOKUP(Table11[[#This Row],[NAME]],Aggregate!$AD:$AO,10,FALSE()),""),IFERROR(VLOOKUP(Table11[[#This Row],[NAME]],Aggregate!$AD:$AO,9,FALSE()),"")) -> -16.377864 | AA51: =SUMIFS(AD52:$AD$84,AC52:$AC$84,"<>x",AC52:$AC$84,"<>o",AD52:$AD$84,">0")/Aggregate!$AL$1 -> 0 | AB51: =VLOOKUP(Table11[[#This Row],[NAME]],ECR!C:E,3,FALSE()) -> WR43 | AD51: =VLOOKUP(W51,Aggregate!AD:AL,9,FALSE()) -> -16.377864
B52: =IFERROR(VLOOKUP(Table12[[#This Row],[NAME]],Aggregate!$AR:$BC,11,FALSE()),"") -> 3 | C52: =Aggregate!AR8 -> Harold Fannin Jr. | D52: =VLOOKUP(Table12[[#This Row],[NAME]],Aggregate!AR:BD,4,FALSE()) -> CLE/11 | E52: =IFERROR(VLOOKUP($C52,Aggregate!$AR:$BC,8,FALSE()),"") -> 129.55197 | F52: =IF(Scoring!$K$6="Auction",IFERROR(VLOOKUP($C52,Aggregate!$AR:$BC,10,FALSE()),""),IFERROR(VLOOKUP($C52,Aggregate!$AR:$BC,9,FALSE()),"")) -> 16.978377 | G52: =SUMIFS(J53:$J$84,I53:$I$84,"<>x",I53:$I$84,"<>o",J53:$J$84,">0")/Aggregate!$AZ$1 -> 0.24661774 | H52: =VLOOKUP(Table12[[#This Row],[NAME]],ECR!C:E,3,FALSE()) -> TE6 | J52: =VLOOKUP(C52,Aggregate!AR:AZ,9,FALSE()) -> 16.978377 | L52: =IFERROR(VLOOKUP(Table10[[#This Row],[NAME]],Aggregate!$P:$AA,11,FALSE()),"") -> 8 | M52: =Aggregate!P47 -> Jonah Coleman | N52: =VLOOKUP(Table10[[#This Row],[NAME]],Aggregate!P:AA,4,FALSE()) -> DEN/10 | O52: =IFERROR(VLOOKUP(Table10[[#This Row],[NAME]],Aggregate!$P:$AA,8,FALSE()),"") -> 81.635547 | P52: =IF(Scoring!$K$6="Auction",IFERROR(VLOOKUP(Table10[[#This Row],[NAME]],Aggregate!$P:$AA,10,FALSE()),""),IFERROR(VLOOKUP(Table10[[#This Row],[NAME]],Aggregate!$P:$AA,9,FALSE()),"")) -> -45.910191 | Q52: =SUMIFS(T53:$T$84,S53:$S$84,"<>x",S53:$S$84,"<>o",T53:$T$84,">0")/Aggregate!$X$1 -> 0 | R52: =VLOOKUP(Table10[[#This Row],[NAME]],ECR!C:E,3,FALSE()) -> RB45 | T52: =VLOOKUP(M52,Aggregate!P:X,9,FALSE()) -> -45.910191 | V52: =IFERROR(VLOOKUP(Table11[[#This Row],[NAME]],Aggregate!$AD:$AO,11,FALSE()),"") -> 7 | W52: =Aggregate!AD60 -> Denzel Boston | X52: =VLOOKUP(Table11[[#This Row],[NAME]],Aggregate!AD:AO,4,FALSE()) -> CLE/11 | Y52: =IFERROR(VLOOKUP(Table11[[#This Row],[NAME]],Aggregate!$AD:$AO,8,FALSE()),"") -> 107.64685 | Z52: =IF(Scoring!$K$6="Auction",IFERROR(VLOOKUP(Table11[[#This Row],[NAME]],Aggregate!$AD:$AO,10,FALSE()),""),IFERROR(VLOOKUP(Table11[[#This Row],[NAME]],Aggregate!$AD:$AO,9,FALSE()),"")) -> -18.031032 | AA52: =SUMIFS(AD53:$AD$84,AC53:$AC$84,"<>x",AC53:$AC$84,"<>o",AD53:$AD$84,">0")/Aggregate!$AL$1 -> 0 | AB52: =VLOOKUP(Table11[[#This Row],[NAME]],ECR!C:E,3,FALSE()) -> WR58 | AD52: =VLOOKUP(W52,Aggregate!AD:AL,9,FALSE()) -> -18.031032
B53: =IFERROR(VLOOKUP(Table12[[#This Row],[NAME]],Aggregate!$AR:$BC,11,FALSE()),"") -> 3 | C53: =Aggregate!AR9 -> Sam LaPorta | D53: =VLOOKUP(Table12[[#This Row],[NAME]],Aggregate!AR:BD,4,FALSE()) -> DET/6 | E53: =IFERROR(VLOOKUP($C53,Aggregate!$AR:$BC,8,FALSE()),"") -> 124.12877 | F53: =IF(Scoring!$K$6="Auction",IFERROR(VLOOKUP($C53,Aggregate!$AR:$BC,10,FALSE()),""),IFERROR(VLOOKUP($C53,Aggregate!$AR:$BC,9,FALSE()),"")) -> 11.555176 | G53: =SUMIFS(J54:$J$84,I54:$I$84,"<>x",I54:$I$84,"<>o",J54:$J$84,">0")/Aggregate!$AZ$1 -> 0.19789361 | H53: =VLOOKUP(Table12[[#This Row],[NAME]],ECR!C:E,3,FALSE()) -> TE7 | J53: =VLOOKUP(C53,Aggregate!AR:AZ,9,FALSE()) -> 11.555176 | L53: =IFERROR(VLOOKUP(Table10[[#This Row],[NAME]],Aggregate!$P:$AA,11,FALSE()),"") -> 8 | M53: =Aggregate!P51 -> Zach Charbonnet | N53: =VLOOKUP(Table10[[#This Row],[NAME]],Aggregate!P:AA,4,FALSE()) -> SEA/11 | O53: =IFERROR(VLOOKUP(Table10[[#This Row],[NAME]],Aggregate!$P:$AA,8,FALSE()),"") -> 79.821302 | P53: =IF(Scoring!$K$6="Auction",IFERROR(VLOOKUP(Table10[[#This Row],[NAME]],Aggregate!$P:$AA,10,FALSE()),""),IFERROR(VLOOKUP(Table10[[#This Row],[NAME]],Aggregate!$P:$AA,9,FALSE()),"")) -> -47.724436 | Q53: =SUMIFS(T54:$T$84,S54:$S$84,"<>x",S54:$S$84,"<>o",T54:$T$84,">0")/Aggregate!$X$1 -> 0 | R53: =VLOOKUP(Table10[[#This Row],[NAME]],ECR!C:E,3,FALSE()) -> RB49 | T53: =VLOOKUP(M53,Aggregate!P:X,9,FALSE()) -> -47.724436 | V53: =IFERROR(VLOOKUP(Table11[[#This Row],[NAME]],Aggregate!$AD:$AO,11,FALSE()),"") -> 7 | W53: =Aggregate!AD44 -> Stefon Diggs | X53: =VLOOKUP(Table11[[#This Row],[NAME]],Aggregate!AD:AO,4,FALSE()) -> WAS/7 | Y53: =IFERROR(VLOOKUP(Table11[[#This Row],[NAME]],Aggregate!$AD:$AO,8,FALSE()),"") -> 107.16146 | Z53: =IF(Scoring!$K$6="Auction",IFERROR(VLOOKUP(Table11[[#This Row],[NAME]],Aggregate!$AD:$AO,10,FALSE()),""),IFERROR(VLOOKUP(Table11[[#This Row],[NAME]],Aggregate!$AD:$AO,9,FALSE()),"")) -> -18.516414 | AA53: =SUMIFS(AD54:$AD$84,AC54:$AC$84,"<>x",AC54:$AC$84,"<>o",AD54:$AD$84,">0")/Aggregate!$AL$1 -> 0 | AB53: =VLOOKUP(Table11[[#This Row],[NAME]],ECR!C:E,3,FALSE()) -> WR42 | AD53: =VLOOKUP(W53,Aggregate!AD:AL,9,FALSE()) -> -18.516414
B54: =IFERROR(VLOOKUP(Table12[[#This Row],[NAME]],Aggregate!$AR:$BC,11,FALSE()),"") -> 3 | C54: =Aggregate!AR10 -> Kyle Pitts Sr. | D54: =VLOOKUP(Table12[[#This Row],[NAME]],Aggregate!AR:BD,4,FALSE()) -> ATL/11 | E54: =IFERROR(VLOOKUP($C54,Aggregate!$AR:$BC,8,FALSE()),"") -> 124.00906 | F54: =IF(Scoring!$K$6="Auction",IFERROR(VLOOKUP($C54,Aggregate!$AR:$BC,10,FALSE()),""),IFERROR(VLOOKUP($C54,Aggregate!$AR:$BC,9,FALSE()),"")) -> 11.435463 | G54: =SUMIFS(J55:$J$84,I55:$I$84,"<>x",I55:$I$84,"<>o",J55:$J$84,">0")/Aggregate!$AZ$1 -> 0.14967426 | H54: =VLOOKUP(Table12[[#This Row],[NAME]],ECR!C:E,3,FALSE()) -> TE8 | J54: =VLOOKUP(C54,Aggregate!AR:AZ,9,FALSE()) -> 11.435463 | L54: =IFERROR(VLOOKUP(Table10[[#This Row],[NAME]],Aggregate!$P:$AA,11,FALSE()),"") -> 8 | M54: =Aggregate!P45 -> Tyler Allgeier | N54: =VLOOKUP(Table10[[#This Row],[NAME]],Aggregate!P:AA,4,FALSE()) -> ARI/14 | O54: =IFERROR(VLOOKUP(Table10[[#This Row],[NAME]],Aggregate!$P:$AA,8,FALSE()),"") -> 77.026955 | P54: =IF(Scoring!$K$6="Auction",IFERROR(VLOOKUP(Table10[[#This Row],[NAME]],Aggregate!$P:$AA,10,FALSE()),""),IFERROR(VLOOKUP(Table10[[#This Row],[NAME]],Aggregate!$P:$AA,9,FALSE()),"")) -> -50.518783 | Q54: =SUMIFS(T55:$T$84,S55:$S$84,"<>x",S55:$S$84,"<>o",T55:$T$84,">0")/Aggregate!$X$1 -> 0 | R54: =VLOOKUP(Table10[[#This Row],[NAME]],ECR!C:E,3,FALSE()) -> RB43 | T54: =VLOOKUP(M54,Aggregate!P:X,9,FALSE()) -> -50.518783 | V54: =IFERROR(VLOOKUP(Table11[[#This Row],[NAME]],Aggregate!$AD:$AO,11,FALSE()),"") -> 7 | W54: =Aggregate!AD54 -> Xavier Worthy | X54: =VLOOKUP(Table11[[#This Row],[NAME]],Aggregate!AD:AO,4,FALSE()) -> KC/5 | Y54: =IFERROR(VLOOKUP(Table11[[#This Row],[NAME]],Aggregate!$AD:$AO,8,FALSE()),"") -> 107.10545 | Z54: =IF(Scoring!$K$6="Auction",IFERROR(VLOOKUP(Table11[[#This Row],[NAME]],Aggregate!$AD:$AO,10,FALSE()),""),IFERROR(VLOOKUP(Table11[[#This Row],[NAME]],Aggregate!$AD:$AO,9,FALSE()),"")) -> -18.572426 | AA54: =SUMIFS(AD55:$AD$84,AC55:$AC$84,"<>x",AC55:$AC$84,"<>o",AD55:$AD$84,">0")/Aggregate!$AL$1 -> 0 | AB54: =VLOOKUP(Table11[[#This Row],[NAME]],ECR!C:E,3,FALSE()) -> WR52 | AD54: =VLOOKUP(W54,Aggregate!AD:AL,9,FALSE()) -> -18.572426
B55: =IFERROR(VLOOKUP(Table12[[#This Row],[NAME]],Aggregate!$AR:$BC,11,FALSE()),"") -> 3 | C55: =Aggregate!AR7 -> Tucker Kraft | D55: =VLOOKUP(Table12[[#This Row],[NAME]],Aggregate!AR:BD,4,FALSE()) -> GB/11 | E55: =IFERROR(VLOOKUP($C55,Aggregate!$AR:$BC,8,FALSE()),"") -> 124.00431 | F55: =IF(Scoring!$K$6="Auction",IFERROR(VLOOKUP($C55,Aggregate!$AR:$BC,10,FALSE()),""),IFERROR(VLOOKUP($C55,Aggregate!$AR:$BC,9,FALSE()),"")) -> 11.430714 | G55: =SUMIFS(J56:$J$84,I56:$I$84,"<>x",I56:$I$84,"<>o",J56:$J$84,">0")/Aggregate!$AZ$1 -> 0.10147494 | H55: =VLOOKUP(Table12[[#This Row],[NAME]],ECR!C:E,3,FALSE()) -> TE5 | J55: =VLOOKUP(C55,Aggregate!AR:AZ,9,FALSE()) -> 11.430714 | L55: =IFERROR(VLOOKUP(Table10[[#This Row],[NAME]],Aggregate!$P:$AA,11,FALSE()),"") -> 9 | M55: =Aggregate!P53 -> Dylan Sampson | N55: =VLOOKUP(Table10[[#This Row],[NAME]],Aggregate!P:AA,4,FALSE()) -> CLE/11 | O55: =IFERROR(VLOOKUP(Table10[[#This Row],[NAME]],Aggregate!$P:$AA,8,FALSE()),"") -> 71.147932 | P55: =IF(Scoring!$K$6="Auction",IFERROR(VLOOKUP(Table10[[#This Row],[NAME]],Aggregate!$P:$AA,10,FALSE()),""),IFERROR(VLOOKUP(Table10[[#This Row],[NAME]],Aggregate!$P:$AA,9,FALSE()),"")) -> -56.397806 | Q55: =SUMIFS(T56:$T$84,S56:$S$84,"<>x",S56:$S$84,"<>o",T56:$T$84,">0")/Aggregate!$X$1 -> 0 | R55: =VLOOKUP(Table10[[#This Row],[NAME]],ECR!C:E,3,FALSE()) -> RB51 | T55: =VLOOKUP(M55,Aggregate!P:X,9,FALSE()) -> -56.397806 | V55: =IFERROR(VLOOKUP(Table11[[#This Row],[NAME]],Aggregate!$AD:$AO,11,FALSE()),"") -> 7 | W55: =Aggregate!AD52 -> Matthew Golden | X55: =VLOOKUP(Table11[[#This Row],[NAME]],Aggregate!AD:AO,4,FALSE()) -> GB/11 | Y55: =IFERROR(VLOOKUP(Table11[[#This Row],[NAME]],Aggregate!$AD:$AO,8,FALSE()),"") -> 106.9056 | Z55: =IF(Scoring!$K$6="Auction",IFERROR(VLOOKUP(Table11[[#This Row],[NAME]],Aggregate!$AD:$AO,10,FALSE()),""),IFERROR(VLOOKUP(Table11[[#This Row],[NAME]],Aggregate!$AD:$AO,9,FALSE()),"")) -> -18.772283 | AA55: =SUMIFS(AD56:$AD$84,AC56:$AC$84,"<>x",AC56:$AC$84,"<>o",AD56:$AD$84,">0")/Aggregate!$AL$1 -> 0 | AB55: =VLOOKUP(Table11[[#This Row],[NAME]],ECR!C:E,3,FALSE()) -> WR50 | AD55: =VLOOKUP(W55,Aggregate!AD:AL,9,FALSE()) -> -18.772283
B56: =IFERROR(VLOOKUP(Table12[[#This Row],[NAME]],Aggregate!$AR:$BC,11,FALSE()),"") -> 3 | C56: =Aggregate!AR11 -> George Kittle | D56: =VLOOKUP(Table12[[#This Row],[NAME]],Aggregate!AR:BD,4,FALSE()) -> SF/8 | E56: =IFERROR(VLOOKUP($C56,Aggregate!$AR:$BC,8,FALSE()),"") -> 123.71521 | F56: =IF(Scoring!$K$6="Auction",IFERROR(VLOOKUP($C56,Aggregate!$AR:$BC,10,FALSE()),""),IFERROR(VLOOKUP($C56,Aggregate!$AR:$BC,9,FALSE()),"")) -> 11.141611 | G56: =SUMIFS(J57:$J$84,I57:$I$84,"<>x",I57:$I$84,"<>o",J57:$J$84,">0")/Aggregate!$AZ$1 -> 0.054494661 | H56: =VLOOKUP(Table12[[#This Row],[NAME]],ECR!C:E,3,FALSE()) -> TE9 | J56: =VLOOKUP(C56,Aggregate!AR:AZ,9,FALSE()) -> 11.141611 | L56: =IFERROR(VLOOKUP(Table10[[#This Row],[NAME]],Aggregate!$P:$AA,11,FALSE()),"") -> 9 | M56: =Aggregate!P55 -> Alvin Kamara | N56: =VLOOKUP(Table10[[#This Row],[NAME]],Aggregate!P:AA,4,FALSE()) -> NO/8 | O56: =IFERROR(VLOOKUP(Table10[[#This Row],[NAME]],Aggregate!$P:$AA,8,FALSE()),"") -> 71.039657 | P56: =IF(Scoring!$K$6="Auction",IFERROR(VLOOKUP(Table10[[#This Row],[NAME]],Aggregate!$P:$AA,10,FALSE()),""),IFERROR(VLOOKUP(Table10[[#This Row],[NAME]],Aggregate!$P:$AA,9,FALSE()),"")) -> -56.506081 | Q56: =SUMIFS(T57:$T$84,S57:$S$84,"<>x",S57:$S$84,"<>o",T57:$T$84,">0")/Aggregate!$X$1 -> 0 | R56: =VLOOKUP(Table10[[#This Row],[NAME]],ECR!C:E,3,FALSE()) -> RB53 | T56: =VLOOKUP(M56,Aggregate!P:X,9,FALSE()) -> -56.506081 | V56: =IFERROR(VLOOKUP(Table11[[#This Row],[NAME]],Aggregate!$AD:$AO,11,FALSE()),"") -> 7 | W56: =Aggregate!AD53 -> Romeo Doubs | X56: =VLOOKUP(Table11[[#This Row],[NAME]],Aggregate!AD:AO,4,FALSE()) -> NE/11 | Y56: =IFERROR(VLOOKUP(Table11[[#This Row],[NAME]],Aggregate!$AD:$AO,8,FALSE()),"") -> 104.99063 | Z56: =IF(Scoring!$K$6="Auction",IFERROR(VLOOKUP(Table11[[#This Row],[NAME]],Aggregate!$AD:$AO,10,FALSE()),""),IFERROR(VLOOKUP(Table11[[#This Row],[NAME]],Aggregate!$AD:$AO,9,FALSE()),"")) -> -20.687251 | AA56: =SUMIFS(AD57:$AD$84,AC57:$AC$84,"<>x",AC57:$AC$84,"<>o",AD57:$AD$84,">0")/Aggregate!$AL$1 -> 0 | AB56: =VLOOKUP(Table11[[#This Row],[NAME]],ECR!C:E,3,FALSE()) -> WR51 | AD56: =VLOOKUP(W56,Aggregate!AD:AL,9,FALSE()) -> -20.687251
B57: =IFERROR(VLOOKUP(Table12[[#This Row],[NAME]],Aggregate!$AR:$BC,11,FALSE()),"") -> 4 | C57: =Aggregate!AR12 -> Travis Kelce | D57: =VLOOKUP(Table12[[#This Row],[NAME]],Aggregate!AR:BD,4,FALSE()) -> KC/5 | E57: =IFERROR(VLOOKUP($C57,Aggregate!$AR:$BC,8,FALSE()),"") -> 120.13362 | F57: =IF(Scoring!$K$6="Auction",IFERROR(VLOOKUP($C57,Aggregate!$AR:$BC,10,FALSE()),""),IFERROR(VLOOKUP($C57,Aggregate!$AR:$BC,9,FALSE()),"")) -> 7.5600222 | G57: =SUMIFS(J58:$J$84,I58:$I$84,"<>x",I58:$I$84,"<>o",J58:$J$84,">0")/Aggregate!$AZ$1 -> 0.022616692 | H57: =VLOOKUP(Table12[[#This Row],[NAME]],ECR!C:E,3,FALSE()) -> TE10 | J57: =VLOOKUP(C57,Aggregate!AR:AZ,9,FALSE()) -> 7.5600222 | L57: =IFERROR(VLOOKUP(Table10[[#This Row],[NAME]],Aggregate!$P:$AA,11,FALSE()),"") -> 9 | M57: =Aggregate!P57 -> Emmett Johnson | N57: =VLOOKUP(Table10[[#This Row],[NAME]],Aggregate!P:AA,4,FALSE()) -> KC/5 | O57: =IFERROR(VLOOKUP(Table10[[#This Row],[NAME]],Aggregate!$P:$AA,8,FALSE()),"") -> 69.745785 | P57: =IF(Scoring!$K$6="Auction",IFERROR(VLOOKUP(Table10[[#This Row],[NAME]],Aggregate!$P:$AA,10,FALSE()),""),IFERROR(VLOOKUP(Table10[[#This Row],[NAME]],Aggregate!$P:$AA,9,FALSE()),"")) -> -57.799953 | Q57: =SUMIFS(T58:$T$84,S58:$S$84,"<>x",S58:$S$84,"<>o",T58:$T$84,">0")/Aggregate!$X$1 -> 0 | R57: =VLOOKUP(Table10[[#This Row],[NAME]],ECR!C:E,3,FALSE()) -> RB55 | T57: =VLOOKUP(M57,Aggregate!P:X,9,FALSE()) -> -57.799953 | V57: =IFERROR(VLOOKUP(Table11[[#This Row],[NAME]],Aggregate!$AD:$AO,11,FALSE()),"") -> 7 | W57: =Aggregate!AD43 -> Josh Downs | X57: =VLOOKUP(Table11[[#This Row],[NAME]],Aggregate!AD:AO,4,FALSE()) -> IND/13 | Y57: =IFERROR(VLOOKUP(Table11[[#This Row],[NAME]],Aggregate!$AD:$AO,8,FALSE()),"") -> 104.32937 | Z57: =IF(Scoring!$K$6="Auction",IFERROR(VLOOKUP(Table11[[#This Row],[NAME]],Aggregate!$AD:$AO,10,FALSE()),""),IFERROR(VLOOKUP(Table11[[#This Row],[NAME]],Aggregate!$AD:$AO,9,FALSE()),"")) -> -21.348508 | AA57: =SUMIFS(AD58:$AD$84,AC58:$AC$84,"<>x",AC58:$AC$84,"<>o",AD58:$AD$84,">0")/Aggregate!$AL$1 -> 0 | AB57: =VLOOKUP(Table11[[#This Row],[NAME]],ECR!C:E,3,FALSE()) -> WR41 | AD57: =VLOOKUP(W57,Aggregate!AD:AL,9,FALSE()) -> -21.348508
B58: =IFERROR(VLOOKUP(Table12[[#This Row],[NAME]],Aggregate!$AR:$BC,11,FALSE()),"") -> 4 | C58: =Aggregate!AR15 -> Dallas Goedert | D58: =VLOOKUP(Table12[[#This Row],[NAME]],Aggregate!AR:BD,4,FALSE()) -> PHI/10 | E58: =IFERROR(VLOOKUP($C58,Aggregate!$AR:$BC,8,FALSE()),"") -> 117.93726 | F58: =IF(Scoring!$K$6="Auction",IFERROR(VLOOKUP($C58,Aggregate!$AR:$BC,10,FALSE()),""),IFERROR(VLOOKUP($C58,Aggregate!$AR:$BC,9,FALSE()),"")) -> 5.3636634 | G58: =SUMIFS(J59:$J$84,I59:$I$84,"<>x",I59:$I$84,"<>o",J59:$J$84,">0")/Aggregate!$AZ$1 -> 0 | H58: =VLOOKUP(Table12[[#This Row],[NAME]],ECR!C:E,3,FALSE()) -> TE13 | J58: =VLOOKUP(C58,Aggregate!AR:AZ,9,FALSE()) -> 5.3636634 | L58: =IFERROR(VLOOKUP(Table10[[#This Row],[NAME]],Aggregate!$P:$AA,11,FALSE()),"") -> 9 | M58: =Aggregate!P54 -> Braelon Allen | N58: =VLOOKUP(Table10[[#This Row],[NAME]],Aggregate!P:AA,4,FALSE()) -> NYJ/13 | O58: =IFERROR(VLOOKUP(Table10[[#This Row],[NAME]],Aggregate!$P:$AA,8,FALSE()),"") -> 69.299023 | P58: =IF(Scoring!$K$6="Auction",IFERROR(VLOOKUP(Table10[[#This Row],[NAME]],Aggregate!$P:$AA,10,FALSE()),""),IFERROR(VLOOKUP(Table10[[#This Row],[NAME]],Aggregate!$P:$AA,9,FALSE()),"")) -> -58.246716 | Q58: =SUMIFS(T59:$T$84,S59:$S$84,"<>x",S59:$S$84,"<>o",T59:$T$84,">0")/Aggregate!$X$1 -> 0 | R58: =VLOOKUP(Table10[[#This Row],[NAME]],ECR!C:E,3,FALSE()) -> RB52 | T58: =VLOOKUP(M58,Aggregate!P:X,9,FALSE()) -> -58.246716 | V58: =IFERROR(VLOOKUP(Table11[[#This Row],[NAME]],Aggregate!$AD:$AO,11,FALSE()),"") -> 7 | W58: =Aggregate!AD57 -> Deebo Samuel Sr. | X58: =VLOOKUP(Table11[[#This Row],[NAME]],Aggregate!AD:AO,4,FALSE()) -> SF/8 | Y58: =IFERROR(VLOOKUP(Table11[[#This Row],[NAME]],Aggregate!$AD:$AO,8,FALSE()),"") -> 103.45387 | Z58: =IF(Scoring!$K$6="Auction",IFERROR(VLOOKUP(Table11[[#This Row],[NAME]],Aggregate!$AD:$AO,10,FALSE()),""),IFERROR(VLOOKUP(Table11[[#This Row],[NAME]],Aggregate!$AD:$AO,9,FALSE()),"")) -> -22.224012 | AA58: =SUMIFS(AD59:$AD$84,AC59:$AC$84,"<>x",AC59:$AC$84,"<>o",AD59:$AD$84,">0")/Aggregate!$AL$1 -> 0 | AB58: =VLOOKUP(Table11[[#This Row],[NAME]],ECR!C:E,3,FALSE()) -> WR55 | AD58: =VLOOKUP(W58,Aggregate!AD:AL,9,FALSE()) -> -22.224012
B59: =IFERROR(VLOOKUP(Table12[[#This Row],[NAME]],Aggregate!$AR:$BC,11,FALSE()),"") -> 4 | C59: =Aggregate!AR13 -> Dalton Kincaid | D59: =VLOOKUP(Table12[[#This Row],[NAME]],Aggregate!AR:BD,4,FALSE()) -> BUF/7 | E59: =IFERROR(VLOOKUP($C59,Aggregate!$AR:$BC,8,FALSE()),"") -> 112.5736 | F59: =IF(Scoring!$K$6="Auction",IFERROR(VLOOKUP($C59,Aggregate!$AR:$BC,10,FALSE()),""),IFERROR(VLOOKUP($C59,Aggregate!$AR:$BC,9,FALSE()),"")) -> 0 | G59: =SUMIFS(J60:$J$84,I60:$I$84,"<>x",I60:$I$84,"<>o",J60:$J$84,">0")/Aggregate!$AZ$1 -> 0 | H59: =VLOOKUP(Table12[[#This Row],[NAME]],ECR!C:E,3,FALSE()) -> TE11 | J59: =VLOOKUP(C59,Aggregate!AR:AZ,9,FALSE()) -> 0 | L59: =IFERROR(VLOOKUP(Table10[[#This Row],[NAME]],Aggregate!$P:$AA,11,FALSE()),"") -> 9 | M59: =Aggregate!P71 -> Justice Hill | N59: =VLOOKUP(Table10[[#This Row],[NAME]],Aggregate!P:AA,4,FALSE()) -> BAL/13 | O59: =IFERROR(VLOOKUP(Table10[[#This Row],[NAME]],Aggregate!$P:$AA,8,FALSE()),"") -> 67.843431 | P59: =IF(Scoring!$K$6="Auction",IFERROR(VLOOKUP(Table10[[#This Row],[NAME]],Aggregate!$P:$AA,10,FALSE()),""),IFERROR(VLOOKUP(Table10[[#This Row],[NAME]],Aggregate!$P:$AA,9,FALSE()),"")) -> -59.702307 | Q59: =SUMIFS(T60:$T$84,S60:$S$84,"<>x",S60:$S$84,"<>o",T60:$T$84,">0")/Aggregate!$X$1 -> 0 | R59: =VLOOKUP(Table10[[#This Row],[NAME]],ECR!C:E,3,FALSE()) -> RB69 | T59: =VLOOKUP(M59,Aggregate!P:X,9,FALSE()) -> -59.702307 | V59: =IFERROR(VLOOKUP(Table11[[#This Row],[NAME]],Aggregate!$AD:$AO,11,FALSE()),"") -> 7 | W59: =Aggregate!AD59 -> Rashid Shaheed | X59: =VLOOKUP(Table11[[#This Row],[NAME]],Aggregate!AD:AO,4,FALSE()) -> SEA/11 | Y59: =IFERROR(VLOOKUP(Table11[[#This Row],[NAME]],Aggregate!$AD:$AO,8,FALSE()),"") -> 101.26059 | Z59: =IF(Scoring!$K$6="Auction",IFERROR(VLOOKUP(Table11[[#This Row],[NAME]],Aggregate!$AD:$AO,10,FALSE()),""),IFERROR(VLOOKUP(Table11[[#This Row],[NAME]],Aggregate!$AD:$AO,9,FALSE()),"")) -> -24.417284 | AA59: =SUMIFS(AD60:$AD$84,AC60:$AC$84,"<>x",AC60:$AC$84,"<>o",AD60:$AD$84,">0")/Aggregate!$AL$1 -> 0 | AB59: =VLOOKUP(Table11[[#This Row],[NAME]],ECR!C:E,3,FALSE()) -> WR57 | AD59: =VLOOKUP(W59,Aggregate!AD:AL,9,FALSE()) -> -24.417284
B60: =IFERROR(VLOOKUP(Table12[[#This Row],[NAME]],Aggregate!$AR:$BC,11,FALSE()),"") -> 4 | C60: =Aggregate!AR14 -> Isaiah Likely | D60: =VLOOKUP(Table12[[#This Row],[NAME]],Aggregate!AR:BD,4,FALSE()) -> NYG/8 | E60: =IFERROR(VLOOKUP($C60,Aggregate!$AR:$BC,8,FALSE()),"") -> 112.22889 | F60: =IF(Scoring!$K$6="Auction",IFERROR(VLOOKUP($C60,Aggregate!$AR:$BC,10,FALSE()),""),IFERROR(VLOOKUP($C60,Aggregate!$AR:$BC,9,FALSE()),"")) -> -0.34470285 | G60: =SUMIFS(J61:$J$84,I61:$I$84,"<>x",I61:$I$84,"<>o",J61:$J$84,">0")/Aggregate!$AZ$1 -> 0 | H60: =VLOOKUP(Table12[[#This Row],[NAME]],ECR!C:E,3,FALSE()) -> TE12 | J60: =VLOOKUP(C60,Aggregate!AR:AZ,9,FALSE()) -> -0.34470285 | L60: =IFERROR(VLOOKUP(Table10[[#This Row],[NAME]],Aggregate!$P:$AA,11,FALSE()),"") -> 9 | M60: =Aggregate!P52 -> Tank Bigsby | N60: =VLOOKUP(Table10[[#This Row],[NAME]],Aggregate!P:AA,4,FALSE()) -> PHI/10 | O60: =IFERROR(VLOOKUP(Table10[[#This Row],[NAME]],Aggregate!$P:$AA,8,FALSE()),"") -> 66.037175 | P60: =IF(Scoring!$K$6="Auction",IFERROR(VLOOKUP(Table10[[#This Row],[NAME]],Aggregate!$P:$AA,10,FALSE()),""),IFERROR(VLOOKUP(Table10[[#This Row],[NAME]],Aggregate!$P:$AA,9,FALSE()),"")) -> -61.508563 | Q60: =SUMIFS(T61:$T$84,S61:$S$84,"<>x",S61:$S$84,"<>o",T61:$T$84,">0")/Aggregate!$X$1 -> 0 | R60: =VLOOKUP(Table10[[#This Row],[NAME]],ECR!C:E,3,FALSE()) -> RB50 | T60: =VLOOKUP(M60,Aggregate!P:X,9,FALSE()) -> -61.508563 | V60: =IFERROR(VLOOKUP(Table11[[#This Row],[NAME]],Aggregate!$AD:$AO,11,FALSE()),"") -> 7 | W60: =Aggregate!AD56 -> Khalil Shakir | X60: =VLOOKUP(Table11[[#This Row],[NAME]],Aggregate!AD:AO,4,FALSE()) -> BUF/7 | Y60: =IFERROR(VLOOKUP(Table11[[#This Row],[NAME]],Aggregate!$AD:$AO,8,FALSE()),"") -> 101.16518 | Z60: =IF(Scoring!$K$6="Auction",IFERROR(VLOOKUP(Table11[[#This Row],[NAME]],Aggregate!$AD:$AO,10,FALSE()),""),IFERROR(VLOOKUP(Table11[[#This Row],[NAME]],Aggregate!$AD:$AO,9,FALSE()),"")) -> -24.5127 | AA60: =SUMIFS(AD61:$AD$84,AC61:$AC$84,"<>x",AC61:$AC$84,"<>o",AD61:$AD$84,">0")/Aggregate!$AL$1 -> 0 | AB60: =VLOOKUP(Table11[[#This Row],[NAME]],ECR!C:E,3,FALSE()) -> WR54 | AD60: =VLOOKUP(W60,Aggregate!AD:AL,9,FALSE()) -> -24.5127
B61: =IFERROR(VLOOKUP(Table12[[#This Row],[NAME]],Aggregate!$AR:$BC,11,FALSE()),"") -> 5 | C61: =Aggregate!AR18 -> Mark Andrews | D61: =VLOOKUP(Table12[[#This Row],[NAME]],Aggregate!AR:BD,4,FALSE()) -> BAL/13 | E61: =IFERROR(VLOOKUP($C61,Aggregate!$AR:$BC,8,FALSE()),"") -> 107.91485 | F61: =IF(Scoring!$K$6="Auction",IFERROR(VLOOKUP($C61,Aggregate!$AR:$BC,10,FALSE()),""),IFERROR(VLOOKUP($C61,Aggregate!$AR:$BC,9,FALSE()),"")) -> -4.6587512 | G61: =SUMIFS(J62:$J$84,I62:$I$84,"<>x",I62:$I$84,"<>o",J62:$J$84,">0")/Aggregate!$AZ$1 -> 0 | H61: =VLOOKUP(Table12[[#This Row],[NAME]],ECR!C:E,3,FALSE()) -> TE16 | J61: =VLOOKUP(C61,Aggregate!AR:AZ,9,FALSE()) -> -4.6587512 | L61: =IFERROR(VLOOKUP(Table10[[#This Row],[NAME]],Aggregate!$P:$AA,11,FALSE()),"") -> 9 | M61: =Aggregate!P50 -> Keaton Mitchell | N61: =VLOOKUP(Table10[[#This Row],[NAME]],Aggregate!P:AA,4,FALSE()) -> LAC/7 | O61: =IFERROR(VLOOKUP(Table10[[#This Row],[NAME]],Aggregate!$P:$AA,8,FALSE()),"") -> 65.565692 | P61: =IF(Scoring!$K$6="Auction",IFERROR(VLOOKUP(Table10[[#This Row],[NAME]],Aggregate!$P:$AA,10,FALSE()),""),IFERROR(VLOOKUP(Table10[[#This Row],[NAME]],Aggregate!$P:$AA,9,FALSE()),"")) -> -61.980047 | Q61: =SUMIFS(T62:$T$84,S62:$S$84,"<>x",S62:$S$84,"<>o",T62:$T$84,">0")/Aggregate!$X$1 -> 0 | R61: =VLOOKUP(Table10[[#This Row],[NAME]],ECR!C:E,3,FALSE()) -> RB48 | T61: =VLOOKUP(M61,Aggregate!P:X,9,FALSE()) -> -61.980047 | V61: =IFERROR(VLOOKUP(Table11[[#This Row],[NAME]],Aggregate!$AD:$AO,11,FALSE()),"") -> 7 | W61: =Aggregate!AD55 -> Jalen Coker | X61: =VLOOKUP(Table11[[#This Row],[NAME]],Aggregate!AD:AO,4,FALSE()) -> CAR/5 | Y61: =IFERROR(VLOOKUP(Table11[[#This Row],[NAME]],Aggregate!$AD:$AO,8,FALSE()),"") -> 100.36575 | Z61: =IF(Scoring!$K$6="Auction",IFERROR(VLOOKUP(Table11[[#This Row],[NAME]],Aggregate!$AD:$AO,10,FALSE()),""),IFERROR(VLOOKUP(Table11[[#This Row],[NAME]],Aggregate!$AD:$AO,9,FALSE()),"")) -> -25.312129 | AA61: =SUMIFS(AD62:$AD$84,AC62:$AC$84,"<>x",AC62:$AC$84,"<>o",AD62:$AD$84,">0")/Aggregate!$AL$1 -> 0 | AB61: =VLOOKUP(Table11[[#This Row],[NAME]],ECR!C:E,3,FALSE()) -> WR53 | AD61: =VLOOKUP(W61,Aggregate!AD:AL,9,FALSE()) -> -25.312129
B62: =IFERROR(VLOOKUP(Table12[[#This Row],[NAME]],Aggregate!$AR:$BC,11,FALSE()),"") -> 5 | C62: =Aggregate!AR16 -> Jake Ferguson | D62: =VLOOKUP(Table12[[#This Row],[NAME]],Aggregate!AR:BD,4,FALSE()) -> DAL/14 | E62: =IFERROR(VLOOKUP($C62,Aggregate!$AR:$BC,8,FALSE()),"") -> 107.61327 | F62: =IF(Scoring!$K$6="Auction",IFERROR(VLOOKUP($C62,Aggregate!$AR:$BC,10,FALSE()),""),IFERROR(VLOOKUP($C62,Aggregate!$AR:$BC,9,FALSE()),"")) -> -4.9603235 | G62: =SUMIFS(J63:$J$84,I63:$I$84,"<>x",I63:$I$84,"<>o",J63:$J$84,">0")/Aggregate!$AZ$1 -> 0 | H62: =VLOOKUP(Table12[[#This Row],[NAME]],ECR!C:E,3,FALSE()) -> TE14 | J62: =VLOOKUP(C62,Aggregate!AR:AZ,9,FALSE()) -> -4.9603235 | L62: =IFERROR(VLOOKUP(Table10[[#This Row],[NAME]],Aggregate!$P:$AA,11,FALSE()),"") -> 9 | M62: =Aggregate!P58 -> Brian Robinson Jr. | N62: =VLOOKUP(Table10[[#This Row],[NAME]],Aggregate!P:AA,4,FALSE()) -> ATL/11 | O62: =IFERROR(VLOOKUP(Table10[[#This Row],[NAME]],Aggregate!$P:$AA,8,FALSE()),"") -> 64.201994 | P62: =IF(Scoring!$K$6="Auction",IFERROR(VLOOKUP(Table10[[#This Row],[NAME]],Aggregate!$P:$AA,10,FALSE()),""),IFERROR(VLOOKUP(Table10[[#This Row],[NAME]],Aggregate!$P:$AA,9,FALSE()),"")) -> -63.343745 | Q62: =SUMIFS(T63:$T$84,S63:$S$84,"<>x",S63:$S$84,"<>o",T63:$T$84,">0")/Aggregate!$X$1 -> 0 | R62: =VLOOKUP(Table10[[#This Row],[NAME]],ECR!C:E,3,FALSE()) -> RB56 | T62: =VLOOKUP(M62,Aggregate!P:X,9,FALSE()) -> -63.343745 | V62: =IFERROR(VLOOKUP(Table11[[#This Row],[NAME]],Aggregate!$AD:$AO,11,FALSE()),"") -> 7 | W62: =Aggregate!AD80 -> Ja'Kobi Lane | X62: =VLOOKUP(Table11[[#This Row],[NAME]],Aggregate!AD:AO,4,FALSE()) -> BAL/13 | Y62: =IFERROR(VLOOKUP(Table11[[#This Row],[NAME]],Aggregate!$AD:$AO,8,FALSE()),"") -> 96.615756 | Z62: =IF(Scoring!$K$6="Auction",IFERROR(VLOOKUP(Table11[[#This Row],[NAME]],Aggregate!$AD:$AO,10,FALSE()),""),IFERROR(VLOOKUP(Table11[[#This Row],[NAME]],Aggregate!$AD:$AO,9,FALSE()),"")) -> -29.062122 | AA62: =SUMIFS(AD63:$AD$84,AC63:$AC$84,"<>x",AC63:$AC$84,"<>o",AD63:$AD$84,">0")/Aggregate!$AL$1 -> 0 | AB62: =VLOOKUP(Table11[[#This Row],[NAME]],ECR!C:E,3,FALSE()) -> WR78 | AD62: =VLOOKUP(W62,Aggregate!AD:AL,9,FALSE()) -> -29.062122
B63: =IFERROR(VLOOKUP(Table12[[#This Row],[NAME]],Aggregate!$AR:$BC,11,FALSE()),"") -> 5 | C63: =Aggregate!AR17 -> Juwan Johnson | D63: =VLOOKUP(Table12[[#This Row],[NAME]],Aggregate!AR:BD,4,FALSE()) -> NO/8 | E63: =IFERROR(VLOOKUP($C63,Aggregate!$AR:$BC,8,FALSE()),"") -> 103.50716 | F63: =IF(Scoring!$K$6="Auction",IFERROR(VLOOKUP($C63,Aggregate!$AR:$BC,10,FALSE()),""),IFERROR(VLOOKUP($C63,Aggregate!$AR:$BC,9,FALSE()),"")) -> -9.066438 | G63: =SUMIFS(J64:$J$84,I64:$I$84,"<>x",I64:$I$84,"<>o",J64:$J$84,">0")/Aggregate!$AZ$1 -> 0 | H63: =VLOOKUP(Table12[[#This Row],[NAME]],ECR!C:E,3,FALSE()) -> TE15 | J63: =VLOOKUP(C63,Aggregate!AR:AZ,9,FALSE()) -> -9.066438 | L63: =IFERROR(VLOOKUP(Table10[[#This Row],[NAME]],Aggregate!$P:$AA,11,FALSE()),"") -> 9 | M63: =Aggregate!P66 -> Kaytron Allen | N63: =VLOOKUP(Table10[[#This Row],[NAME]],Aggregate!P:AA,4,FALSE()) -> WAS/7 | O63: =IFERROR(VLOOKUP(Table10[[#This Row],[NAME]],Aggregate!$P:$AA,8,FALSE()),"") -> 61.026344 | P63: =IF(Scoring!$K$6="Auction",IFERROR(VLOOKUP(Table10[[#This Row],[NAME]],Aggregate!$P:$AA,10,FALSE()),""),IFERROR(VLOOKUP(Table10[[#This Row],[NAME]],Aggregate!$P:$AA,9,FALSE()),"")) -> -66.519395 | Q63: =SUMIFS(T64:$T$84,S64:$S$84,"<>x",S64:$S$84,"<>o",T64:$T$84,">0")/Aggregate!$X$1 -> 0 | R63: =VLOOKUP(Table10[[#This Row],[NAME]],ECR!C:E,3,FALSE()) -> RB64 | T63: =VLOOKUP(M63,Aggregate!P:X,9,FALSE()) -> -66.519395 | V63: =IFERROR(VLOOKUP(Table11[[#This Row],[NAME]],Aggregate!$AD:$AO,11,FALSE()),"") -> 7 | W63: =Aggregate!AD58 -> Jordyn Tyson | X63: =VLOOKUP(Table11[[#This Row],[NAME]],Aggregate!AD:AO,4,FALSE()) -> NO/8 | Y63: =IFERROR(VLOOKUP(Table11[[#This Row],[NAME]],Aggregate!$AD:$AO,8,FALSE()),"") -> 96.14693 | Z63: =IF(Scoring!$K$6="Auction",IFERROR(VLOOKUP(Table11[[#This Row],[NAME]],Aggregate!$AD:$AO,10,FALSE()),""),IFERROR(VLOOKUP(Table11[[#This Row],[NAME]],Aggregate!$AD:$AO,9,FALSE()),"")) -> -29.530949 | AA63: =SUMIFS(AD64:$AD$84,AC64:$AC$84,"<>x",AC64:$AC$84,"<>o",AD64:$AD$84,">0")/Aggregate!$AL$1 -> 0 | AB63: =VLOOKUP(Table11[[#This Row],[NAME]],ECR!C:E,3,FALSE()) -> WR56 | AD63: =VLOOKUP(W63,Aggregate!AD:AL,9,FALSE()) -> -29.530949
B64: =IFERROR(VLOOKUP(Table12[[#This Row],[NAME]],Aggregate!$AR:$BC,11,FALSE()),"") -> 5 | C64: =Aggregate!AR19 -> Hunter Henry | D64: =VLOOKUP(Table12[[#This Row],[NAME]],Aggregate!AR:BD,4,FALSE()) -> NE/11 | E64: =IFERROR(VLOOKUP($C64,Aggregate!$AR:$BC,8,FALSE()),"") -> 100.92536 | F64: =IF(Scoring!$K$6="Auction",IFERROR(VLOOKUP($C64,Aggregate!$AR:$BC,10,FALSE()),""),IFERROR(VLOOKUP($C64,Aggregate!$AR:$BC,9,FALSE()),"")) -> -11.64824 | G64: =SUMIFS(J65:$J$84,I65:$I$84,"<>x",I65:$I$84,"<>o",J65:$J$84,">0")/Aggregate!$AZ$1 -> 0 | H64: =VLOOKUP(Table12[[#This Row],[NAME]],ECR!C:E,3,FALSE()) -> TE17 | J64: =VLOOKUP(C64,Aggregate!AR:AZ,9,FALSE()) -> -11.64824 | L64: =IFERROR(VLOOKUP(Table10[[#This Row],[NAME]],Aggregate!$P:$AA,11,FALSE()),"") -> 9 | M64: =Aggregate!P65 -> Nicholas Singleton | N64: =VLOOKUP(Table10[[#This Row],[NAME]],Aggregate!P:AA,4,FALSE()) -> TEN/9 | O64: =IFERROR(VLOOKUP(Table10[[#This Row],[NAME]],Aggregate!$P:$AA,8,FALSE()),"") -> 60.610114 | P64: =IF(Scoring!$K$6="Auction",IFERROR(VLOOKUP(Table10[[#This Row],[NAME]],Aggregate!$P:$AA,10,FALSE()),""),IFERROR(VLOOKUP(Table10[[#This Row],[NAME]],Aggregate!$P:$AA,9,FALSE()),"")) -> -66.935624 | Q64: =SUMIFS(T65:$T$84,S65:$S$84,"<>x",S65:$S$84,"<>o",T65:$T$84,">0")/Aggregate!$X$1 -> 0 | R64: =VLOOKUP(Table10[[#This Row],[NAME]],ECR!C:E,3,FALSE()) -> RB63 | T64: =VLOOKUP(M64,Aggregate!P:X,9,FALSE()) -> -66.935624 | V64: =IFERROR(VLOOKUP(Table11[[#This Row],[NAME]],Aggregate!$AD:$AO,11,FALSE()),"") -> 7 | W64: =Aggregate!AD66 -> Jerry Jeudy | X64: =VLOOKUP(Table11[[#This Row],[NAME]],Aggregate!AD:AO,4,FALSE()) -> CLE/11 | Y64: =IFERROR(VLOOKUP(Table11[[#This Row],[NAME]],Aggregate!$AD:$AO,8,FALSE()),"") -> 95.689399 | Z64: =IF(Scoring!$K$6="Auction",IFERROR(VLOOKUP(Table11[[#This Row],[NAME]],Aggregate!$AD:$AO,10,FALSE()),""),IFERROR(VLOOKUP(Table11[[#This Row],[NAME]],Aggregate!$AD:$AO,9,FALSE()),"")) -> -29.98848 | AA64: =SUMIFS(AD65:$AD$84,AC65:$AC$84,"<>x",AC65:$AC$84,"<>o",AD65:$AD$84,">0")/Aggregate!$AL$1 -> 0 | AB64: =VLOOKUP(Table11[[#This Row],[NAME]],ECR!C:E,3,FALSE()) -> WR64 | AD64: =VLOOKUP(W64,Aggregate!AD:AL,9,FALSE()) -> -29.98848
B65: =IFERROR(VLOOKUP(Table12[[#This Row],[NAME]],Aggregate!$AR:$BC,11,FALSE()),"") -> 5 | C65: =Aggregate!AR20 -> Brenton Strange | D65: =VLOOKUP(Table12[[#This Row],[NAME]],Aggregate!AR:BD,4,FALSE()) -> JAC/7 | E65: =IFERROR(VLOOKUP($C65,Aggregate!$AR:$BC,8,FALSE()),"") -> 97.8274 | F65: =IF(Scoring!$K$6="Auction",IFERROR(VLOOKUP($C65,Aggregate!$AR:$BC,10,FALSE()),""),IFERROR(VLOOKUP($C65,Aggregate!$AR:$BC,9,FALSE()),"")) -> -14.746197 | G65: =SUMIFS(J66:$J$84,I66:$I$84,"<>x",I66:$I$84,"<>o",J66:$J$84,">0")/Aggregate!$AZ$1 -> 0 | H65: =VLOOKUP(Table12[[#This Row],[NAME]],ECR!C:E,3,FALSE()) -> TE18 | J65: =VLOOKUP(C65,Aggregate!AR:AZ,9,FALSE()) -> -14.746197 | L65: =IFERROR(VLOOKUP(Table10[[#This Row],[NAME]],Aggregate!$P:$AA,11,FALSE()),"") -> 9 | M65: =Aggregate!P62 -> Isiah Pacheco | N65: =VLOOKUP(Table10[[#This Row],[NAME]],Aggregate!P:AA,4,FALSE()) -> DET/6 | O65: =IFERROR(VLOOKUP(Table10[[#This Row],[NAME]],Aggregate!$P:$AA,8,FALSE()),"") -> 59.664902 | P65: =IF(Scoring!$K$6="Auction",IFERROR(VLOOKUP(Table10[[#This Row],[NAME]],Aggregate!$P:$AA,10,FALSE()),""),IFERROR(VLOOKUP(Table10[[#This Row],[NAME]],Aggregate!$P:$AA,9,FALSE()),"")) -> -67.880836 | Q65: =SUMIFS(T66:$T$84,S66:$S$84,"<>x",S66:$S$84,"<>o",T66:$T$84,">0")/Aggregate!$X$1 -> 0 | R65: =VLOOKUP(Table10[[#This Row],[NAME]],ECR!C:E,3,FALSE()) -> RB60 | T65: =VLOOKUP(M65,Aggregate!P:X,9,FALSE()) -> -67.880836 | V65: =IFERROR(VLOOKUP(Table11[[#This Row],[NAME]],Aggregate!$AD:$AO,11,FALSE()),"") -> 7 | W65: =Aggregate!AD61 -> Tre Tucker | X65: =VLOOKUP(Table11[[#This Row],[NAME]],Aggregate!AD:AO,4,FALSE()) -> LV/13 | Y65: =IFERROR(VLOOKUP(Table11[[#This Row],[NAME]],Aggregate!$AD:$AO,8,FALSE()),"") -> 92.994239 | Z65: =IF(Scoring!$K$6="Auction",IFERROR(VLOOKUP(Table11[[#This Row],[NAME]],Aggregate!$AD:$AO,10,FALSE()),""),IFERROR(VLOOKUP(Table11[[#This Row],[NAME]],Aggregate!$AD:$AO,9,FALSE()),"")) -> -32.683639 | AA65: =SUMIFS(AD66:$AD$84,AC66:$AC$84,"<>x",AC66:$AC$84,"<>o",AD66:$AD$84,">0")/Aggregate!$AL$1 -> 0 | AB65: =VLOOKUP(Table11[[#This Row],[NAME]],ECR!C:E,3,FALSE()) -> WR59 | AD65: =VLOOKUP(W65,Aggregate!AD:AL,9,FALSE()) -> -32.683639
B66: =IFERROR(VLOOKUP(Table12[[#This Row],[NAME]],Aggregate!$AR:$BC,11,FALSE()),"") -> 6 | C66: =Aggregate!AR22 -> Dalton Schultz | D66: =VLOOKUP(Table12[[#This Row],[NAME]],Aggregate!AR:BD,4,FALSE()) -> HOU/8 | E66: =IFERROR(VLOOKUP($C66,Aggregate!$AR:$BC,8,FALSE()),"") -> 87.797929 | F66: =IF(Scoring!$K$6="Auction",IFERROR(VLOOKUP($C66,Aggregate!$AR:$BC,10,FALSE()),""),IFERROR(VLOOKUP($C66,Aggregate!$AR:$BC,9,FALSE()),"")) -> -24.775669 | G66: =SUMIFS(J67:$J$84,I67:$I$84,"<>x",I67:$I$84,"<>o",J67:$J$84,">0")/Aggregate!$AZ$1 -> 0 | H66: =VLOOKUP(Table12[[#This Row],[NAME]],ECR!C:E,3,FALSE()) -> TE20 | J66: =VLOOKUP(C66,Aggregate!AR:AZ,9,FALSE()) -> -24.775669 | L66: =IFERROR(VLOOKUP(Table10[[#This Row],[NAME]],Aggregate!$P:$AA,11,FALSE()),"") -> 9 | M66: =Aggregate!P74 -> Samaje Perine | N66: =VLOOKUP(Table10[[#This Row],[NAME]],Aggregate!P:AA,4,FALSE()) -> CIN/6 | O66: =IFERROR(VLOOKUP(Table10[[#This Row],[NAME]],Aggregate!$P:$AA,8,FALSE()),"") -> 58.053922 | P66: =IF(Scoring!$K$6="Auction",IFERROR(VLOOKUP(Table10[[#This Row],[NAME]],Aggregate!$P:$AA,10,FALSE()),""),IFERROR(VLOOKUP(Table10[[#This Row],[NAME]],Aggregate!$P:$AA,9,FALSE()),"")) -> -69.491817 | Q66: =SUMIFS(T67:$T$84,S67:$S$84,"<>x",S67:$S$84,"<>o",T67:$T$84,">0")/Aggregate!$X$1 -> 0 | R66: =VLOOKUP(Table10[[#This Row],[NAME]],ECR!C:E,3,FALSE()) -> RB72 | T66: =VLOOKUP(M66,Aggregate!P:X,9,FALSE()) -> -69.491817 | V66: =IFERROR(VLOOKUP(Table11[[#This Row],[NAME]],Aggregate!$AD:$AO,11,FALSE()),"") -> 8 | W66: =Aggregate!AD75 -> Calvin Ridley | X66: =VLOOKUP(Table11[[#This Row],[NAME]],Aggregate!AD:AO,4,FALSE()) -> TEN/9 | Y66: =IFERROR(VLOOKUP(Table11[[#This Row],[NAME]],Aggregate!$AD:$AO,8,FALSE()),"") -> 92.054265 | Z66: =IF(Scoring!$K$6="Auction",IFERROR(VLOOKUP(Table11[[#This Row],[NAME]],Aggregate!$AD:$AO,10,FALSE()),""),IFERROR(VLOOKUP(Table11[[#This Row],[NAME]],Aggregate!$AD:$AO,9,FALSE()),"")) -> -33.623613 | AA66: =SUMIFS(AD67:$AD$84,AC67:$AC$84,"<>x",AC67:$AC$84,"<>o",AD67:$AD$84,">0")/Aggregate!$AL$1 -> 0 | AB66: =VLOOKUP(Table11[[#This Row],[NAME]],ECR!C:E,3,FALSE()) -> WR73 | AD66: =VLOOKUP(W66,Aggregate!AD:AL,9,FALSE()) -> -33.623613
B67: =IFERROR(VLOOKUP(Table12[[#This Row],[NAME]],Aggregate!$AR:$BC,11,FALSE()),"") -> 6 | C67: =Aggregate!AR25 -> T.J. Hockenson | D67: =VLOOKUP(Table12[[#This Row],[NAME]],Aggregate!AR:BD,4,FALSE()) -> MIN/6 | E67: =IFERROR(VLOOKUP($C67,Aggregate!$AR:$BC,8,FALSE()),"") -> 83.147745 | F67: =IF(Scoring!$K$6="Auction",IFERROR(VLOOKUP($C67,Aggregate!$AR:$BC,10,FALSE()),""),IFERROR(VLOOKUP($C67,Aggregate!$AR:$BC,9,FALSE()),"")) -> -29.425852 | G67: =SUMIFS(J67:$J$85,I67:$I$85,"<>x",I67:$I$85,"<>o",J67:$J$85,">0")/Aggregate!$AZ$1 -> 0 | H67: =VLOOKUP(Table12[[#This Row],[NAME]],ECR!C:E,3,FALSE()) -> TE23 | J67: =VLOOKUP(C67,Aggregate!AR:AZ,9,FALSE()) -> -29.425852 | L67: =IFERROR(VLOOKUP(Table10[[#This Row],[NAME]],Aggregate!$P:$AA,11,FALSE()),"") -> 9 | M67: =Aggregate!P63 -> Malik Davis | N67: =VLOOKUP(Table10[[#This Row],[NAME]],Aggregate!P:AA,4,FALSE()) -> DAL/14 | O67: =IFERROR(VLOOKUP(Table10[[#This Row],[NAME]],Aggregate!$P:$AA,8,FALSE()),"") -> 57.164771 | P67: =IF(Scoring!$K$6="Auction",IFERROR(VLOOKUP(Table10[[#This Row],[NAME]],Aggregate!$P:$AA,10,FALSE()),""),IFERROR(VLOOKUP(Table10[[#This Row],[NAME]],Aggregate!$P:$AA,9,FALSE()),"")) -> -70.380968 | Q67: =SUMIFS(T68:$T$84,S68:$S$84,"<>x",S68:$S$84,"<>o",T68:$T$84,">0")/Aggregate!$X$1 -> 0 | R67: =VLOOKUP(Table10[[#This Row],[NAME]],ECR!C:E,3,FALSE()) -> RB61 | T67: =VLOOKUP(M67,Aggregate!P:X,9,FALSE()) -> -70.380968 | V67: =IFERROR(VLOOKUP(Table11[[#This Row],[NAME]],Aggregate!$AD:$AO,11,FALSE()),"") -> 8 | W67: =Aggregate!AD63 -> Kayshon Boutte | X67: =VLOOKUP(Table11[[#This Row],[NAME]],Aggregate!AD:AO,4,FALSE()) -> HOU/8 | Y67: =IFERROR(VLOOKUP(Table11[[#This Row],[NAME]],Aggregate!$AD:$AO,8,FALSE()),"") -> 90.049297 | Z67: =IF(Scoring!$K$6="Auction",IFERROR(VLOOKUP(Table11[[#This Row],[NAME]],Aggregate!$AD:$AO,10,FALSE()),""),IFERROR(VLOOKUP(Table11[[#This Row],[NAME]],Aggregate!$AD:$AO,9,FALSE()),"")) -> -35.628582 | AA67: =SUMIFS(AD68:$AD$84,AC68:$AC$84,"<>x",AC68:$AC$84,"<>o",AD68:$AD$84,">0")/Aggregate!$AL$1 -> 0 | AB67: =VLOOKUP(Table11[[#This Row],[NAME]],ECR!C:E,3,FALSE()) -> WR61 | AD67: =VLOOKUP(W67,Aggregate!AD:AL,9,FALSE()) -> -35.628582
B68: =IFERROR(VLOOKUP(Table12[[#This Row],[NAME]],Aggregate!$AR:$BC,11,FALSE()),"") -> 6 | C68: =Aggregate!AR21 -> Chig Okonkwo | D68: =VLOOKUP(Table12[[#This Row],[NAME]],Aggregate!AR:BD,4,FALSE()) -> WAS/7 | E68: =IFERROR(VLOOKUP($C68,Aggregate!$AR:$BC,8,FALSE()),"") -> 82.327596 | F68: =IF(Scoring!$K$6="Auction",IFERROR(VLOOKUP($C68,Aggregate!$AR:$BC,10,FALSE()),""),IFERROR(VLOOKUP($C68,Aggregate!$AR:$BC,9,FALSE()),"")) -> -30.246001 | G68: =SUMIFS(J69:$J$84,I69:$I$84,"<>x",I69:$I$84,"<>o",J69:$J$84,">0")/Aggregate!$AZ$1 -> 0 | H68: =VLOOKUP(Table12[[#This Row],[NAME]],ECR!C:E,3,FALSE()) -> TE19 | J68: =VLOOKUP(C68,Aggregate!AR:AZ,9,FALSE()) -> -30.246001 | L68: =IFERROR(VLOOKUP(Table10[[#This Row],[NAME]],Aggregate!$P:$AA,11,FALSE()),"") -> 9 | M68: =Aggregate!P56 -> Tyrone Tracy Jr. | N68: =VLOOKUP(Table10[[#This Row],[NAME]],Aggregate!P:AA,4,FALSE()) -> NYG/8 | O68: =IFERROR(VLOOKUP(Table10[[#This Row],[NAME]],Aggregate!$P:$AA,8,FALSE()),"") -> 55.695288 | P68: =IF(Scoring!$K$6="Auction",IFERROR(VLOOKUP(Table10[[#This Row],[NAME]],Aggregate!$P:$AA,10,FALSE()),""),IFERROR(VLOOKUP(Table10[[#This Row],[NAME]],Aggregate!$P:$AA,9,FALSE()),"")) -> -71.85045 | Q68: =SUMIFS(T69:$T$84,S69:$S$84,"<>x",S69:$S$84,"<>o",T69:$T$84,">0")/Aggregate!$X$1 -> 0 | R68: =VLOOKUP(Table10[[#This Row],[NAME]],ECR!C:E,3,FALSE()) -> RB54 | T68: =VLOOKUP(M68,Aggregate!P:X,9,FALSE()) -> -71.85045 | V68: =IFERROR(VLOOKUP(Table11[[#This Row],[NAME]],Aggregate!$AD:$AO,11,FALSE()),"") -> 8 | W68: =Aggregate!AD71 -> Omar Cooper Jr. | X68: =VLOOKUP(Table11[[#This Row],[NAME]],Aggregate!AD:AO,4,FALSE()) -> NYJ/13 | Y68: =IFERROR(VLOOKUP(Table11[[#This Row],[NAME]],Aggregate!$AD:$AO,8,FALSE()),"") -> 89.952282 | Z68: =IF(Scoring!$K$6="Auction",IFERROR(VLOOKUP(Table11[[#This Row],[NAME]],Aggregate!$AD:$AO,10,FALSE()),""),IFERROR(VLOOKUP(Table11[[#This Row],[NAME]],Aggregate!$AD:$AO,9,FALSE()),"")) -> -35.725596 | AA68: =SUMIFS(AD69:$AD$84,AC69:$AC$84,"<>x",AC69:$AC$84,"<>o",AD69:$AD$84,">0")/Aggregate!$AL$1 -> 0 | AB68: =VLOOKUP(Table11[[#This Row],[NAME]],ECR!C:E,3,FALSE()) -> WR69 | AD68: =VLOOKUP(W68,Aggregate!AD:AL,9,FALSE()) -> -35.725596
B69: =IFERROR(VLOOKUP(Table12[[#This Row],[NAME]],Aggregate!$AR:$BC,11,FALSE()),"") -> 6 | C69: =Aggregate!AR26 -> Kenyon Sadiq | D69: =VLOOKUP(Table12[[#This Row],[NAME]],Aggregate!AR:BD,4,FALSE()) -> NYJ/13 | E69: =IFERROR(VLOOKUP($C69,Aggregate!$AR:$BC,8,FALSE()),"") -> 81.233664 | F69: =IF(Scoring!$K$6="Auction",IFERROR(VLOOKUP($C69,Aggregate!$AR:$BC,10,FALSE()),""),IFERROR(VLOOKUP($C69,Aggregate!$AR:$BC,9,FALSE()),"")) -> -31.339934 | G69: =SUMIFS(J70:$J$84,I70:$I$84,"<>x",I70:$I$84,"<>o",J70:$J$84,">0")/Aggregate!$AZ$1 -> 0 | H69: =VLOOKUP(Table12[[#This Row],[NAME]],ECR!C:E,3,FALSE()) -> TE24 | J69: =VLOOKUP(C69,Aggregate!AR:AZ,9,FALSE()) -> -31.339934 | L69: =IFERROR(VLOOKUP(Table10[[#This Row],[NAME]],Aggregate!$P:$AA,11,FALSE()),"") -> 9 | M69: =Aggregate!P75 -> Demond Claiborne | N69: =VLOOKUP(Table10[[#This Row],[NAME]],Aggregate!P:AA,4,FALSE()) -> MIN/6 | O69: =IFERROR(VLOOKUP(Table10[[#This Row],[NAME]],Aggregate!$P:$AA,8,FALSE()),"") -> 53.837731 | P69: =IF(Scoring!$K$6="Auction",IFERROR(VLOOKUP(Table10[[#This Row],[NAME]],Aggregate!$P:$AA,10,FALSE()),""),IFERROR(VLOOKUP(Table10[[#This Row],[NAME]],Aggregate!$P:$AA,9,FALSE()),"")) -> -73.708007 | Q69: =SUMIFS(T70:$T$84,S70:$S$84,"<>x",S70:$S$84,"<>o",T70:$T$84,">0")/Aggregate!$X$1 -> 0 | R69: =VLOOKUP(Table10[[#This Row],[NAME]],ECR!C:E,3,FALSE()) -> RB73 | T69: =VLOOKUP(M69,Aggregate!P:X,9,FALSE()) -> -73.708007 | V69: =IFERROR(VLOOKUP(Table11[[#This Row],[NAME]],Aggregate!$AD:$AO,11,FALSE()),"") -> 8 | W69: =Aggregate!AD79 -> Chris Bell | X69: =VLOOKUP(Table11[[#This Row],[NAME]],Aggregate!AD:AO,4,FALSE()) -> MIA/6 | Y69: =IFERROR(VLOOKUP(Table11[[#This Row],[NAME]],Aggregate!$AD:$AO,8,FALSE()),"") -> 88.484788 | Z69: =IF(Scoring!$K$6="Auction",IFERROR(VLOOKUP(Table11[[#This Row],[NAME]],Aggregate!$AD:$AO,10,FALSE()),""),IFERROR(VLOOKUP(Table11[[#This Row],[NAME]],Aggregate!$AD:$AO,9,FALSE()),"")) -> -37.19309 | AA69: =SUMIFS(AD70:$AD$84,AC70:$AC$84,"<>x",AC70:$AC$84,"<>o",AD70:$AD$84,">0")/Aggregate!$AL$1 -> 0 | AB69: =VLOOKUP(Table11[[#This Row],[NAME]],ECR!C:E,3,FALSE()) -> WR77 | AD69: =VLOOKUP(W69,Aggregate!AD:AL,9,FALSE()) -> -37.19309
B70: =IFERROR(VLOOKUP(Table12[[#This Row],[NAME]],Aggregate!$AR:$BC,11,FALSE()),"") -> 6 | C70: =Aggregate!AR23 -> Terrance Ferguson | D70: =VLOOKUP(Table12[[#This Row],[NAME]],Aggregate!AR:BD,4,FALSE()) -> LAR/11 | E70: =IFERROR(VLOOKUP($C70,Aggregate!$AR:$BC,8,FALSE()),"") -> 80.392892 | F70: =IF(Scoring!$K$6="Auction",IFERROR(VLOOKUP($C70,Aggregate!$AR:$BC,10,FALSE()),""),IFERROR(VLOOKUP($C70,Aggregate!$AR:$BC,9,FALSE()),"")) -> -32.180705 | G70: =SUMIFS(J71:$J$84,I71:$I$84,"<>x",I71:$I$84,"<>o",J71:$J$84,">0")/Aggregate!$AZ$1 -> 0 | H70: =VLOOKUP(Table12[[#This Row],[NAME]],ECR!C:E,3,FALSE()) -> TE21 | J70: =VLOOKUP(C70,Aggregate!AR:AZ,9,FALSE()) -> -32.180705 | L70: =IFERROR(VLOOKUP(Table10[[#This Row],[NAME]],Aggregate!$P:$AA,11,FALSE()),"") -> 9 | M70: =Aggregate!P69 -> Najee Harris | N70: =VLOOKUP(Table10[[#This Row],[NAME]],Aggregate!P:AA,4,FALSE()) -> NYG/8 | O70: =IFERROR(VLOOKUP(Table10[[#This Row],[NAME]],Aggregate!$P:$AA,8,FALSE()),"") -> 53.44402 | P70: =IF(Scoring!$K$6="Auction",IFERROR(VLOOKUP(Table10[[#This Row],[NAME]],Aggregate!$P:$AA,10,FALSE()),""),IFERROR(VLOOKUP(Table10[[#This Row],[NAME]],Aggregate!$P:$AA,9,FALSE()),"")) -> -74.101719 | Q70: =SUMIFS(T71:$T$84,S71:$S$84,"<>x",S71:$S$84,"<>o",T71:$T$84,">0")/Aggregate!$X$1 -> 0 | R70: =VLOOKUP(Table10[[#This Row],[NAME]],ECR!C:E,3,FALSE()) -> RB67 | T70: =VLOOKUP(M70,Aggregate!P:X,9,FALSE()) -> -74.101719 | V70: =IFERROR(VLOOKUP(Table11[[#This Row],[NAME]],Aggregate!$AD:$AO,11,FALSE()),"") -> 8 | W70: =Aggregate!AD64 -> Jalen McMillan | X70: =VLOOKUP(Table11[[#This Row],[NAME]],Aggregate!AD:AO,4,FALSE()) -> TB/10 | Y70: =IFERROR(VLOOKUP(Table11[[#This Row],[NAME]],Aggregate!$AD:$AO,8,FALSE()),"") -> 88.067899 | Z70: =IF(Scoring!$K$6="Auction",IFERROR(VLOOKUP(Table11[[#This Row],[NAME]],Aggregate!$AD:$AO,10,FALSE()),""),IFERROR(VLOOKUP(Table11[[#This Row],[NAME]],Aggregate!$AD:$AO,9,FALSE()),"")) -> -37.60998 | AA70: =SUMIFS(AD71:$AD$84,AC71:$AC$84,"<>x",AC71:$AC$84,"<>o",AD71:$AD$84,">0")/Aggregate!$AL$1 -> 0 | AB70: =VLOOKUP(Table11[[#This Row],[NAME]],ECR!C:E,3,FALSE()) -> WR62 | AD70: =VLOOKUP(W70,Aggregate!AD:AL,9,FALSE()) -> -37.60998
B71: =IFERROR(VLOOKUP(Table12[[#This Row],[NAME]],Aggregate!$AR:$BC,11,FALSE()),"") -> 6 | C71: =Aggregate!AR29 -> Pat Freiermuth | D71: =VLOOKUP(Table12[[#This Row],[NAME]],Aggregate!AR:BD,4,FALSE()) -> PIT/9 | E71: =IFERROR(VLOOKUP($C71,Aggregate!$AR:$BC,8,FALSE()),"") -> 79.748627 | F71: =IF(Scoring!$K$6="Auction",IFERROR(VLOOKUP($C71,Aggregate!$AR:$BC,10,FALSE()),""),IFERROR(VLOOKUP($C71,Aggregate!$AR:$BC,9,FALSE()),"")) -> -32.82497 | G71: =SUMIFS(J72:$J$84,I72:$I$84,"<>x",I72:$I$84,"<>o",J72:$J$84,">0")/Aggregate!$AZ$1 -> 0 | H71: =VLOOKUP(Table12[[#This Row],[NAME]],ECR!C:E,3,FALSE()) -> TE27 | J71: =VLOOKUP(C71,Aggregate!AR:AZ,9,FALSE()) -> -32.82497 | L71: =IFERROR(VLOOKUP(Table10[[#This Row],[NAME]],Aggregate!$P:$AA,11,FALSE()),"") -> 9 | M71: =Aggregate!P81 -> Ty Johnson | N71: =VLOOKUP(Table10[[#This Row],[NAME]],Aggregate!P:AA,4,FALSE()) -> BUF/7 | O71: =IFERROR(VLOOKUP(Table10[[#This Row],[NAME]],Aggregate!$P:$AA,8,FALSE()),"") -> 50.635 | P71: =IF(Scoring!$K$6="Auction",IFERROR(VLOOKUP(Table10[[#This Row],[NAME]],Aggregate!$P:$AA,10,FALSE()),""),IFERROR(VLOOKUP(Table10[[#This Row],[NAME]],Aggregate!$P:$AA,9,FALSE()),"")) -> -76.910738 | Q71: =SUMIFS(T72:$T$84,S72:$S$84,"<>x",S72:$S$84,"<>o",T72:$T$84,">0")/Aggregate!$X$1 -> 0 | R71: =VLOOKUP(Table10[[#This Row],[NAME]],ECR!C:E,3,FALSE()) -> RB79 | T71: =VLOOKUP(M71,Aggregate!P:X,9,FALSE()) -> -76.910738 | V71: =IFERROR(VLOOKUP(Table11[[#This Row],[NAME]],Aggregate!$AD:$AO,11,FALSE()),"") -> 8 | W71: =Aggregate!AD67 -> Jauan Jennings | X71: =VLOOKUP(Table11[[#This Row],[NAME]],Aggregate!AD:AO,4,FALSE()) -> MIN/6 | Y71: =IFERROR(VLOOKUP(Table11[[#This Row],[NAME]],Aggregate!$AD:$AO,8,FALSE()),"") -> 87.161707 | Z71: =IF(Scoring!$K$6="Auction",IFERROR(VLOOKUP(Table11[[#This Row],[NAME]],Aggregate!$AD:$AO,10,FALSE()),""),IFERROR(VLOOKUP(Table11[[#This Row],[NAME]],Aggregate!$AD:$AO,9,FALSE()),"")) -> -38.516171 | AA71: =SUMIFS(AD72:$AD$84,AC72:$AC$84,"<>x",AC72:$AC$84,"<>o",AD72:$AD$84,">0")/Aggregate!$AL$1 -> 0 | AB71: =VLOOKUP(Table11[[#This Row],[NAME]],ECR!C:E,3,FALSE()) -> WR65 | AD71: =VLOOKUP(W71,Aggregate!AD:AL,9,FALSE()) -> -38.516171
B72: =IFERROR(VLOOKUP(Table12[[#This Row],[NAME]],Aggregate!$AR:$BC,11,FALSE()),"") -> 6 | C72: =Aggregate!AR24 -> AJ Barner | D72: =VLOOKUP(Table12[[#This Row],[NAME]],Aggregate!AR:BD,4,FALSE()) -> SEA/11 | E72: =IFERROR(VLOOKUP($C72,Aggregate!$AR:$BC,8,FALSE()),"") -> 78.796569 | F72: =IF(Scoring!$K$6="Auction",IFERROR(VLOOKUP($C72,Aggregate!$AR:$BC,10,FALSE()),""),IFERROR(VLOOKUP($C72,Aggregate!$AR:$BC,9,FALSE()),"")) -> -33.777029 | G72: =SUMIFS(J73:$J$84,I73:$I$84,"<>x",I73:$I$84,"<>o",J73:$J$84,">0")/Aggregate!$AZ$1 -> 0 | H72: =VLOOKUP(Table12[[#This Row],[NAME]],ECR!C:E,3,FALSE()) -> TE22 | J72: =VLOOKUP(C72,Aggregate!AR:AZ,9,FALSE()) -> -33.777029 | L72: =IFERROR(VLOOKUP(Table10[[#This Row],[NAME]],Aggregate!$P:$AA,11,FALSE()),"") -> 10 | M72: =Aggregate!P61 -> Kimani Vidal | N72: =VLOOKUP(Table10[[#This Row],[NAME]],Aggregate!P:AA,4,FALSE()) -> LAC/7 | O72: =IFERROR(VLOOKUP(Table10[[#This Row],[NAME]],Aggregate!$P:$AA,8,FALSE()),"") -> 48.456863 | P72: =IF(Scoring!$K$6="Auction",IFERROR(VLOOKUP(Table10[[#This Row],[NAME]],Aggregate!$P:$AA,10,FALSE()),""),IFERROR(VLOOKUP(Table10[[#This Row],[NAME]],Aggregate!$P:$AA,9,FALSE()),"")) -> -79.088876 | Q72: =SUMIFS(T73:$T$84,S73:$S$84,"<>x",S73:$S$84,"<>o",T73:$T$84,">0")/Aggregate!$X$1 -> 0 | R72: =VLOOKUP(Table10[[#This Row],[NAME]],ECR!C:E,3,FALSE()) -> RB59 | T72: =VLOOKUP(M72,Aggregate!P:X,9,FALSE()) -> -79.088876 | V72: =IFERROR(VLOOKUP(Table11[[#This Row],[NAME]],Aggregate!$AD:$AO,11,FALSE()),"") -> 8 | W72: =Aggregate!AD73 -> Keenan Allen | X72: =VLOOKUP(Table11[[#This Row],[NAME]],Aggregate!AD:AO,4,FALSE()) -> IND/13 | Y72: =IFERROR(VLOOKUP(Table11[[#This Row],[NAME]],Aggregate!$AD:$AO,8,FALSE()),"") -> 86.459551 | Z72: =IF(Scoring!$K$6="Auction",IFERROR(VLOOKUP(Table11[[#This Row],[NAME]],Aggregate!$AD:$AO,10,FALSE()),""),IFERROR(VLOOKUP(Table11[[#This Row],[NAME]],Aggregate!$AD:$AO,9,FALSE()),"")) -> -39.218328 | AA72: =SUMIFS(AD73:$AD$84,AC73:$AC$84,"<>x",AC73:$AC$84,"<>o",AD73:$AD$84,">0")/Aggregate!$AL$1 -> 0 | AB72: =VLOOKUP(Table11[[#This Row],[NAME]],ECR!C:E,3,FALSE()) -> WR71 | AD72: =VLOOKUP(W72,Aggregate!AD:AL,9,FALSE()) -> -39.218328
B73: =IFERROR(VLOOKUP(Table12[[#This Row],[NAME]],Aggregate!$AR:$BC,11,FALSE()),"") -> 7 | C73: =Aggregate!AR30 -> Cade Otton | D73: =VLOOKUP(Table12[[#This Row],[NAME]],Aggregate!AR:BD,4,FALSE()) -> TB/10 | E73: =IFERROR(VLOOKUP($C73,Aggregate!$AR:$BC,8,FALSE()),"") -> 76.359706 | F73: =IF(Scoring!$K$6="Auction",IFERROR(VLOOKUP($C73,Aggregate!$AR:$BC,10,FALSE()),""),IFERROR(VLOOKUP($C73,Aggregate!$AR:$BC,9,FALSE()),"")) -> -36.213892 | G73: =SUMIFS(J74:$J$84,I74:$I$84,"<>x",I74:$I$84,"<>o",J74:$J$84,">0")/Aggregate!$AZ$1 -> 0 | H73: =VLOOKUP(Table12[[#This Row],[NAME]],ECR!C:E,3,FALSE()) -> TE28 | J73: =VLOOKUP(C73,Aggregate!AR:AZ,9,FALSE()) -> -36.213892 | L73: =IFERROR(VLOOKUP(Table10[[#This Row],[NAME]],Aggregate!$P:$AA,11,FALSE()),"") -> 10 | M73: =Aggregate!P76 -> Chris Brooks | N73: =VLOOKUP(Table10[[#This Row],[NAME]],Aggregate!P:AA,4,FALSE()) -> GB/11 | O73: =IFERROR(VLOOKUP(Table10[[#This Row],[NAME]],Aggregate!$P:$AA,8,FALSE()),"") -> 48.191765 | P73: =IF(Scoring!$K$6="Auction",IFERROR(VLOOKUP(Table10[[#This Row],[NAME]],Aggregate!$P:$AA,10,FALSE()),""),IFERROR(VLOOKUP(Table10[[#This Row],[NAME]],Aggregate!$P:$AA,9,FALSE()),"")) -> -79.353974 | Q73: =SUMIFS(T74:$T$84,S74:$S$84,"<>x",S74:$S$84,"<>o",T74:$T$84,">0")/Aggregate!$X$1 -> 0 | R73: =VLOOKUP(Table10[[#This Row],[NAME]],ECR!C:E,3,FALSE()) -> RB74 | T73: =VLOOKUP(M73,Aggregate!P:X,9,FALSE()) -> -79.353974 | V73: =IFERROR(VLOOKUP(Table11[[#This Row],[NAME]],Aggregate!$AD:$AO,11,FALSE()),"") -> 8 | W73: =Aggregate!AD78 -> Rashod Bateman | X73: =VLOOKUP(Table11[[#This Row],[NAME]],Aggregate!AD:AO,4,FALSE()) -> BAL/13 | Y73: =IFERROR(VLOOKUP(Table11[[#This Row],[NAME]],Aggregate!$AD:$AO,8,FALSE()),"") -> 85.989538 | Z73: =IF(Scoring!$K$6="Auction",IFERROR(VLOOKUP(Table11[[#This Row],[NAME]],Aggregate!$AD:$AO,10,FALSE()),""),IFERROR(VLOOKUP(Table11[[#This Row],[NAME]],Aggregate!$AD:$AO,9,FALSE()),"")) -> -39.688341 | AA73: =SUMIFS(AD74:$AD$84,AC74:$AC$84,"<>x",AC74:$AC$84,"<>o",AD74:$AD$84,">0")/Aggregate!$AL$1 -> 0 | AB73: =VLOOKUP(Table11[[#This Row],[NAME]],ECR!C:E,3,FALSE()) -> WR76 | AD73: =VLOOKUP(W73,Aggregate!AD:AL,9,FALSE()) -> -39.688341
B74: =IFERROR(VLOOKUP(Table12[[#This Row],[NAME]],Aggregate!$AR:$BC,11,FALSE()),"") -> 7 | C74: =Aggregate!AR34 -> Greg Dulcich | D74: =VLOOKUP(Table12[[#This Row],[NAME]],Aggregate!AR:BD,4,FALSE()) -> MIA/6 | E74: =IFERROR(VLOOKUP($C74,Aggregate!$AR:$BC,8,FALSE()),"") -> 75.851176 | F74: =IF(Scoring!$K$6="Auction",IFERROR(VLOOKUP($C74,Aggregate!$AR:$BC,10,FALSE()),""),IFERROR(VLOOKUP($C74,Aggregate!$AR:$BC,9,FALSE()),"")) -> -36.722421 | G74: =SUMIFS(J75:$J$84,I75:$I$84,"<>x",I75:$I$84,"<>o",J75:$J$84,">0")/Aggregate!$AZ$1 -> 0 | H74: =VLOOKUP(Table12[[#This Row],[NAME]],ECR!C:E,3,FALSE()) -> TE32 | J74: =VLOOKUP(C74,Aggregate!AR:AZ,9,FALSE()) -> -36.722421 | L74: =IFERROR(VLOOKUP(Table10[[#This Row],[NAME]],Aggregate!$P:$AA,11,FALSE()),"") -> 10 | M74: =Aggregate!P79 -> Jordan James | N74: =VLOOKUP(Table10[[#This Row],[NAME]],Aggregate!P:AA,4,FALSE()) -> SF/8 | O74: =IFERROR(VLOOKUP(Table10[[#This Row],[NAME]],Aggregate!$P:$AA,8,FALSE()),"") -> 44.978725 | P74: =IF(Scoring!$K$6="Auction",IFERROR(VLOOKUP(Table10[[#This Row],[NAME]],Aggregate!$P:$AA,10,FALSE()),""),IFERROR(VLOOKUP(Table10[[#This Row],[NAME]],Aggregate!$P:$AA,9,FALSE()),"")) -> -82.567013 | Q74: =SUMIFS(T75:$T$84,S75:$S$84,"<>x",S75:$S$84,"<>o",T75:$T$84,">0")/Aggregate!$X$1 -> 0 | R74: =VLOOKUP(Table10[[#This Row],[NAME]],ECR!C:E,3,FALSE()) -> RB77 | T74: =VLOOKUP(M74,Aggregate!P:X,9,FALSE()) -> -82.567013 | V74: =IFERROR(VLOOKUP(Table11[[#This Row],[NAME]],Aggregate!$AD:$AO,11,FALSE()),"") -> 8 | W74: =Aggregate!AD72 -> Jalen Nailor | X74: =VLOOKUP(Table11[[#This Row],[NAME]],Aggregate!AD:AO,4,FALSE()) -> LV/13 | Y74: =IFERROR(VLOOKUP(Table11[[#This Row],[NAME]],Aggregate!$AD:$AO,8,FALSE()),"") -> 83.341777 | Z74: =IF(Scoring!$K$6="Auction",IFERROR(VLOOKUP(Table11[[#This Row],[NAME]],Aggregate!$AD:$AO,10,FALSE()),""),IFERROR(VLOOKUP(Table11[[#This Row],[NAME]],Aggregate!$AD:$AO,9,FALSE()),"")) -> -42.336102 | AA74: =SUMIFS(AD75:$AD$84,AC75:$AC$84,"<>x",AC75:$AC$84,"<>o",AD75:$AD$84,">0")/Aggregate!$AL$1 -> 0 | AB74: =VLOOKUP(Table11[[#This Row],[NAME]],ECR!C:E,3,FALSE()) -> WR70 | AD74: =VLOOKUP(W74,Aggregate!AD:AL,9,FALSE()) -> -42.336102
B75: =IFERROR(VLOOKUP(Table12[[#This Row],[NAME]],Aggregate!$AR:$BC,11,FALSE()),"") -> 7 | C75: =Aggregate!AR27 -> Gunnar Helm | D75: =VLOOKUP(Table12[[#This Row],[NAME]],Aggregate!AR:BD,4,FALSE()) -> TEN/9 | E75: =IFERROR(VLOOKUP($C75,Aggregate!$AR:$BC,8,FALSE()),"") -> 70.740204 | F75: =IF(Scoring!$K$6="Auction",IFERROR(VLOOKUP($C75,Aggregate!$AR:$BC,10,FALSE()),""),IFERROR(VLOOKUP($C75,Aggregate!$AR:$BC,9,FALSE()),"")) -> -41.833394 | G75: =SUMIFS(J76:$J$84,I76:$I$84,"<>x",I76:$I$84,"<>o",J76:$J$84,">0")/Aggregate!$AZ$1 -> 0 | H75: =VLOOKUP(Table12[[#This Row],[NAME]],ECR!C:E,3,FALSE()) -> TE25 | J75: =VLOOKUP(C75,Aggregate!AR:AZ,9,FALSE()) -> -41.833394 | L75: =IFERROR(VLOOKUP(Table10[[#This Row],[NAME]],Aggregate!$P:$AA,11,FALSE()),"") -> 10 | M75: =Aggregate!P70 -> Jaylen Wright | N75: =VLOOKUP(Table10[[#This Row],[NAME]],Aggregate!P:AA,4,FALSE()) -> MIA/6 | O75: =IFERROR(VLOOKUP(Table10[[#This Row],[NAME]],Aggregate!$P:$AA,8,FALSE()),"") -> 42.622157 | P75: =IF(Scoring!$K$6="Auction",IFERROR(VLOOKUP(Table10[[#This Row],[NAME]],Aggregate!$P:$AA,10,FALSE()),""),IFERROR(VLOOKUP(Table10[[#This Row],[NAME]],Aggregate!$P:$AA,9,FALSE()),"")) -> -84.923582 | Q75: =SUMIFS(T76:$T$84,S76:$S$84,"<>x",S76:$S$84,"<>o",T76:$T$84,">0")/Aggregate!$X$1 -> 0 | R75: =VLOOKUP(Table10[[#This Row],[NAME]],ECR!C:E,3,FALSE()) -> RB68 | T75: =VLOOKUP(M75,Aggregate!P:X,9,FALSE()) -> -84.923582 | V75: =IFERROR(VLOOKUP(Table11[[#This Row],[NAME]],Aggregate!$AD:$AO,11,FALSE()),"") -> 8 | W75: =Aggregate!AD62 -> Adonai Mitchell | X75: =VLOOKUP(Table11[[#This Row],[NAME]],Aggregate!AD:AO,4,FALSE()) -> NYJ/13 | Y75: =IFERROR(VLOOKUP(Table11[[#This Row],[NAME]],Aggregate!$AD:$AO,8,FALSE()),"") -> 80.935753 | Z75: =IF(Scoring!$K$6="Auction",IFERROR(VLOOKUP(Table11[[#This Row],[NAME]],Aggregate!$AD:$AO,10,FALSE()),""),IFERROR(VLOOKUP(Table11[[#This Row],[NAME]],Aggregate!$AD:$AO,9,FALSE()),"")) -> -44.742125 | AA75: =SUMIFS(AD76:$AD$84,AC76:$AC$84,"<>x",AC76:$AC$84,"<>o",AD76:$AD$84,">0")/Aggregate!$AL$1 -> 0 | AB75: =VLOOKUP(Table11[[#This Row],[NAME]],ECR!C:E,3,FALSE()) -> WR60 | AD75: =VLOOKUP(W75,Aggregate!AD:AL,9,FALSE()) -> -44.742125
B76: =IFERROR(VLOOKUP(Table12[[#This Row],[NAME]],Aggregate!$AR:$BC,11,FALSE()),"") -> 7 | C76: =Aggregate!AR31 -> Evan Engram | D76: =VLOOKUP(Table12[[#This Row],[NAME]],Aggregate!AR:BD,4,FALSE()) -> DEN/10 | E76: =IFERROR(VLOOKUP($C76,Aggregate!$AR:$BC,8,FALSE()),"") -> 68.659118 | F76: =IF(Scoring!$K$6="Auction",IFERROR(VLOOKUP($C76,Aggregate!$AR:$BC,10,FALSE()),""),IFERROR(VLOOKUP($C76,Aggregate!$AR:$BC,9,FALSE()),"")) -> -43.91448 | G76: =SUMIFS(J76:$J$84,I76:$I$84,"<>x",I76:$I$84,"<>o",J76:$J$84,">0")/Aggregate!$AZ$1 -> 0 | H76: =VLOOKUP(Table12[[#This Row],[NAME]],ECR!C:E,3,FALSE()) -> TE29 | J76: =VLOOKUP(C76,Aggregate!AR:AZ,9,FALSE()) -> -43.91448 | L76: =IFERROR(VLOOKUP(Table10[[#This Row],[NAME]],Aggregate!$P:$AA,11,FALSE()),"") -> 10 | M76: =Aggregate!P73 -> Emanuel Wilson | N76: =VLOOKUP(Table10[[#This Row],[NAME]],Aggregate!P:AA,4,FALSE()) -> SEA/11 | O76: =IFERROR(VLOOKUP(Table10[[#This Row],[NAME]],Aggregate!$P:$AA,8,FALSE()),"") -> 40.263039 | P76: =IF(Scoring!$K$6="Auction",IFERROR(VLOOKUP(Table10[[#This Row],[NAME]],Aggregate!$P:$AA,10,FALSE()),""),IFERROR(VLOOKUP(Table10[[#This Row],[NAME]],Aggregate!$P:$AA,9,FALSE()),"")) -> -87.282699 | Q76: =SUMIFS(T77:$T$84,S77:$S$84,"<>x",S77:$S$84,"<>o",T77:$T$84,">0")/Aggregate!$X$1 -> 0 | R76: =VLOOKUP(Table10[[#This Row],[NAME]],ECR!C:E,3,FALSE()) -> RB71 | T76: =VLOOKUP(M76,Aggregate!P:X,9,FALSE()) -> -87.282699 | V76: =IFERROR(VLOOKUP(Table11[[#This Row],[NAME]],Aggregate!$AD:$AO,11,FALSE()),"") -> 8 | W76: =Aggregate!AD82 -> Malachi Fields | X76: =VLOOKUP(Table11[[#This Row],[NAME]],Aggregate!AD:AO,4,FALSE()) -> NYG/8 | Y76: =IFERROR(VLOOKUP(Table11[[#This Row],[NAME]],Aggregate!$AD:$AO,8,FALSE()),"") -> 79.767555 | Z76: =IF(Scoring!$K$6="Auction",IFERROR(VLOOKUP(Table11[[#This Row],[NAME]],Aggregate!$AD:$AO,10,FALSE()),""),IFERROR(VLOOKUP(Table11[[#This Row],[NAME]],Aggregate!$AD:$AO,9,FALSE()),"")) -> -45.910324 | AA76: =SUMIFS(AD77:$AD$84,AC77:$AC$84,"<>x",AC77:$AC$84,"<>o",AD77:$AD$84,">0")/Aggregate!$AL$1 -> 0 | AB76: =VLOOKUP(Table11[[#This Row],[NAME]],ECR!C:E,3,FALSE()) -> WR80 | AD76: =VLOOKUP(W76,Aggregate!AD:AL,9,FALSE()) -> -45.910324
B77: =IFERROR(VLOOKUP(Table12[[#This Row],[NAME]],Aggregate!$AR:$BC,11,FALSE()),"") -> 7 | C77: =Aggregate!AR32 -> David Njoku | D77: =VLOOKUP(Table12[[#This Row],[NAME]],Aggregate!AR:BD,4,FALSE()) -> LAC/7 | E77: =IFERROR(VLOOKUP($C77,Aggregate!$AR:$BC,8,FALSE()),"") -> 66.712941 | F77: =IF(Scoring!$K$6="Auction",IFERROR(VLOOKUP($C77,Aggregate!$AR:$BC,10,FALSE()),""),IFERROR(VLOOKUP($C77,Aggregate!$AR:$BC,9,FALSE()),"")) -> -45.860656 | G77: 0 | H77: =VLOOKUP(Table12[[#This Row],[NAME]],ECR!C:E,3,FALSE()) -> TE30 | J77: =VLOOKUP(C77,Aggregate!AR:AZ,9,FALSE()) -> -45.860656 | L77: =IFERROR(VLOOKUP(Table10[[#This Row],[NAME]],Aggregate!$P:$AA,11,FALSE()),"") -> 10 | M77: =Aggregate!P60 -> Ray Davis | N77: =VLOOKUP(Table10[[#This Row],[NAME]],Aggregate!P:AA,4,FALSE()) -> BUF/7 | O77: =IFERROR(VLOOKUP(Table10[[#This Row],[NAME]],Aggregate!$P:$AA,8,FALSE()),"") -> 38.500389 | P77: =IF(Scoring!$K$6="Auction",IFERROR(VLOOKUP(Table10[[#This Row],[NAME]],Aggregate!$P:$AA,10,FALSE()),""),IFERROR(VLOOKUP(Table10[[#This Row],[NAME]],Aggregate!$P:$AA,9,FALSE()),"")) -> -89.04535 | Q77: =SUMIFS(T78:$T$84,S78:$S$84,"<>x",S78:$S$84,"<>o",T78:$T$84,">0")/Aggregate!$X$1 -> 0 | R77: =VLOOKUP(Table10[[#This Row],[NAME]],ECR!C:E,3,FALSE()) -> RB58 | T77: =VLOOKUP(M77,Aggregate!P:X,9,FALSE()) -> -89.04535 | V77: =IFERROR(VLOOKUP(Table11[[#This Row],[NAME]],Aggregate!$AD:$AO,11,FALSE()),"") -> 8 | W77: =Aggregate!AD81 -> Zachariah Branch | X77: =VLOOKUP(Table11[[#This Row],[NAME]],Aggregate!AD:AO,4,FALSE()) -> ATL/11 | Y77: =IFERROR(VLOOKUP(Table11[[#This Row],[NAME]],Aggregate!$AD:$AO,8,FALSE()),"") -> 78.672801 | Z77: =IF(Scoring!$K$6="Auction",IFERROR(VLOOKUP(Table11[[#This Row],[NAME]],Aggregate!$AD:$AO,10,FALSE()),""),IFERROR(VLOOKUP(Table11[[#This Row],[NAME]],Aggregate!$AD:$AO,9,FALSE()),"")) -> -47.005077 | AA77: =SUMIFS(AD78:$AD$84,AC78:$AC$84,"<>x",AC78:$AC$84,"<>o",AD78:$AD$84,">0")/Aggregate!$AL$1 -> 0 | AB77: =VLOOKUP(Table11[[#This Row],[NAME]],ECR!C:E,3,FALSE()) -> WR79 | AD77: =VLOOKUP(W77,Aggregate!AD:AL,9,FALSE()) -> -47.005077
B78: =IFERROR(VLOOKUP(Table12[[#This Row],[NAME]],Aggregate!$AR:$BC,11,FALSE()),"") -> 8 | C78: =Aggregate!AR39 -> Darren Waller | D78: =VLOOKUP(Table12[[#This Row],[NAME]],Aggregate!AR:BD,4,FALSE()) -> CAR/5 | E78: =IFERROR(VLOOKUP($C78,Aggregate!$AR:$BC,8,FALSE()),"") -> 64.743824 | F78: =IF(Scoring!$K$6="Auction",IFERROR(VLOOKUP($C78,Aggregate!$AR:$BC,10,FALSE()),""),IFERROR(VLOOKUP($C78,Aggregate!$AR:$BC,9,FALSE()),"")) -> -47.829774 | G78: =SUMIFS(J78:$J$85,I78:$I$85,"<>x",I78:$I$85,"<>o",J78:$J$85,">0")/Aggregate!$AZ$1 -> 0 | H78: =VLOOKUP(Table12[[#This Row],[NAME]],ECR!C:E,3,FALSE()) -> TE37 | J78: =VLOOKUP(C78,Aggregate!AR:AZ,9,FALSE()) -> -47.829774 | L78: =IFERROR(VLOOKUP(Table10[[#This Row],[NAME]],Aggregate!$P:$AA,11,FALSE()),"") -> 10 | M78: =Aggregate!P72 -> James Conner | N78: =VLOOKUP(Table10[[#This Row],[NAME]],Aggregate!P:AA,4,FALSE()) -> ARI/14 | O78: =IFERROR(VLOOKUP(Table10[[#This Row],[NAME]],Aggregate!$P:$AA,8,FALSE()),"") -> 38.166471 | P78: =IF(Scoring!$K$6="Auction",IFERROR(VLOOKUP(Table10[[#This Row],[NAME]],Aggregate!$P:$AA,10,FALSE()),""),IFERROR(VLOOKUP(Table10[[#This Row],[NAME]],Aggregate!$P:$AA,9,FALSE()),"")) -> -89.379268 | Q78: =SUMIFS(T79:$T$84,S79:$S$84,"<>x",S79:$S$84,"<>o",T79:$T$84,">0")/Aggregate!$X$1 -> 0 | R78: =VLOOKUP(Table10[[#This Row],[NAME]],ECR!C:E,3,FALSE()) -> RB70 | T78: =VLOOKUP(M78,Aggregate!P:X,9,FALSE()) -> -89.379268 | V78: =IFERROR(VLOOKUP(Table11[[#This Row],[NAME]],Aggregate!$AD:$AO,11,FALSE()),"") -> 8 | W78: =Aggregate!AD76 -> Jaylin Noel | X78: =VLOOKUP(Table11[[#This Row],[NAME]],Aggregate!AD:AO,4,FALSE()) -> HOU/8 | Y78: =IFERROR(VLOOKUP(Table11[[#This Row],[NAME]],Aggregate!$AD:$AO,8,FALSE()),"") -> 77.746959 | Z78: =IF(Scoring!$K$6="Auction",IFERROR(VLOOKUP(Table11[[#This Row],[NAME]],Aggregate!$AD:$AO,10,FALSE()),""),IFERROR(VLOOKUP(Table11[[#This Row],[NAME]],Aggregate!$AD:$AO,9,FALSE()),"")) -> -47.930919 | AA78: =SUMIFS(AD79:$AD$84,AC79:$AC$84,"<>x",AC79:$AC$84,"<>o",AD79:$AD$84,">0")/Aggregate!$AL$1 -> 0 | AB78: =VLOOKUP(Table11[[#This Row],[NAME]],ECR!C:E,3,FALSE()) -> WR74 | AD78: =VLOOKUP(W78,Aggregate!AD:AL,9,FALSE()) -> -47.930919
B79: =IFERROR(VLOOKUP(Table12[[#This Row],[NAME]],Aggregate!$AR:$BC,11,FALSE()),"") -> 8 | C79: =Aggregate!AR28 -> Oronde Gadsden II | D79: =VLOOKUP(Table12[[#This Row],[NAME]],Aggregate!AR:BD,4,FALSE()) -> LAC/7 | E79: =IFERROR(VLOOKUP($C79,Aggregate!$AR:$BC,8,FALSE()),"") -> 62.92 | F79: =IF(Scoring!$K$6="Auction",IFERROR(VLOOKUP($C79,Aggregate!$AR:$BC,10,FALSE()),""),IFERROR(VLOOKUP($C79,Aggregate!$AR:$BC,9,FALSE()),"")) -> -49.653597 | G79: =SUMIFS(J80:$J$84,I80:$I$84,"<>x",I80:$I$84,"<>o",J80:$J$84,">0")/Aggregate!$AZ$1 -> 0 | H79: =VLOOKUP(Table12[[#This Row],[NAME]],ECR!C:E,3,FALSE()) -> TE26 | J79: =VLOOKUP(C79,Aggregate!AR:AZ,9,FALSE()) -> -49.653597 | L79: =IFERROR(VLOOKUP(Table10[[#This Row],[NAME]],Aggregate!$P:$AA,11,FALSE()),"") -> 10 | M79: =Aggregate!P64 -> Sean Tucker | N79: =VLOOKUP(Table10[[#This Row],[NAME]],Aggregate!P:AA,4,FALSE()) -> TB/10 | O79: =IFERROR(VLOOKUP(Table10[[#This Row],[NAME]],Aggregate!$P:$AA,8,FALSE()),"") -> 36.350773 | P79: =IF(Scoring!$K$6="Auction",IFERROR(VLOOKUP(Table10[[#This Row],[NAME]],Aggregate!$P:$AA,10,FALSE()),""),IFERROR(VLOOKUP(Table10[[#This Row],[NAME]],Aggregate!$P:$AA,9,FALSE()),"")) -> -91.194965 | Q79: =SUMIFS(T80:$T$84,S80:$S$84,"<>x",S80:$S$84,"<>o",T80:$T$84,">0")/Aggregate!$X$1 -> 0 | R79: =VLOOKUP(Table10[[#This Row],[NAME]],ECR!C:E,3,FALSE()) -> RB62 | T79: =VLOOKUP(M79,Aggregate!P:X,9,FALSE()) -> -91.194965 | V79: =IFERROR(VLOOKUP(Table11[[#This Row],[NAME]],Aggregate!$AD:$AO,11,FALSE()),"") -> 8 | W79: =Aggregate!AD65 -> Dontayvion Wicks | X79: =VLOOKUP(Table11[[#This Row],[NAME]],Aggregate!AD:AO,4,FALSE()) -> PHI/10 | Y79: =IFERROR(VLOOKUP(Table11[[#This Row],[NAME]],Aggregate!$AD:$AO,8,FALSE()),"") -> 73.939253 | Z79: =IF(Scoring!$K$6="Auction",IFERROR(VLOOKUP(Table11[[#This Row],[NAME]],Aggregate!$AD:$AO,10,FALSE()),""),IFERROR(VLOOKUP(Table11[[#This Row],[NAME]],Aggregate!$AD:$AO,9,FALSE()),"")) -> -51.738626 | AA79: =SUMIFS(AD80:$AD$84,AC80:$AC$84,"<>x",AC80:$AC$84,"<>o",AD80:$AD$84,">0")/Aggregate!$AL$1 -> 0 | AB79: =VLOOKUP(Table11[[#This Row],[NAME]],ECR!C:E,3,FALSE()) -> WR63 | AD79: =VLOOKUP(W79,Aggregate!AD:AL,9,FALSE()) -> -51.738626
B80: =IFERROR(VLOOKUP(Table12[[#This Row],[NAME]],Aggregate!$AR:$BC,11,FALSE()),"") -> 8 | C80: =Aggregate!AR38 -> Mike Gesicki | D80: =VLOOKUP(Table12[[#This Row],[NAME]],Aggregate!AR:BD,4,FALSE()) -> CIN/6 | E80: =IFERROR(VLOOKUP($C80,Aggregate!$AR:$BC,8,FALSE()),"") -> 62.602647 | F80: =IF(Scoring!$K$6="Auction",IFERROR(VLOOKUP($C80,Aggregate!$AR:$BC,10,FALSE()),""),IFERROR(VLOOKUP($C80,Aggregate!$AR:$BC,9,FALSE()),"")) -> -49.97095 | G80: =SUMIFS(J80:$J$85,I80:$I$85,"<>x",I80:$I$85,"<>o",J80:$J$85,">0")/Aggregate!$AZ$1 -> 0 | H80: =VLOOKUP(Table12[[#This Row],[NAME]],ECR!C:E,3,FALSE()) -> TE36 | J80: =VLOOKUP(C80,Aggregate!AR:AZ,9,FALSE()) -> -49.97095 | L80: =IFERROR(VLOOKUP(Table10[[#This Row],[NAME]],Aggregate!$P:$AA,11,FALSE()),"") -> 10 | M80: =Aggregate!P68 -> George Holani | N80: =VLOOKUP(Table10[[#This Row],[NAME]],Aggregate!P:AA,4,FALSE()) -> SEA/11 | O80: =IFERROR(VLOOKUP(Table10[[#This Row],[NAME]],Aggregate!$P:$AA,8,FALSE()),"") -> 34.506078 | P80: =IF(Scoring!$K$6="Auction",IFERROR(VLOOKUP(Table10[[#This Row],[NAME]],Aggregate!$P:$AA,10,FALSE()),""),IFERROR(VLOOKUP(Table10[[#This Row],[NAME]],Aggregate!$P:$AA,9,FALSE()),"")) -> -93.03966 | Q80: =SUMIFS(T81:$T$84,S81:$S$84,"<>x",S81:$S$84,"<>o",T81:$T$84,">0")/Aggregate!$X$1 -> 0 | R80: =VLOOKUP(Table10[[#This Row],[NAME]],ECR!C:E,3,FALSE()) -> RB66 | T80: =VLOOKUP(M80,Aggregate!P:X,9,FALSE()) -> -93.03966 | V80: =IFERROR(VLOOKUP(Table11[[#This Row],[NAME]],Aggregate!$AD:$AO,11,FALSE()),"") -> 9 | W80: =Aggregate!AD74 -> Malik Washington | X80: =VLOOKUP(Table11[[#This Row],[NAME]],Aggregate!AD:AO,4,FALSE()) -> MIA/6 | Y80: =IFERROR(VLOOKUP(Table11[[#This Row],[NAME]],Aggregate!$AD:$AO,8,FALSE()),"") -> 73.860805 | Z80: =IF(Scoring!$K$6="Auction",IFERROR(VLOOKUP(Table11[[#This Row],[NAME]],Aggregate!$AD:$AO,10,FALSE()),""),IFERROR(VLOOKUP(Table11[[#This Row],[NAME]],Aggregate!$AD:$AO,9,FALSE()),"")) -> -51.817073 | AA80: =SUMIFS(AD81:$AD$84,AC81:$AC$84,"<>x",AC81:$AC$84,"<>o",AD81:$AD$84,">0")/Aggregate!$AL$1 -> 0 | AB80: =VLOOKUP(Table11[[#This Row],[NAME]],ECR!C:E,3,FALSE()) -> WR72 | AD80: =VLOOKUP(W80,Aggregate!AD:AL,9,FALSE()) -> -51.817073
B81: =IFERROR(VLOOKUP(Table12[[#This Row],[NAME]],Aggregate!$AR:$BC,11,FALSE()),"") -> 8 | C81: =Aggregate!AR33 -> Colby Parkinson | D81: =VLOOKUP(Table12[[#This Row],[NAME]],Aggregate!AR:BD,4,FALSE()) -> LAR/11 | E81: =IFERROR(VLOOKUP($C81,Aggregate!$AR:$BC,8,FALSE()),"") -> 61.173922 | F81: =IF(Scoring!$K$6="Auction",IFERROR(VLOOKUP($C81,Aggregate!$AR:$BC,10,FALSE()),""),IFERROR(VLOOKUP($C81,Aggregate!$AR:$BC,9,FALSE()),"")) -> -51.399676 | G81: =SUMIFS(J82:$J$84,I82:$I$84,"<>x",I82:$I$84,"<>o",J82:$J$84,">0")/Aggregate!$AZ$1 -> 0 | H81: =VLOOKUP(Table12[[#This Row],[NAME]],ECR!C:E,3,FALSE()) -> TE31 | J81: =VLOOKUP(C81,Aggregate!AR:AZ,9,FALSE()) -> -51.399676 | L81: =IFERROR(VLOOKUP(Table10[[#This Row],[NAME]],Aggregate!$P:$AA,11,FALSE()),"") -> 10 | M81: =Aggregate!P80 -> Isaiah Davis | N81: =VLOOKUP(Table10[[#This Row],[NAME]],Aggregate!P:AA,4,FALSE()) -> NYJ/13 | O81: =IFERROR(VLOOKUP(Table10[[#This Row],[NAME]],Aggregate!$P:$AA,8,FALSE()),"") -> 28.545196 | P81: =IF(Scoring!$K$6="Auction",IFERROR(VLOOKUP(Table10[[#This Row],[NAME]],Aggregate!$P:$AA,10,FALSE()),""),IFERROR(VLOOKUP(Table10[[#This Row],[NAME]],Aggregate!$P:$AA,9,FALSE()),"")) -> -99.000542 | Q81: =SUMIFS(T82:$T$84,S82:$S$84,"<>x",S82:$S$84,"<>o",T82:$T$84,">0")/Aggregate!$X$1 -> 0 | R81: =VLOOKUP(Table10[[#This Row],[NAME]],ECR!C:E,3,FALSE()) -> RB78 | T81: =VLOOKUP(M81,Aggregate!P:X,9,FALSE()) -> -99.000542 | V81: =IFERROR(VLOOKUP(Table11[[#This Row],[NAME]],Aggregate!$AD:$AO,11,FALSE()),"") -> 9 | W81: =Aggregate!AD77 -> Travis Hunter | X81: =VLOOKUP(Table11[[#This Row],[NAME]],Aggregate!AD:AO,4,FALSE()) -> JAC/7 | Y81: =IFERROR(VLOOKUP(Table11[[#This Row],[NAME]],Aggregate!$AD:$AO,8,FALSE()),"") -> 70.262085 | Z81: =IF(Scoring!$K$6="Auction",IFERROR(VLOOKUP(Table11[[#This Row],[NAME]],Aggregate!$AD:$AO,10,FALSE()),""),IFERROR(VLOOKUP(Table11[[#This Row],[NAME]],Aggregate!$AD:$AO,9,FALSE()),"")) -> -55.415794 | AA81: =SUMIFS(AD82:$AD$84,AC82:$AC$84,"<>x",AC82:$AC$84,"<>o",AD82:$AD$84,">0")/Aggregate!$AL$1 -> 0 | AB81: =VLOOKUP(Table11[[#This Row],[NAME]],ECR!C:E,3,FALSE()) -> WR75 | AD81: =VLOOKUP(W81,Aggregate!AD:AL,9,FALSE()) -> -55.415794
B82: =IFERROR(VLOOKUP(Table12[[#This Row],[NAME]],Aggregate!$AR:$BC,11,FALSE()),"") -> 8 | C82: =Aggregate!AR35 -> Mason Taylor | D82: =VLOOKUP(Table12[[#This Row],[NAME]],Aggregate!AR:BD,4,FALSE()) -> NYJ/13 | E82: =IFERROR(VLOOKUP($C82,Aggregate!$AR:$BC,8,FALSE()),"") -> 57.823235 | F82: =IF(Scoring!$K$6="Auction",IFERROR(VLOOKUP($C82,Aggregate!$AR:$BC,10,FALSE()),""),IFERROR(VLOOKUP($C82,Aggregate!$AR:$BC,9,FALSE()),"")) -> -54.750362 | G82: =SUMIFS(J83:$J$84,I83:$I$84,"<>x",I83:$I$84,"<>o",J83:$J$84,">0")/Aggregate!$AZ$1 -> 0 | H82: =VLOOKUP(Table12[[#This Row],[NAME]],ECR!C:E,3,FALSE()) -> TE33 | J82: =VLOOKUP(C82,Aggregate!AR:AZ,9,FALSE()) -> -54.750362 | L82: =IFERROR(VLOOKUP(Table10[[#This Row],[NAME]],Aggregate!$P:$AA,11,FALSE()),"") -> 11 | M82: =Aggregate!P82 -> LeQuint Allen Jr. | N82: =VLOOKUP(Table10[[#This Row],[NAME]],Aggregate!P:AA,4,FALSE()) -> JAC/7 | O82: =IFERROR(VLOOKUP(Table10[[#This Row],[NAME]],Aggregate!$P:$AA,8,FALSE()),"") -> 25.885294 | P82: =IF(Scoring!$K$6="Auction",IFERROR(VLOOKUP(Table10[[#This Row],[NAME]],Aggregate!$P:$AA,10,FALSE()),""),IFERROR(VLOOKUP(Table10[[#This Row],[NAME]],Aggregate!$P:$AA,9,FALSE()),"")) -> -101.66044 | Q82: =SUMIFS(T83:$T$84,S83:$S$84,"<>x",S83:$S$84,"<>o",T83:$T$84,">0")/Aggregate!$X$1 -> 0 | R82: =VLOOKUP(Table10[[#This Row],[NAME]],ECR!C:E,3,FALSE()) -> RB80 | T82: =VLOOKUP(M82,Aggregate!P:X,9,FALSE()) -> -101.66044 | V82: =IFERROR(VLOOKUP(Table11[[#This Row],[NAME]],Aggregate!$AD:$AO,11,FALSE()),"") -> 9 | W82: =Aggregate!AD68 -> Ryan Flournoy | X82: =VLOOKUP(Table11[[#This Row],[NAME]],Aggregate!AD:AO,4,FALSE()) -> DAL/14 | Y82: =IFERROR(VLOOKUP(Table11[[#This Row],[NAME]],Aggregate!$AD:$AO,8,FALSE()),"") -> 67.712164 | Z82: =IF(Scoring!$K$6="Auction",IFERROR(VLOOKUP(Table11[[#This Row],[NAME]],Aggregate!$AD:$AO,10,FALSE()),""),IFERROR(VLOOKUP(Table11[[#This Row],[NAME]],Aggregate!$AD:$AO,9,FALSE()),"")) -> -57.965715 | AA82: =SUMIFS(AD$83:$AD84,AC$83:$AC84,"<>x",AC$83:$AC84,"<>o",AD$83:$AD84,">0")/Aggregate!$AL$1 -> 0 | AB82: =VLOOKUP(Table11[[#This Row],[NAME]],ECR!C:E,3,FALSE()) -> WR66 | AD82: =VLOOKUP(W82,Aggregate!AD:AL,9,FALSE()) -> -57.965715
B83: =IFERROR(VLOOKUP(Table12[[#This Row],[NAME]],Aggregate!$AR:$BC,11,FALSE()),"") -> 9 | C83: =Aggregate!AR36 -> Theo Johnson | D83: =VLOOKUP(Table12[[#This Row],[NAME]],Aggregate!AR:BD,4,FALSE()) -> NYG/8 | E83: =IFERROR(VLOOKUP($C83,Aggregate!$AR:$BC,8,FALSE()),"") -> 51.908235 | F83: =IF(Scoring!$K$6="Auction",IFERROR(VLOOKUP($C83,Aggregate!$AR:$BC,10,FALSE()),""),IFERROR(VLOOKUP($C83,Aggregate!$AR:$BC,9,FALSE()),"")) -> -60.665362 | G83: =SUMIFS(J83:$J$85,I83:$I$85,"<>x",I83:$I$85,"<>o",J83:$J$85,">0")/Aggregate!$AZ$1 -> 0 | H83: =VLOOKUP(Table12[[#This Row],[NAME]],ECR!C:E,3,FALSE()) -> TE34 | J83: =VLOOKUP(C83,Aggregate!AR:AZ,9,FALSE()) -> -60.665362 | L83: =IFERROR(VLOOKUP(Table10[[#This Row],[NAME]],Aggregate!$P:$AA,11,FALSE()),"") -> 11 | M83: =Aggregate!P78 -> Ollie Gordon II | N83: =VLOOKUP(Table10[[#This Row],[NAME]],Aggregate!P:AA,4,FALSE()) -> MIA/6 | O83: =IFERROR(VLOOKUP(Table10[[#This Row],[NAME]],Aggregate!$P:$AA,8,FALSE()),"") -> 22.270784 | P83: =IF(Scoring!$K$6="Auction",IFERROR(VLOOKUP(Table10[[#This Row],[NAME]],Aggregate!$P:$AA,10,FALSE()),""),IFERROR(VLOOKUP(Table10[[#This Row],[NAME]],Aggregate!$P:$AA,9,FALSE()),"")) -> -105.27495 | Q83: =SUMIFS(T84:$T$84,S84:$S$84,"<>x",S84:$S$84,"<>o",T84:$T$84,">0")/Aggregate!$X$1 -> 0 | R83: =VLOOKUP(Table10[[#This Row],[NAME]],ECR!C:E,3,FALSE()) -> RB76 | T83: =VLOOKUP(M83,Aggregate!P:X,9,FALSE()) -> -105.27495 | V83: =IFERROR(VLOOKUP(Table11[[#This Row],[NAME]],Aggregate!$AD:$AO,11,FALSE()),"") -> 9 | W83: =Aggregate!AD70 -> Tre' Harris | X83: =VLOOKUP(Table11[[#This Row],[NAME]],Aggregate!AD:AO,4,FALSE()) -> LAC/7 | Y83: =IFERROR(VLOOKUP(Table11[[#This Row],[NAME]],Aggregate!$AD:$AO,8,FALSE()),"") -> 67.002477 | Z83: =IF(Scoring!$K$6="Auction",IFERROR(VLOOKUP(Table11[[#This Row],[NAME]],Aggregate!$AD:$AO,10,FALSE()),""),IFERROR(VLOOKUP(Table11[[#This Row],[NAME]],Aggregate!$AD:$AO,9,FALSE()),"")) -> -58.675402 | AA83: =SUMIFS(AD84:$AD$84,AC84:$AC$84,"<>x",AC84:$AC$84,"<>o",AD84:$AD$84,">0")/Aggregate!$AL$1 -> 0 | AB83: =VLOOKUP(Table11[[#This Row],[NAME]],ECR!C:E,3,FALSE()) -> WR68 | AD83: =VLOOKUP(W83,Aggregate!AD:AL,9,FALSE()) -> -58.675402
B84: =IFERROR(VLOOKUP(Table12[[#This Row],[NAME]],Aggregate!$AR:$BC,11,FALSE()),"") -> 10 | C84: =Aggregate!AR37 -> Eli Stowers | D84: =VLOOKUP(Table12[[#This Row],[NAME]],Aggregate!AR:BD,4,FALSE()) -> PHI/10 | E84: =IFERROR(VLOOKUP($C84,Aggregate!$AR:$BC,8,FALSE()),"") -> 38.249314 | F84: =IF(Scoring!$K$6="Auction",IFERROR(VLOOKUP($C84,Aggregate!$AR:$BC,10,FALSE()),""),IFERROR(VLOOKUP($C84,Aggregate!$AR:$BC,9,FALSE()),"")) -> -74.324284 | G84: =SUMIFS(J84:$J$85,I84:$I$85,"<>x",I84:$I$85,"<>o",J84:$J$85,">0")/Aggregate!$AZ$1 -> 0 | H84: =VLOOKUP(Table12[[#This Row],[NAME]],ECR!C:E,3,FALSE()) -> TE35 | J84: =VLOOKUP(C84,Aggregate!AR:AZ,9,FALSE()) -> -74.324284 | L84: =IFERROR(VLOOKUP(Table10[[#This Row],[NAME]],Aggregate!$P:$AA,11,FALSE()),"") -> 11 | M84: =Aggregate!P77 -> Kaleb Johnson | N84: =VLOOKUP(Table10[[#This Row],[NAME]],Aggregate!P:AA,4,FALSE()) -> GB/11 | O84: =IFERROR(VLOOKUP(Table10[[#This Row],[NAME]],Aggregate!$P:$AA,8,FALSE()),"") -> 15.793725 | P84: =IF(Scoring!$K$6="Auction",IFERROR(VLOOKUP(Table10[[#This Row],[NAME]],Aggregate!$P:$AA,10,FALSE()),""),IFERROR(VLOOKUP(Table10[[#This Row],[NAME]],Aggregate!$P:$AA,9,FALSE()),"")) -> -111.75201 | Q84: =SUMIFS(T$84:$T85,S$84:$S85,"<>x",S$84:$S85,"<>o",T$84:$T85,">0")/Aggregate!$X$1 -> 0 | R84: =VLOOKUP(Table10[[#This Row],[NAME]],ECR!C:E,3,FALSE()) -> RB75 | T84: =VLOOKUP(M84,Aggregate!P:X,9,FALSE()) -> -111.75201 | V84: =IFERROR(VLOOKUP(Table11[[#This Row],[NAME]],Aggregate!$AD:$AO,11,FALSE()),"") -> 9 | W84: =Aggregate!AD69 -> Pat Bryant | X84: =VLOOKUP(Table11[[#This Row],[NAME]],Aggregate!AD:AO,4,FALSE()) -> DEN/10 | Y84: =IFERROR(VLOOKUP(Table11[[#This Row],[NAME]],Aggregate!$AD:$AO,8,FALSE()),"") -> 60.341427 | Z84: =IF(Scoring!$K$6="Auction",IFERROR(VLOOKUP(Table11[[#This Row],[NAME]],Aggregate!$AD:$AO,10,FALSE()),""),IFERROR(VLOOKUP(Table11[[#This Row],[NAME]],Aggregate!$AD:$AO,9,FALSE()),"")) -> -65.336452 | AA84: =SUMIFS(AD84:$AD$85,AC84:$AC$85,"<>x",AC84:$AC$85,"<>o",AD84:$AD$85,">0")/Aggregate!$AL$1 -> 0 | AB84: =VLOOKUP(Table11[[#This Row],[NAME]],ECR!C:E,3,FALSE()) -> WR67 | AD84: =VLOOKUP(W84,Aggregate!AD:AL,9,FALSE()) -> -65.336452

Sheet Aggregate
A1: Baseline: | B1: =Scoring!B43 -> 12 | C1: =MAX(LARGE(I3:I50, $B$1),Q1,AE1,AS1) -> 268.37937 | J1: =SUMIF(Table2[VBD],">0") -> 138.95841 | O1: Baseline: | P1: =Scoring!C43 -> 31 | Q1: =LARGE($W$3:$W$102,P1) -> 127.54574 | X1: =SUMIF(Table4[VBD],">0") -> 1851.3161 | AC1: Baseline: | AD1: =Scoring!D43 -> 33 | AE1: =LARGE(Table6[Zscore Projection],AD1) -> 125.67788 | AL1: =SUMIF(Table6[VBD],">0") -> 1394.0311 | AQ1: Baseline: | AR1: =Scoring!E43 -> 12 | AS1: =IF(AR1=0,AE1,LARGE($AY$3:$AY$202,AR1)) -> 112.5736 | AZ1: =SUMIF(Table7[VBD],">0") -> 237.15508
B2: PLAYER | C2: Team | D2: Bye | E2: Team/Bye | F2: LOW | G2: AVG | H2: HIGH | I2: Zscore Projection | J2: VBD | K2: Auc | L2: Tier | M2: Missed Games | P2: PLAYER | Q2: Team | R2: Bye | S2: Team/Bye | T2: LOW | U2: AVG | V2: HIGH | W2: Zscore Projection | X2: VBD | Y2: Auction | Z2: Tier | AA2: Missed Games | AD2: PLAYER | AE2: Team | AF2: Bye | AG2: Team/Bye | AH2: LOW | AI2: AVG | AJ2: HIGH | AK2: Zscore Projection | AL2: VBD | AM2: Auction | AN2: Tier | AO2: Missed Games | AR2: PLAYER | AS2: Team | AT2: Bye | AU2: Team/Bye | AV2: LOW | AW2: AVG | AX2: HIGH | AY2: Zscore Projection | AZ2: VBD | BA2: Auction | BB2: Tier | BC2: Missed Games | BD2: V/R | BF2: QBRank | BG2: QBPts | BH2: QB | BI2: QBTier | BJ2: Tier | BK2: RBRank | BL2: RBPts | BM2: RB | BN2: RB Tier | BO2: Tier | BP2: WRRank | BQ2: WRPts | BR2: WR | BS2: WRTier | BT2: Tier | BU2: TERank | BV2: TEPts | BW2: TE | BX2: TETier | BY2: Tier
A3: QB1 | B3: =VLOOKUP(A3,ECR!E:L,8,FALSE()) -> Josh Allen | C3: =IFERROR(VLOOKUP(Table2[[#This Row],[PLAYER]],ECR!C:F,2,FALSE()),"-") -> BUF | D3: =IFERROR(VLOOKUP(Table2[[#This Row],[PLAYER]],ECR!C:F,4,FALSE()),"-") -> 7 | E3: =Table2[[#This Row],[Team]] & "/" & Table2[[#This Row],[Bye]] -> BUF/7 | F3: =IFERROR(VLOOKUP(Table2[[#This Row],[PLAYER]],QB!A:Q,15,FALSE())/17*(17-Table2[[#This Row],[Missed Games]]),0) -> 304.17057 | G3: =IFERROR(VLOOKUP(Table2[[#This Row],[PLAYER]],QB!A:Q,16,FALSE())/17*(17-Table2[[#This Row],[Missed Games]]),0) -> 324.54666 | H3: =IFERROR(VLOOKUP(Table2[[#This Row],[PLAYER]],QB!A:Q,17,FALSE())/17*(17-Table2[[#This Row],[Missed Games]]),0) -> 347.51046 | I3: =AVERAGE(AVERAGE(Table2[[#This Row],[LOW]],Table2[[#This Row],[HIGH]]),Table2[[#This Row],[AVG]],VLOOKUP(Table2[[#This Row],[PLAYER]],ECR!L:N,3,FALSE())) -> 324.97794 | J3: =Table2[[#This Row],[Zscore Projection]]-$C$1 -> 56.598576 | K3: =MAX(Table2[[#This Row],[VBD]]*Scoring!$B$48+1,1) -> #VALUE! | L3: =VLOOKUP(Table2[[#This Row],[VBD]],BH:BJ,3,FALSE()) -> 1 | M3: =VLOOKUP(INDEX(ECR!$E:$E,MATCH(B3,ECR!$C:$C,0)),RISK!A:B,2,FALSE()) -> 2.118 | O3: RB1 | P3: =VLOOKUP(O3,ECR!E:L,8,FALSE()) -> Jahmyr Gibbs | Q3: =IFERROR(VLOOKUP(Table4[[#This Row],[PLAYER]],ECR!C:F,2,FALSE()),"-") -> DET | R3: =IFERROR(VLOOKUP(Table4[[#This Row],[PLAYER]],ECR!C:F,4,FALSE()),"-") -> 6 | S3: =Table4[[#This Row],[Team]] & "/" & Table4[[#This Row],[Bye]] -> DET/6 | T3: =IFERROR(VLOOKUP(Table4[[#This Row],[PLAYER]],RB!A:Q,13,FALSE())/17*(17-Table4[[#This Row],[Missed Games]]),0) -> 269.75536 | U3: =IFERROR(VLOOKUP(Table4[[#This Row],[PLAYER]],RB!A:Q,14,FALSE())/17*(17-Table4[[#This Row],[Missed Games]]),0) -> 291.33477 | V3: =IFERROR(VLOOKUP(Table4[[#This Row],[PLAYER]],RB!A:Q,15,FALSE())/17*(17-Table4[[#This Row],[Missed Games]]),0) -> 313.02467 | W3: =AVERAGE(AVERAGE(Table4[[#This Row],[LOW]],Table4[[#This Row],[HIGH]]),Table4[[#This Row],[AVG]],VLOOKUP(Table4[[#This Row],[PLAYER]],ECR!L:N,3,FALSE())) -> 291.35319 | X3: =Table4[[#This Row],[Zscore Projection]]-$Q$1 -> 163.80745 | Y3: =MAX(Table4[[#This Row],[VBD]]*Scoring!$B$48+1,1) -> #VALUE! | Z3: =VLOOKUP(Table4[[#This Row],[VBD]],BM:BO,3,FALSE()) -> 1 | AA3: =VLOOKUP(INDEX(ECR!$E:$E,MATCH(P3,ECR!$C:$C,0)),RISK!A:B,2,FALSE()) -> 2.5514 | AC3: WR1 | AD3: =VLOOKUP(AC3,ECR!E:L,8,FALSE()) -> Ja'Marr Chase | AE3: =IFERROR(VLOOKUP(Table6[[#This Row],[PLAYER]],ECR!C:F,2,FALSE()),"-") -> CIN | AF3: =IFERROR(VLOOKUP(Table6[[#This Row],[PLAYER]],ECR!C:F,4,FALSE()),"-") -> 6 | AG3: =Table6[[#This Row],[Team]] & "/" & Table6[[#This Row],[Bye]] -> CIN/6 | AH3: =IFERROR(VLOOKUP(Table6[[#This Row],[PLAYER]],WR!A:Q,13,FALSE())/17*(17-Table6[[#This Row],[Missed Games]]),0) -> 235.99468 | AI3: =IFERROR(VLOOKUP(Table6[[#This Row],[PLAYER]],WR!A:Q,14,FALSE())/17*(17-Table6[[#This Row],[Missed Games]]),0) -> 245.44339 | AJ3: =IFERROR(VLOOKUP(Table6[[#This Row],[PLAYER]],WR!A:Q,15,FALSE())/17*(17-Table6[[#This Row],[Missed Games]]),0) -> 255.16869 | AK3: =AVERAGE(AVERAGE(Table6[[#This Row],[LOW]],Table6[[#This Row],[HIGH]]),Table6[[#This Row],[AVG]],VLOOKUP(Table6[[#This Row],[PLAYER]],ECR!L:N,3,FALSE())) -> 246.79195 | AL3: =Table6[[#This Row],[Zscore Projection]]-$AE$1 -> 121.11407 | AM3: =MAX(Table6[[#This Row],[VBD]]*Scoring!$B$48+1,1) -> #VALUE! | AN3: =VLOOKUP(Table6[[#This Row],[VBD]],BR:BT,3,FALSE()) -> 1 | AO3: =VLOOKUP(INDEX(ECR!$E:$E,MATCH(AD3,ECR!$C:$C,0)),RISK!A:B,2,FALSE()) -> 1.8321 | AQ3: TE1 | AR3: =VLOOKUP(AQ3,ECR!E:L,8,FALSE()) -> Brock Bowers | AS3: =IFERROR(VLOOKUP(Table7[[#This Row],[PLAYER]],ECR!C:F,2,FALSE()),"-") -> LV | AT3: =IFERROR(VLOOKUP(Table7[[#This Row],[PLAYER]],ECR!C:F,4,FALSE()),"-") -> 13 | AU3: =Table7[[#This Row],[Team]] & "/" & Table7[[#This Row],[Bye]] -> LV/13 | AV3: =IFERROR(VLOOKUP(Table7[[#This Row],[PLAYER]],TE!A:K,9,FALSE())/17*(17-Table7[[#This Row],[Missed Games]]),0) -> 160.9598 | AW3: =IFERROR(VLOOKUP(Table7[[#This Row],[PLAYER]],TE!A:K,10,FALSE())/17*(17-Table7[[#This Row],[Missed Games]]),0) -> 173.58239 | AX3: =IFERROR(VLOOKUP(Table7[[#This Row],[PLAYER]],TE!A:K,11,FALSE())/17*(17-Table7[[#This Row],[Missed Games]]),0) -> 186.55319 | AY3: =AVERAGE(AVERAGE(Table7[[#This Row],[LOW]],Table7[[#This Row],[HIGH]]),Table7[[#This Row],[AVG]],VLOOKUP(Table7[[#This Row],[PLAYER]],ECR!L:N,3,FALSE())) -> 173.64043 | AZ3: =Table7[[#This Row],[Zscore Projection]]-$AS$1 -> 61.066829 | BA3: =MAX(Table7[[#This Row],[VBD]]*Scoring!$B$48+1,1) -> #VALUE! | BB3: =VLOOKUP(Table7[[#This Row],[VBD]],BW:BY,3,FALSE()) -> 1 | BC3: =VLOOKUP(INDEX(ECR!$E:$E,MATCH(AR3,ECR!$C:$C,0)),RISK!A:B,2,FALSE()) -> 2.2011 | BF3: 1 | BG3: =IFERROR(LARGE($G$3:$G$52,BF3),"") -> 324.54666 | BH3: =IFERROR(LARGE($J$3:$J$52,1),"") -> 56.598576 | BI3: =BH3 -> 56.598576 | BJ3: 1 | BK3: 1 | BL3: =IFERROR(LARGE($U$3:$U$102,BK3),"") -> 291.33477 | BM3: =IFERROR(LARGE($X$3:$X$102,1),"") -> 163.80745 | BN3: =BM3 -> 163.80745 | BO3: 1 | BP3: 1 | BQ3: =IFERROR(LARGE($AI$3:$AI$102,BP3),"") -> 249.35076 | BR3: =IFERROR(LARGE($AL$3:$AL$102,1),"") -> 122.75536 | BS3: =BR3 -> 122.75536 | BT3: 1 | BU3: 1 | BV3: =IFERROR(LARGE($AW$3:$AW$52,BU3),"") -> 173.58239 | BW3: =IFERROR(LARGE($AZ$3:$AZ$52,1),"") -> 61.066829 | BX3: =BW3 -> 61.066829 | BY3: 1
A4: QB2 | B4: =VLOOKUP(A4,ECR!E:L,8,FALSE()) -> Lamar Jackson | C4: =IFERROR(VLOOKUP(Table2[[#This Row],[PLAYER]],ECR!C:F,2,FALSE()),"-") -> BAL | D4: =IFERROR(VLOOKUP(Table2[[#This Row],[PLAYER]],ECR!C:F,4,FALSE()),"-") -> 13 | E4: =Table2[[#This Row],[Team]] & "/" & Table2[[#This Row],[Bye]] -> BAL/13 | F4: =IFERROR(VLOOKUP(Table2[[#This Row],[PLAYER]],QB!A:Q,15,FALSE())/17*(17-Table2[[#This Row],[Missed Games]]),0) -> 261.35495 | G4: =IFERROR(VLOOKUP(Table2[[#This Row],[PLAYER]],QB!A:Q,16,FALSE())/17*(17-Table2[[#This Row],[Missed Games]]),0) -> 285.19296 | H4: =IFERROR(VLOOKUP(Table2[[#This Row],[PLAYER]],QB!A:Q,17,FALSE())/17*(17-Table2[[#This Row],[Missed Games]]),0) -> 317.03614 | I4: =AVERAGE(AVERAGE(Table2[[#This Row],[LOW]],Table2[[#This Row],[HIGH]]),Table2[[#This Row],[AVG]],VLOOKUP(Table2[[#This Row],[PLAYER]],ECR!L:N,3,FALSE())) -> 286.78631 | J4: =Table2[[#This Row],[Zscore Projection]]-$C$1 -> 18.406947 | K4: =MAX(Table2[[#This Row],[VBD]]*Scoring!$B$48+1,1) -> #VALUE! | L4: =VLOOKUP(Table2[[#This Row],[VBD]],BH:BJ,3,FALSE()) -> 2 | M4: =VLOOKUP(INDEX(ECR!$E:$E,MATCH(B4,ECR!$C:$C,0)),RISK!A:B,2,FALSE()) -> 2.0584 | O4: RB2 | P4: =VLOOKUP(O4,ECR!E:L,8,FALSE()) -> Bijan Robinson | Q4: =IFERROR(VLOOKUP(Table4[[#This Row],[PLAYER]],ECR!C:F,2,FALSE()),"-") -> ATL | R4: =IFERROR(VLOOKUP(Table4[[#This Row],[PLAYER]],ECR!C:F,4,FALSE()),"-") -> 11 | S4: =Table4[[#This Row],[Team]] & "/" & Table4[[#This Row],[Bye]] -> ATL/11 | T4: =IFERROR(VLOOKUP(Table4[[#This Row],[PLAYER]],RB!A:Q,13,FALSE())/17*(17-Table4[[#This Row],[Missed Games]]),0) -> 261.154 | U4: =IFERROR(VLOOKUP(Table4[[#This Row],[PLAYER]],RB!A:Q,14,FALSE())/17*(17-Table4[[#This Row],[Missed Games]]),0) -> 270.572 | V4: =IFERROR(VLOOKUP(Table4[[#This Row],[PLAYER]],RB!A:Q,15,FALSE())/17*(17-Table4[[#This Row],[Missed Games]]),0) -> 278.6045 | W4: =AVERAGE(AVERAGE(Table4[[#This Row],[LOW]],Table4[[#This Row],[HIGH]]),Table4[[#This Row],[AVG]],VLOOKUP(Table4[[#This Row],[PLAYER]],ECR!L:N,3,FALSE())) -> 270.34108 | X4: =Table4[[#This Row],[Zscore Projection]]-$Q$1 -> 142.79534 | Y4: =MAX(Table4[[#This Row],[VBD]]*Scoring!$B$48+1,1) -> #VALUE! | Z4: =VLOOKUP(Table4[[#This Row],[VBD]],BM:BO,3,FALSE()) -> 1 | AA4: =VLOOKUP(INDEX(ECR!$E:$E,MATCH(P4,ECR!$C:$C,0)),RISK!A:B,2,FALSE()) -> 2.55 | AC4: WR2 | AD4: =VLOOKUP(AC4,ECR!E:L,8,FALSE()) -> Puka Nacua | AE4: =IFERROR(VLOOKUP(Table6[[#This Row],[PLAYER]],ECR!C:F,2,FALSE()),"-") -> LAR | AF4: =IFERROR(VLOOKUP(Table6[[#This Row],[PLAYER]],ECR!C:F,4,FALSE()),"-") -> 11 | AG4: =Table6[[#This Row],[Team]] & "/" & Table6[[#This Row],[Bye]] -> LAR/11 | AH4: =IFERROR(VLOOKUP(Table6[[#This Row],[PLAYER]],WR!A:Q,13,FALSE())/17*(17-Table6[[#This Row],[Missed Games]]),0) -> 247.75179 | AI4: =IFERROR(VLOOKUP(Table6[[#This Row],[PLAYER]],WR!A:Q,14,FALSE())/17*(17-Table6[[#This Row],[Missed Games]]),0) -> 249.35076 | AJ4: =IFERROR(VLOOKUP(Table6[[#This Row],[PLAYER]],WR!A:Q,15,FALSE())/17*(17-Table6[[#This Row],[Missed Games]]),0) -> 253.25936 | AK4: =AVERAGE(AVERAGE(Table6[[#This Row],[LOW]],Table6[[#This Row],[HIGH]]),Table6[[#This Row],[AVG]],VLOOKUP(Table6[[#This Row],[PLAYER]],ECR!L:N,3,FALSE())) -> 248.43324 | AL4: =Table6[[#This Row],[Zscore Projection]]-$AE$1 -> 122.75536 | AM4: =MAX(Table6[[#This Row],[VBD]]*Scoring!$B$48+1,1) -> #VALUE! | AN4: =VLOOKUP(Table6[[#This Row],[VBD]],BR:BT,3,FALSE()) -> 1 | AO4: =VLOOKUP(INDEX(ECR!$E:$E,MATCH(AD4,ECR!$C:$C,0)),RISK!A:B,2,FALSE()) -> 1.8986 | AQ4: TE2 | AR4: =VLOOKUP(AQ4,ECR!E:L,8,FALSE()) -> Trey McBride | AS4: =IFERROR(VLOOKUP(Table7[[#This Row],[PLAYER]],ECR!C:F,2,FALSE()),"-") -> ARI | AT4: =IFERROR(VLOOKUP(Table7[[#This Row],[PLAYER]],ECR!C:F,4,FALSE()),"-") -> 14 | AU4: =Table7[[#This Row],[Team]] & "/" & Table7[[#This Row],[Bye]] -> ARI/14 | AV4: =IFERROR(VLOOKUP(Table7[[#This Row],[PLAYER]],TE!A:K,9,FALSE())/17*(16-Table7[[#This Row],[Missed Games]]),0) -> 151.12762 | AW4: =IFERROR(VLOOKUP(Table7[[#This Row],[PLAYER]],TE!A:K,10,FALSE())/17*(16-Table7[[#This Row],[Missed Games]]),0) -> 164.73139 | AX4: =IFERROR(VLOOKUP(Table7[[#This Row],[PLAYER]],TE!A:K,11,FALSE())/17*(16-Table7[[#This Row],[Missed Games]]),0) -> 178.82509 | AY4: =AVERAGE(AVERAGE(Table7[[#This Row],[LOW]],Table7[[#This Row],[HIGH]]),Table7[[#This Row],[AVG]],VLOOKUP(Table7[[#This Row],[PLAYER]],ECR!L:N,3,FALSE())) -> 164.81305 | AZ4: =Table7[[#This Row],[Zscore Projection]]-$AS$1 -> 52.239448 | BA4: =MAX(Table7[[#This Row],[VBD]]*Scoring!$B$48+1,1) -> #VALUE! | BB4: =VLOOKUP(Table7[[#This Row],[VBD]],BW:BY,3,FALSE()) -> 1 | BC4: =VLOOKUP(INDEX(ECR!$E:$E,MATCH(AR4,ECR!$C:$C,0)),RISK!A:B,2,FALSE()) -> 2.1186 | BF4: 2 | BG4: =IFERROR(LARGE($G$3:$G$52,BF4),"") -> 285.97044 | BH4: =IFERROR(LARGE($J$3:$J$52,2),"") -> 18.406947 | BI4: =IF(BH4="",BI3,IF((BI3-BH4)>0.2*LARGE($J$3:$J$52,2),BH4,BI3)) -> 18.406947 | BJ4: =MIN(IF(BH4="",BJ3,IF((BI3-BH4)>0.2*LARGE($J$3:$J$52,2),BJ3+1,BJ3)),15) -> 2 | BK4: 2 | BL4: =IFERROR(LARGE($U$3:$U$102,BK4),"") -> 270.572 | BM4: =IFERROR(LARGE($X$3:$X$102,2),"") -> 142.79534 | BN4: =IF(BM4="",BN3,IF((BN3-BM4)>0.15*LARGE($X$3:$X$102,2),BM4,BN3)) -> 163.80745 | BO4: =IF(BM4="",BO3,IF((BN3-BM4)>0.15*LARGE($X$3:$X$102,2),BO3+1,BO3)) -> 1 | BP4: 2 | BQ4: =IFERROR(LARGE($AI$3:$AI$102,BP4),"") -> 245.44339 | BR4: =IFERROR(LARGE($AL$3:$AL$102,2),"") -> 121.11407 | BS4: =IF(BR4="",BS3,IF((BS3-BR4)>0.15*LARGE($AL$3:$AL$102,2),BR4,BS3)) -> 122.75536 | BT4: =IF(BR4="",BT3,IF((BS3-BR4)>0.15*LARGE($AL$3:$AL$102,2),BT3+1,BT3)) -> 1 | BU4: 2 | BV4: =IFERROR(LARGE($AW$3:$AW$52,BU4),"") -> 164.73139 | BW4: =IFERROR(LARGE($AZ$3:$AZ$52,2),"") -> 52.239448 | BX4: =IF(BW4="",BX3,IF((BX3-BW4)>0.2*LARGE($AZ$3:$AZ$52,2),BW4,BX3)) -> 61.066829 | BY4: =IF(BW4="",BY3,IF((BX3-BW4)>0.2*LARGE($AZ$3:$AZ$52,2),BY3+1,BY3)) -> 1
A5: QB3 | B5: =VLOOKUP(A5,ECR!E:L,8,FALSE()) -> Drake Maye | C5: =IFERROR(VLOOKUP(Table2[[#This Row],[PLAYER]],ECR!C:F,2,FALSE()),"-") -> NE | D5: =IFERROR(VLOOKUP(Table2[[#This Row],[PLAYER]],ECR!C:F,4,FALSE()),"-") -> 11 | E5: =Table2[[#This Row],[Team]] & "/" & Table2[[#This Row],[Bye]] -> NE/11 | F5: =IFERROR(VLOOKUP(Table2[[#This Row],[PLAYER]],QB!A:Q,15,FALSE())/17*(17-Table2[[#This Row],[Missed Games]]),0) -> 265.4077 | G5: =IFERROR(VLOOKUP(Table2[[#This Row],[PLAYER]],QB!A:Q,16,FALSE())/17*(17-Table2[[#This Row],[Missed Games]]),0) -> 283.0263 | H5: =IFERROR(VLOOKUP(Table2[[#This Row],[PLAYER]],QB!A:Q,17,FALSE())/17*(17-Table2[[#This Row],[Missed Games]]),0) -> 295.09302 | I5: =AVERAGE(AVERAGE(Table2[[#This Row],[LOW]],Table2[[#This Row],[HIGH]]),Table2[[#This Row],[AVG]],VLOOKUP(Table2[[#This Row],[PLAYER]],ECR!L:N,3,FALSE())) -> 282.82321 | J5: =Table2[[#This Row],[Zscore Projection]]-$C$1 -> 14.443841 | K5: =MAX(Table2[[#This Row],[VBD]]*Scoring!$B$48+1,1) -> #VALUE! | L5: =VLOOKUP(Table2[[#This Row],[VBD]],BH:BJ,3,FALSE()) -> 3 | M5: =VLOOKUP(INDEX(ECR!$E:$E,MATCH(B5,ECR!$C:$C,0)),RISK!A:B,2,FALSE()) -> 2.0092 | O5: RB3 | P5: =VLOOKUP(O5,ECR!E:L,8,FALSE()) -> Jonathan Taylor | Q5: =IFERROR(VLOOKUP(Table4[[#This Row],[PLAYER]],ECR!C:F,2,FALSE()),"-") -> IND | R5: =IFERROR(VLOOKUP(Table4[[#This Row],[PLAYER]],ECR!C:F,4,FALSE()),"-") -> 13 | S5: =Table4[[#This Row],[Team]] & "/" & Table4[[#This Row],[Bye]] -> IND/13 | T5: =IFERROR(VLOOKUP(Table4[[#This Row],[PLAYER]],RB!A:Q,13,FALSE())/17*(17-Table4[[#This Row],[Missed Games]]),0) -> 225.84813 | U5: =IFERROR(VLOOKUP(Table4[[#This Row],[PLAYER]],RB!A:Q,14,FALSE())/17*(17-Table4[[#This Row],[Missed Games]]),0) -> 246.82642 | V5: =IFERROR(VLOOKUP(Table4[[#This Row],[PLAYER]],RB!A:Q,15,FALSE())/17*(17-Table4[[#This Row],[Missed Games]]),0) -> 273.22778 | W5: =AVERAGE(AVERAGE(Table4[[#This Row],[LOW]],Table4[[#This Row],[HIGH]]),Table4[[#This Row],[AVG]],VLOOKUP(Table4[[#This Row],[PLAYER]],ECR!L:N,3,FALSE())) -> 249.19215 | X5: =Table4[[#This Row],[Zscore Projection]]-$Q$1 -> 121.64642 | Y5: =MAX(Table4[[#This Row],[VBD]]*Scoring!$B$48+1,1) -> #VALUE! | Z5: =VLOOKUP(Table4[[#This Row],[VBD]],BM:BO,3,FALSE()) -> 2 | AA5: =VLOOKUP(INDEX(ECR!$E:$E,MATCH(P5,ECR!$C:$C,0)),RISK!A:B,2,FALSE()) -> 2.5498 | AC5: WR3 | AD5: =VLOOKUP(AC5,ECR!E:L,8,FALSE()) -> Jaxon Smith-Njigba | AE5: =IFERROR(VLOOKUP(Table6[[#This Row],[PLAYER]],ECR!C:F,2,FALSE()),"-") -> SEA | AF5: =IFERROR(VLOOKUP(Table6[[#This Row],[PLAYER]],ECR!C:F,4,FALSE()),"-") -> 11 | AG5: =Table6[[#This Row],[Team]] & "/" & Table6[[#This Row],[Bye]] -> SEA/11 | AH5: =IFERROR(VLOOKUP(Table6[[#This Row],[PLAYER]],WR!A:Q,13,FALSE())/17*(17-Table6[[#This Row],[Missed Games]]),0) -> 223.51597 | AI5: =IFERROR(VLOOKUP(Table6[[#This Row],[PLAYER]],WR!A:Q,14,FALSE())/17*(17-Table6[[#This Row],[Missed Games]]),0) -> 239.22365 | AJ5: =IFERROR(VLOOKUP(Table6[[#This Row],[PLAYER]],WR!A:Q,15,FALSE())/17*(17-Table6[[#This Row],[Missed Games]]),0) -> 259.98148 | AK5: =AVERAGE(AVERAGE(Table6[[#This Row],[LOW]],Table6[[#This Row],[HIGH]]),Table6[[#This Row],[AVG]],VLOOKUP(Table6[[#This Row],[PLAYER]],ECR!L:N,3,FALSE())) -> 240.06534 | AL5: =Table6[[#This Row],[Zscore Projection]]-$AE$1 -> 114.38746 | AM5: =MAX(Table6[[#This Row],[VBD]]*Scoring!$B$48+1,1) -> #VALUE! | AN5: =VLOOKUP(Table6[[#This Row],[VBD]],BR:BT,3,FALSE()) -> 1 | AO5: =VLOOKUP(INDEX(ECR!$E:$E,MATCH(AD5,ECR!$C:$C,0)),RISK!A:B,2,FALSE()) -> 1.9645 | AQ5: TE3 | AR5: =VLOOKUP(AQ5,ECR!E:L,8,FALSE()) -> Colston Loveland | AS5: =IFERROR(VLOOKUP(Table7[[#This Row],[PLAYER]],ECR!C:F,2,FALSE()),"-") -> CHI | AT5: =IFERROR(VLOOKUP(Table7[[#This Row],[PLAYER]],ECR!C:F,4,FALSE()),"-") -> 10 | AU5: =Table7[[#This Row],[Team]] & "/" & Table7[[#This Row],[Bye]] -> CHI/10 | AV5: =IFERROR(VLOOKUP(Table7[[#This Row],[PLAYER]],TE!A:K,9,FALSE())/17*(16-Table7[[#This Row],[Missed Games]]),0) -> 128.43587 | AW5: =IFERROR(VLOOKUP(Table7[[#This Row],[PLAYER]],TE!A:K,10,FALSE())/17*(16-Table7[[#This Row],[Missed Games]]),0) -> 141.38614 | AX5: =IFERROR(VLOOKUP(Table7[[#This Row],[PLAYER]],TE!A:K,11,FALSE())/17*(16-Table7[[#This Row],[Missed Games]]),0) -> 158.88296 | AY5: =AVERAGE(AVERAGE(Table7[[#This Row],[LOW]],Table7[[#This Row],[HIGH]]),Table7[[#This Row],[AVG]],VLOOKUP(Table7[[#This Row],[PLAYER]],ECR!L:N,3,FALSE())) -> 142.1439 | AZ5: =Table7[[#This Row],[Zscore Projection]]-$AS$1 -> 29.570303 | BA5: =MAX(Table7[[#This Row],[VBD]]*Scoring!$B$48+1,1) -> #VALUE! | BB5: =VLOOKUP(Table7[[#This Row],[VBD]],BW:BY,3,FALSE()) -> 2 | BC5: =VLOOKUP(INDEX(ECR!$E:$E,MATCH(AR5,ECR!$C:$C,0)),RISK!A:B,2,FALSE()) -> 2.0485 | BF5: 3 | BG5: =IFERROR(LARGE($G$3:$G$52,BF5),"") -> 285.19296 | BH5: =IFERROR(LARGE($J$3:$J$52,3),"") -> 15.933283 | BI5: =IF(BH5="",BI4,IF((BI4-BH5)>0.2*LARGE($J$3:$J$52,2),BH5,BI4)) -> 18.406947 | BJ5: =MIN(IF(BH5="",BJ4,IF((BI4-BH5)>0.2*LARGE($J$3:$J$52,2),BJ4+1,BJ4)),15) -> 2 | BK5: 3 | BL5: =IFERROR(LARGE($U$3:$U$102,BK5),"") -> 251.21209 | BM5: =IFERROR(LARGE($X$3:$X$102,3),"") -> 121.64642 | BN5: =IF(BM5="",BN4,IF((BN4-BM5)>0.15*LARGE($X$3:$X$102,2),BM5,BN4)) -> 121.64642 | BO5: =IF(BM5="",BO4,IF((BN4-BM5)>0.15*LARGE($X$3:$X$102,2),BO4+1,BO4)) -> 2 | BP5: 3 | BQ5: =IFERROR(LARGE($AI$3:$AI$102,BP5),"") -> 239.22365 | BR5: =IFERROR(LARGE($AL$3:$AL$102,3),"") -> 114.38746 | BS5: =IF(BR5="",BS4,IF((BS4-BR5)>0.15*LARGE($AL$3:$AL$102,2),BR5,BS4)) -> 122.75536 | BT5: =IF(BR5="",BT4,IF((BS4-BR5)>0.15*LARGE($AL$3:$AL$102,2),BT4+1,BT4)) -> 1 | BU5: 3 | BV5: =IFERROR(LARGE($AW$3:$AW$52,BU5),"") -> 141.38614 | BW5: =IFERROR(LARGE($AZ$3:$AZ$52,3),"") -> 29.570303 | BX5: =IF(BW5="",BX4,IF((BX4-BW5)>0.2*LARGE($AZ$3:$AZ$52,2),BW5,BX4)) -> 29.570303 | BY5: =IF(BW5="",BY4,IF((BX4-BW5)>0.2*LARGE($AZ$3:$AZ$52,2),BY4+1,BY4)) -> 2
